Workbook

Sheet Inputs
B2: ASSUMPTIONS & INPUTS
B4: CORE FINANCIAL ASSUMPTIONS
B5: Tax Rate | C5: 0.22 | D5: Corporate tax rate (Indonesia)
B6: Discount Rate (Base Case) | C6: 0.1 | D6: Weighted Average Cost of Capital
B7: Inflation Rate | C7: 0.0406 | D7: Annual inflation rate for ESL analysis
B8: Salvage Value % | C8: 0.9 | D8: Expected salvage value as % of original cost
B10: DEPRECIATION USEFUL LIFE SCENARIOS (Months)
B11: Baseline Useful Life | C11: 480 | D11: 40 years (current accounting policy)
B12: Conservative Useful Life | C12: 480 | D12: 40 years (conservative scenario)
B13: Realistic Useful Life | C13: 600 | D13: 50 years (recommended scenario)
B14: Optimistic Useful Life | C14: 900 | D14: 75 years (optimistic scenario)
B16: SENSITIVITY ANALYSIS PARAMETERS
B17: Discount Rate - Low | C17: 0.08 | D17: Lower bound for sensitivity analysis
B18: Discount Rate - High | C18: 0.12 | D18: Upper bound for sensitivity analysis
B19: Tax Rate - Low | C19: 0.2 | D19: Lower tax rate scenario
B20: Tax Rate - High | C20: 0.25 | D20: Higher tax rate scenario
B22: UNIT CONVERSION CONSTANTS
B23: Billion Scaling Factor | C23: 1000000000 | D23: Convert IDR to billions (÷ by this)
B24: Months Per Year | C24: 12 | D24: Convert monthly to annual (× by this)
B26: MAINTENANCE COST ESCALATION PARAMETERS
B27: Base Annual Maintenance Cost (IDR) | C27: =AVERAGE('Maintenance History'!D4:D37) -> 43288824 | D27: Historical average maintenance cost
B28: Baseline Escalation Rate (0-40 yrs) | C28: 0.04 | D28: Standard inflation-driven maintenance growth
B29: Medium Escalation Rate (40-50 yrs) | C29: 0.08 | D29: Increased maintenance for aging assets
B30: High Escalation Rate (50+ yrs) | C30: 0.12 | D30: Significant maintenance for extended life

Sheet Depreciation_Scenario_Analysis
B2: ASSET LIFE EXTENSION ANALYSIS
B3: Depreciation Scenario Comparison: Building Assets
B5: ASSUMPTIONS
B6: Analysis Period: | C6: 2025 - 2034
B7: Asset Class: | C7: Buildings (Bangunan)
B8: Historical Depreciation Locked: | C8: Through December 31, 2024
B9: Tax Rate: | C9: {=Inputs!C5} -> 0.22
B11: SCENARIO DEFINITIONS
B12: Scenario | C12: Useful Life (Months) | D12: Useful Life (Years) | E12: Description | F12: Color Code
B13: Baseline (Current) | C13: {=Inputs!C11} -> 480 | D13: =C13/Inputs!$C$24 -> 40 | E13: Current accounting policy - 40 year life | F13: Black
B14: Conservative | C14: {=Inputs!C12} -> 480 | D14: =C14/Inputs!$C$24 -> 40 | E14: No change from current policy | F14: Orange
B15: Realistic (Recommended) | C15: {=Inputs!C13} -> 600 | D15: =C15/Inputs!$C$24 -> 50 | E15: Extended to 50 years - industry standard | F15: Yellow
B16: Optimistic | C16: {=Inputs!C14} -> 900 | D16: =C16/Inputs!$C$24 -> 75 | E16: Extended to 75 years - maximum estimate | F16: Green
B18: BUILDING ASSETS - DETAIL
B19: No. | C19: Asset Description | D19: Acquisition Date | E19: Original Cost (IDR) | F19: Current Life (Months) | G19: Accum Depre 2024 (IDR) | H19: NBV 2024 (IDR) | I19: Monthly Depre (Current) | J19: Months Used Through 2024
B20: 1 | C20: {='Asset Data Pullman'!D221} -> Pembangunan Hotel Pullman Mandalika | D20: {='Asset Data Pullman'!F221} -> 44569 | E20: {='Asset Data Pullman'!G221} -> 533254574462 | F20: {='Asset Data Pullman'!H221} -> 480 | G20: {='Asset Data Pullman'!P221} -> -32217463874 | H20: =IFERROR(E20+G20,0) -> 501037110588 | I20: {='Asset Data Pullman'!I221} -> 1110947030 | J20: =IFERROR(IF(I20=0,0,ABS(G20/I20)),0) -> 29
B21: 2 | C21: {='Asset Data Pullman'!D222} -> Pembebanan Pekerjaan Noise Treatment Cooling Tower, PO-2023000193, 293/KONTRAK/ITDC.05-PROC/X/2023, Hotel Pullman; PT.Indocell Prima, Tahap 1 (50%), Tahap 2 (45%), Tahap 3 (5%), Progress 100% (18-10-2023) [PULLMAN] | D21: {='Asset Data Pullman'!F222} -> 13/11/2023 | E21: {='Asset Data Pullman'!G222} -> 2032700816 | F21: {='Asset Data Pullman'!H222} -> 240 | G21: {='Asset Data Pullman'!P222} -> -118574214 | H21: =IFERROR(E21+G21,0) -> 1914126602 | I21: {='Asset Data Pullman'!I222} -> 8469587 | J21: =IFERROR(IF(I21=0,0,ABS(G21/I21)),0) -> 14
B22: 3 | C22: {='Asset Data Pullman'!D223} -> Pembebanan Pembangunan Pagar Pembatas Garden Villa Pullman Lombok Merunjani Mandalika Beach Resort; 281/kontrak/itdc.05-proc/VIII/2024; PO-2024000192; Mandalika | D22: {='Asset Data Pullman'!F223} -> 45638 | E22: {='Asset Data Pullman'!G223} -> 152295416 | F22: {='Asset Data Pullman'!H223} -> 360 | G22: {='Asset Data Pullman'!P223} -> -423043 | H22: =IFERROR(E22+G22,0) -> 151872373 | I22: {='Asset Data Pullman'!I223} -> 423043 | J22: =IFERROR(IF(I22=0,0,ABS(G22/I22)),0) -> 1
B23: 4 | C23: {='Asset Data Pullman'!D224} -> Aktivir ke aset tetap bangunan, Hotel Pullman Tranche A | D23: {='Asset Data Pullman'!F224} -> 31/12/2024 | E23: {='Asset Data Pullman'!G224} -> - | F23: {='Asset Data Pullman'!H224} -> 360 | G23: {='Asset Data Pullman'!P224} -> - | H23: =IFERROR(E23+G23,0) -> 0 | I23: {='Asset Data Pullman'!I224} -> - | J23: =IFERROR(IF(I23=0,0,ABS(G23/I23)),0) -> 0
B24: 5 | C24: {='Asset Data Pullman'!D225} -> Adjustment Reklasifikasi, Pekerjaan Noise Treatment Cooling Tower, PO-2023000193, 293/KONTRAK/ITDC.05-PROC/X/2023, Hotel Pullman; PT.Indocell Prima ex. 00204/MEM-HO/11/23, 00264/MEM-HO/11/23, UM, 20% | D24: {='Asset Data Pullman'!F225} -> 13/11/2023 | E24: {='Asset Data Pullman'!G225} -> 1397481811 | F24: {='Asset Data Pullman'!H225} -> 240 | G24: {='Asset Data Pullman'!P225} -> -81519772 | H24: =IFERROR(E24+G24,0) -> 1315962039 | I24: {='Asset Data Pullman'!I225} -> 5822841 | J24: =IFERROR(IF(I24=0,0,ABS(G24/I24)),0) -> 14
B25: 6 | C25: {='Asset Data Pullman'!D226} -> Koreksi Audit 2024 - Aktivir Pekerjaan Hotel Pullman | D25: {='Asset Data Pullman'!F226} -> 24/12/2022 | E25: {='Asset Data Pullman'!G226} -> 10895403600 | F25: {='Asset Data Pullman'!H226} -> 360 | G25: {='Asset Data Pullman'!P226} -> -363180120 | H25: =IFERROR(E25+G25,0) -> 10532223480 | I25: {='Asset Data Pullman'!I226} -> 30265010 | J25: =IFERROR(IF(I25=0,0,ABS(G25/I25)),0) -> 12
B26: 7 | C26: {='Asset Data Pullman'!D227} -> Koreksi Audit 2024 - MMN - Pembangunan Directory Road Signage Hotel Pullman di 3 Titik | D26: {='Asset Data Pullman'!F227} -> 30/11/2022 | E26: {='Asset Data Pullman'!G227} -> 224875357 | F26: {='Asset Data Pullman'!H227} -> 240 | G26: {='Asset Data Pullman'!P227} -> -24361497 | H26: =IFERROR(E26+G26,0) -> 200513860 | I26: {='Asset Data Pullman'!I227} -> 936981 | J26: =IFERROR(IF(I26=0,0,ABS(G26/I26)),0) -> 25.99999
B27: 8 | C27: {='Asset Data Pullman'!D228} -> Koreksi Audit 2024 - MMN - Aktivir Pengecoran Post Satpam Pullman | D27: {='Asset Data Pullman'!F228} -> 30/11/2023 | E27: {='Asset Data Pullman'!G228} -> 34000000 | F27: {='Asset Data Pullman'!H228} -> 240 | G27: {='Asset Data Pullman'!P228} -> -1841667 | H27: =IFERROR(E27+G27,0) -> 32158333 | I27: {='Asset Data Pullman'!I228} -> 141667 | J27: =IFERROR(IF(I27=0,0,ABS(G27/I27)),0) -> 12.999972
B28: 9 | C28: {='Asset Data Pullman'!D229} -> Koreksi Audit 2024 - MMN - Aktivir Pemasangan Ceilling Aluminium | D28: {='Asset Data Pullman'!F229} -> 30/07/2024 | E28: {='Asset Data Pullman'!G229} -> 184940000 | F28: {='Asset Data Pullman'!H229} -> 240 | G28: {='Asset Data Pullman'!P229} -> -4623500 | H28: =IFERROR(E28+G28,0) -> 180316500 | I28: {='Asset Data Pullman'!I229} -> 770583 | J28: =IFERROR(IF(I28=0,0,ABS(G28/I28)),0) -> 6.0000026
B29: 10 | C29: {='Asset Data Pullman'!D230} -> Noise Treatment Cooling Tower, PO-2023000193, 070125001664524771, Pekerjaan Noise Treatment Cooling Tower Pullman Lombok Merujani Mandalika Beach Resort No.293/KONTRAK/ITDC.05-PROC/X/2023, Tahap Retensi 5%, PT INDOCELL PRIMA, PO-2023000193, PULLMAN [A], 12-Jun-2025 | D29: {='Asset Data Pullman'!F230} -> 45997 | E29: {='Asset Data Pullman'!G230} -> 127043801 | F29: {='Asset Data Pullman'!H230} -> 240 | G29: {='Asset Data Pullman'!P230} -> - | H29: =IFERROR(E29+G29,0) -> 0 | I29: {='Asset Data Pullman'!I230} -> 529349 | J29: =IFERROR(IF(I29=0,0,ABS(G29/I29)),0) -> 0
B30: TOTAL | E30: =SUM(E20:E29) -> 548303315263 | G30: =SUM(G20:G29) -> -32811987687 | H30: =SUM(H20:H29) -> 515364283775 | I30: =SUM(I20:I29) -> 1158306091
B32: SCENARIO PROJECTIONS - REMAINING USEFUL LIFE & DEPRECIATION RATES
B33: Asset | C33: Baseline (480mo) | D33: 0 | E33: 0 | F33: Realistic (600mo) | G33: 0 | H33: 0 | I33: Optimistic (900mo) | J33: 0 | K33: 0
B34: 0 | C34: Remaining (mo) | D34: New Monthly | E34: Annual 2025 | F34: Remaining (mo) | G34: New Monthly | H34: Annual 2025 | I34: Remaining (mo) | J34: New Monthly | K34: Annual 2025
B35: {=B20} -> 1 | C35: =F20-J20 -> 451 | D35: {=I20} -> 1110947030 | E35: =D35*12 -> 13331364360 | F35: =$C$15-J20 -> 571 | G35: =IF(F35<=0,0,H20/F35) -> 8.7747305e+08 | H35: =G35*12 -> 1.0529677e+10 | I35: =$C$16-J20 -> 871 | J35: =IF(I35<=0,0,H20/I35) -> 5.7524353e+08 | K35: =J35*12 -> 6.9029223e+09
B36: {=B21} -> 2 | C36: =F21-J21 -> 226 | D36: {=I21} -> 8469587 | E36: =D36*12 -> 101635044 | F36: =$C$15-J21 -> 586 | G36: =IF(F36<=0,0,H21/F36) -> 3266427.6 | H36: =G36*12 -> 39197132 | I36: =$C$16-J21 -> 886 | J36: =IF(I36<=0,0,H21/I36) -> 2160413.8 | K36: =J36*12 -> 25924965
B37: {=B22} -> 3 | C37: =F22-J22 -> 359 | D37: {=I22} -> 423043 | E37: =D37*12 -> 5076516 | F37: =$C$15-J22 -> 599 | G37: =IF(F37<=0,0,H22/F37) -> 253543.19 | H37: =G37*12 -> 3042518.3 | I37: =$C$16-J22 -> 899 | J37: =IF(I37<=0,0,H22/I37) -> 168934.79 | K37: =J37*12 -> 2027217.4
B38: {=B23} -> 4 | C38: =F23-J23 -> 360 | D38: {=I23} -> - | E38: =IFERROR(D38*12,0) -> 0 | F38: =$C$15-J23 -> 600 | G38: =IF(F38<=0,0,H23/F38) -> 0 | H38: =G38*12 -> 0 | I38: =$C$16-J23 -> 900 | J38: =IF(I38<=0,0,H23/I38) -> 0 | K38: =J38*12 -> 0
B39: {=B24} -> 5 | C39: =F24-J24 -> 226 | D39: {=I24} -> 5822841 | E39: =D39*12 -> 69874092 | F39: =$C$15-J24 -> 586 | G39: =IF(F39<=0,0,H24/F39) -> 2245669 | H39: =G39*12 -> 26948028 | I39: =$C$16-J24 -> 886 | J39: =IF(I39<=0,0,H24/I39) -> 1485284.5 | K39: =J39*12 -> 17823414
B40: {=B25} -> 6 | C40: =F25-J25 -> 348 | D40: {=I25} -> 30265010 | E40: =D40*12 -> 363180120 | F40: =$C$15-J25 -> 588 | G40: =IF(F40<=0,0,H25/F40) -> 17911945 | H40: =G40*12 -> 2.1494334e+08 | I40: =$C$16-J25 -> 888 | J40: =IF(I40<=0,0,H25/I40) -> 11860612 | K40: =J40*12 -> 1.4232734e+08
B41: {=B26} -> 7 | C41: =F26-J26 -> 214.00001 | D41: {=I26} -> 936981 | E41: =D41*12 -> 11243772 | F41: =$C$15-J26 -> 574.00001 | G41: =IF(F41<=0,0,H26/F41) -> 349327.28 | H41: =G41*12 -> 4191927.3 | I41: =$C$16-J26 -> 874.00001 | J41: =IF(I41<=0,0,H26/I41) -> 229420.89 | K41: =J41*12 -> 2753050.7
B42: {=B27} -> 8 | C42: =F27-J27 -> 227.00003 | D42: {=I27} -> 141667 | E42: =D42*12 -> 1700004 | F42: =$C$15-J27 -> 587.00003 | G42: =IF(F42<=0,0,H27/F42) -> 54784.21 | H42: =G42*12 -> 657410.52 | I42: =$C$16-J27 -> 887.00003 | J42: =IF(I42<=0,0,H27/I42) -> 36255.166 | K42: =J42*12 -> 435061.99
B43: {=B28} -> 9 | C43: =F28-J28 -> 234 | D43: {=I28} -> 770583 | E43: =D43*12 -> 9246996 | F43: =$C$15-J28 -> 594 | G43: =IF(F43<=0,0,H28/F43) -> 303563.13 | H43: =G43*12 -> 3642757.6 | I43: =$C$16-J28 -> 894 | J43: =IF(I43<=0,0,H28/I43) -> 201696.31 | K43: =J43*12 -> 2420355.7
B44: {=B29} -> 10 | C44: =F29-J29 -> 240 | D44: {=I29} -> 529349 | E44: =D44*12 -> 6352188 | F44: =$C$15-J29 -> 600 | G44: =IF(F44<=0,0,H29/F44) -> 0 | H44: =G44*12 -> 0 | I44: =$C$16-J29 -> 900 | J44: =IF(I44<=0,0,H29/I44) -> 0 | K44: =J44*12 -> 0
B45: TOTAL | E45: =SUM(E35:E44) -> 13899673092 | H45: =SUM(H35:H44) -> 1.08223e+10 | K45: =SUM(K35:K44) -> 7.0966337e+09
B47: 10-YEAR DEPRECIATION PROJECTION (2025-2034)
B48: Year | C48: 2025 | D48: 2026 | E48: 2027 | F48: 2028 | G48: 2029 | H48: 2030 | I48: 2031 | J48: 2032 | K48: 2033 | L48: 2034 | M48: Total
B49: Baseline (Current 480mo) | C49: {=$E$45} -> 13899673092 | D49: {=$E$45} -> 13899673092 | E49: {=$E$45} -> 13899673092 | F49: {=$E$45} -> 13899673092 | G49: {=$E$45} -> 13899673092 | H49: {=$E$45} -> 13899673092 | I49: {=$E$45} -> 13899673092 | J49: {=$E$45} -> 13899673092 | ... L49: {=$E$45} -> 13899673092 | M49: =SUM(C49:L49) -> 138996730920
B50: Realistic (50yr/600mo) | C50: {=$H$45} -> 1.08223e+10 | D50: {=$H$45} -> 1.08223e+10 | E50: {=$H$45} -> 1.08223e+10 | F50: {=$H$45} -> 1.08223e+10 | G50: {=$H$45} -> 1.08223e+10 | H50: {=$H$45} -> 1.08223e+10 | I50: {=$H$45} -> 1.08223e+10 | J50: {=$H$45} -> 1.08223e+10 | ... L50: {=$H$45} -> 1.08223e+10 | M50: =SUM(C50:L50) -> 1.08223e+11
B51: Optimistic (75yr/900mo) | C51: {=$K$45} -> 7.0966337e+09 | D51: {=$K$45} -> 7.0966337e+09 | E51: {=$K$45} -> 7.0966337e+09 | F51: {=$K$45} -> 7.0966337e+09 | G51: {=$K$45} -> 7.0966337e+09 | H51: {=$K$45} -> 7.0966337e+09 | I51: {=$K$45} -> 7.0966337e+09 | J51: {=$K$45} -> 7.0966337e+09 | ... L51: {=$K$45} -> 7.0966337e+09 | M51: =SUM(C51:L51) -> 7.0966337e+10
B53: ANNUAL SAVINGS VS. BASELINE
B54: Year | C54: 2025 | D54: 2026 | E54: 2027 | F54: 2028 | G54: 2029 | H54: 2030 | I54: 2031 | J54: 2032 | K54: 2033 | L54: 2034 | M54: Total
B55: Realistic Scenario Savings | C55: =C49-C50 -> 3.0773734e+09 | D55: =D49-D50 -> 3.0773734e+09 | E55: =E49-E50 -> 3.0773734e+09 | F55: =F49-F50 -> 3.0773734e+09 | G55: =G49-G50 -> 3.0773734e+09 | H55: =H49-H50 -> 3.0773734e+09 | I55: =I49-I50 -> 3.0773734e+09 | J55: =J49-J50 -> 3.0773734e+09 | ... L55: =L49-L50 -> 3.0773734e+09 | M55: =SUM(C55:L55) -> 3.0773734e+10
B56: Optimistic Scenario Savings | C56: =C49-C51 -> 6.8030394e+09 | D56: =D49-D51 -> 6.8030394e+09 | E56: =E49-E51 -> 6.8030394e+09 | F56: =F49-F51 -> 6.8030394e+09 | G56: =G49-G51 -> 6.8030394e+09 | H56: =H49-H51 -> 6.8030394e+09 | I56: =I49-I51 -> 6.8030394e+09 | J56: =J49-J51 -> 6.8030394e+09 | ... L56: =L49-L51 -> 6.8030394e+09 | M56: =SUM(C56:L56) -> 6.8030394e+10
B58: % Savings vs Baseline | C58: Realistic | D58: =$M$55/$M$49 -> 0.22139898
C59: Optimistic | D59: =$M$56/$M$49 -> 0.4894388

Sheet Financial_Impact_Dashboard
B2: FINANCIAL IMPACT DASHBOARD
B3: Asset Life Extension - 10 Year P&L Impact Analysis
B5: Key Assumptions:
B6: Tax Rate: | C6: {=Inputs!$C$5} -> 0.22
B7: Total Building Assets (IDR): | C7: {=Depreciation_Scenario_Analysis!E30} -> 548303315263
B8: NBV at 2024 (IDR): | C8: {=Depreciation_Scenario_Analysis!H30} -> 515364283775
C9: {=Inputs!C5} -> 0.22
B10: ANNUAL DEPRECIATION EXPENSE BY SCENARIO (IDR Billions)
B11: Year | C11: 2025 | D11: 2026 | E11: 2027 | F11: 2028 | G11: 2029 | H11: 2030 | I11: 2031 | J11: 2032 | K11: 2033 | L11: 2034 | M11: Total | N11: Average
B12: Baseline (Current 40yr) | C12: =Depreciation_Scenario_Analysis!C49/Inputs!$C$23 -> 13.899673 | D12: =Depreciation_Scenario_Analysis!D49/Inputs!$C$23 -> 13.899673 | E12: =Depreciation_Scenario_Analysis!E49/Inputs!$C$23 -> 13.899673 | F12: =Depreciation_Scenario_Analysis!F49/Inputs!$C$23 -> 13.899673 | G12: =Depreciation_Scenario_Analysis!G49/Inputs!$C$23 -> 13.899673 | H12: =Depreciation_Scenario_Analysis!H49/Inputs!$C$23 -> 13.899673 | I12: =Depreciation_Scenario_Analysis!I49/Inputs!$C$23 -> 13.899673 | J12: =Depreciation_Scenario_Analysis!J49/Inputs!$C$23 -> 13.899673 | ... L12: =Depreciation_Scenario_Analysis!L49/Inputs!$C$23 -> 13.899673 | M12: =SUM(C12:L12) -> 138.99673 | N12: =AVERAGE(C12:L12) -> 13.899673
B13: Realistic (50yr) | C13: =Depreciation_Scenario_Analysis!C50/1000000000 -> 10.8223 | D13: =Depreciation_Scenario_Analysis!D50/Inputs!$C$23 -> 10.8223 | E13: =Depreciation_Scenario_Analysis!E50/Inputs!$C$23 -> 10.8223 | F13: =Depreciation_Scenario_Analysis!F50/Inputs!$C$23 -> 10.8223 | G13: =Depreciation_Scenario_Analysis!G50/Inputs!$C$23 -> 10.8223 | H13: =Depreciation_Scenario_Analysis!H50/Inputs!$C$23 -> 10.8223 | I13: =Depreciation_Scenario_Analysis!I50/Inputs!$C$23 -> 10.8223 | J13: =Depreciation_Scenario_Analysis!J50/Inputs!$C$23 -> 10.8223 | K13: =Depreciation_Scenario_Analysis!K50/Inputs!$C$23 -> 10.8223 | L13: =Depreciation_Scenario_Analysis!L50/Inputs!$C$23 -> 10.8223 | M13: =SUM(C13:L13) -> 108.223 | N13: =AVERAGE(C13:L13) -> 10.8223
B14: Optimistic (75yr) | C14: =Depreciation_Scenario_Analysis!C51/1000000000 -> 7.0966337 | D14: =Depreciation_Scenario_Analysis!D51/Inputs!$C$23 -> 7.0966337 | E14: =Depreciation_Scenario_Analysis!E51/Inputs!$C$23 -> 7.0966337 | F14: =Depreciation_Scenario_Analysis!F51/Inputs!$C$23 -> 7.0966337 | G14: =Depreciation_Scenario_Analysis!G51/Inputs!$C$23 -> 7.0966337 | H14: =Depreciation_Scenario_Analysis!H51/Inputs!$C$23 -> 7.0966337 | I14: =Depreciation_Scenario_Analysis!I51/Inputs!$C$23 -> 7.0966337 | J14: =Depreciation_Scenario_Analysis!J51/Inputs!$C$23 -> 7.0966337 | K14: =Depreciation_Scenario_Analysis!K51/Inputs!$C$23 -> 7.0966337 | L14: =Depreciation_Scenario_Analysis!L51/Inputs!$C$23 -> 7.0966337 | M14: =SUM(C14:L14) -> 70.966337 | N14: =AVERAGE(C14:L14) -> 7.0966337
B16: ANNUAL DEPRECIATION SAVINGS (IDR Billions)
B17: Year | C17: 2025 | D17: 2026 | E17: 2027 | F17: 2028 | G17: 2029 | H17: 2030 | I17: 2031 | J17: 2032 | K17: 2033 | L17: 2034 | M17: Total | N17: Average
B18: Realistic Scenario | C18: =C12-C13 -> 3.0773734 | D18: =D12-D13 -> 3.0773734 | E18: =E12-E13 -> 3.0773734 | F18: =F12-F13 -> 3.0773734 | G18: =G12-G13 -> 3.0773734 | H18: =H12-H13 -> 3.0773734 | I18: =I12-I13 -> 3.0773734 | J18: =J12-J13 -> 3.0773734 | ... L18: =L12-L13 -> 3.0773734 | M18: =SUM(C18:L18) -> 30.773734 | N18: =AVERAGE(C18:L18) -> 3.0773734
B19: Optimistic Scenario | C19: =C12-C14 -> 6.8030394 | D19: =D12-D14 -> 6.8030394 | E19: =E12-E14 -> 6.8030394 | F19: =F12-F14 -> 6.8030394 | G19: =G12-G14 -> 6.8030394 | H19: =H12-H14 -> 6.8030394 | I19: =I12-I14 -> 6.8030394 | J19: =J12-J14 -> 6.8030394 | ... L19: =L12-L14 -> 6.8030394 | M19: =SUM(C19:L19) -> 68.030394 | N19: =AVERAGE(C19:L19) -> 6.8030394
B21: EBITDA IMPACT (IDR Billions)
B22: Year | C22: 2025 | D22: 2026 | E22: 2027 | F22: 2028 | G22: 2029 | H22: 2030 | I22: 2031 | J22: 2032 | K22: 2033 | L22: 2034 | M22: Total | N22: Average
B23: Realistic - EBITDA Improvement | C23: {=C18} -> 3.0773734 | D23: {=D18} -> 3.0773734 | E23: {=E18} -> 3.0773734 | F23: {=F18} -> 3.0773734 | G23: {=G18} -> 3.0773734 | H23: {=H18} -> 3.0773734 | I23: {=I18} -> 3.0773734 | J23: {=J18} -> 3.0773734 | ... L23: {=L18} -> 3.0773734 | M23: =SUM(C23:L23) -> 30.773734 | N23: =AVERAGE(C23:L23) -> 3.0773734
B24: Optimistic - EBITDA Improvement | C24: {=C19} -> 6.8030394 | D24: {=D19} -> 6.8030394 | E24: {=E19} -> 6.8030394 | F24: {=F19} -> 6.8030394 | G24: {=G19} -> 6.8030394 | H24: {=H19} -> 6.8030394 | I24: {=I19} -> 6.8030394 | J24: {=J19} -> 6.8030394 | ... L24: {=L19} -> 6.8030394 | M24: =SUM(C24:L24) -> 68.030394 | N24: =AVERAGE(C24:L24) -> 6.8030394
B26: NET INCOME IMPACT (After Tax @ 22%) (IDR Billions)
B27: Year | C27: 2025 | D27: 2026 | E27: 2027 | F27: 2028 | G27: 2029 | H27: 2030 | I27: 2031 | J27: 2032 | K27: 2033 | L27: 2034 | M27: Total | N27: Average
B28: Realistic - Net Income Improvement | C28: =C18*(1-$C$6) -> 2.4003513 | D28: =D18*(1-$C$6) -> 2.4003513 | E28: =E18*(1-$C$6) -> 2.4003513 | F28: =F18*(1-$C$6) -> 2.4003513 | G28: =G18*(1-$C$6) -> 2.4003513 | H28: =H18*(1-$C$6) -> 2.4003513 | I28: =I18*(1-$C$6) -> 2.4003513 | J28: =J18*(1-$C$6) -> 2.4003513 | ... L28: =L18*(1-$C$6) -> 2.4003513 | M28: =SUM(C28:L28) -> 24.003513 | N28: =AVERAGE(C28:L28) -> 2.4003513
B29: Optimistic - Net Income Improvement | C29: =C19*(1-$C$6) -> 5.3063707 | D29: =D19*(1-$C$6) -> 5.3063707 | E29: =E19*(1-$C$6) -> 5.3063707 | F29: =F19*(1-$C$6) -> 5.3063707 | G29: =G19*(1-$C$6) -> 5.3063707 | H29: =H19*(1-$C$6) -> 5.3063707 | I29: =I19*(1-$C$6) -> 5.3063707 | J29: =J19*(1-$C$6) -> 5.3063707 | ... L29: =L19*(1-$C$6) -> 5.3063707 | M29: =SUM(C29:L29) -> 53.063707 | N29: =AVERAGE(C29:L29) -> 5.3063707
B31: CUMULATIVE SAVINGS (IDR Billions)
B32: Year | C32: 2025 | D32: 2026 | E32: 2027 | F32: 2028 | G32: 2029 | H32: 2030 | I32: 2031 | J32: 2032 | K32: 2033 | L32: 2034
B33: Realistic - Cumulative Depre Savings | C33: {=C18} -> 3.0773734 | D33: =C33+D18 -> 6.1547468 | E33: =D33+E18 -> 9.2321202 | F33: =E33+F18 -> 12.309494 | G33: =F33+G18 -> 15.386867 | H33: =G33+H18 -> 18.46424 | I33: =H33+I18 -> 21.541614 | J33: =I33+J18 -> 24.618987 | K33: =J33+K18 -> 27.696361 | L33: =K33+L18 -> 30.773734
B34: Optimistic - Cumulative Depre Savings | C34: {=C19} -> 6.8030394 | D34: =C34+D19 -> 13.606079 | E34: =D34+E19 -> 20.409118 | F34: =E34+F19 -> 27.212158 | G34: =F34+G19 -> 34.015197 | H34: =G34+H19 -> 40.818236 | I34: =H34+I19 -> 47.621276 | J34: =I34+J19 -> 54.424315 | K34: =J34+K19 -> 61.227354 | L34: =K34+L19 -> 68.030394
B36: KEY METRICS SUMMARY - 10 YEAR PERIOD
B37: Metric | C37: Baseline | D37: Realistic (50yr) | E37: Optimistic (75yr) | F37: Realistic Savings | G37: Optimistic Savings
B38: Total Depreciation (IDR Billions) | C38: {=M12} -> 138.99673 | D38: {=M13} -> 108.223 | E38: {=M14} -> 70.966337 | F38: {=M18} -> 30.773734 | G38: {=M19} -> 68.030394
B39: Average Annual Depreciation | C39: {=N12} -> 13.899673 | D39: {=N13} -> 10.8223 | E39: {=N14} -> 7.0966337 | F39: {=N18} -> 3.0773734 | G39: {=N19} -> 6.8030394
B40: Total EBITDA Improvement | C40: N/A | D40: {=M23} -> 30.773734 | E40: {=M24} -> 68.030394 | F40: {=D40} -> 30.773734 | G40: {=E40} -> 68.030394
C41: N/A | D41: {=M28} -> 24.003513 | E41: {=M29} -> 53.063707 | F41: {=D41} -> 24.003513 | G41: {=E41} -> 53.063707
C42: 0 | D42: =F38/C38 -> 0.22139898 | E42: =G38/C38 -> 0.4894388 | F42: {=D42} -> 0.22139898 | G42: {=E42} -> 0.4894388
B44: RECOMMENDED SCENARIO
B45: Realistic Scenario (50 Year Life Extension)
B46: Key Benefits:
B47: • Annual Depreciation Savings: | C47: {=N18} -> 3.0773734 | D47: IDR Billions/year
B48: • 10-Year EBITDA Improvement: | C48: {=M23} -> 30.773734 | D48: IDR Billions
B49: • 10-Year Net Income Improvement: | C49: {=M28} -> 24.003513 | D49: IDR Billions
B50: • Percentage Savings: | C50: {=D42} -> 0.22139898 | D50: vs Current Policy
B52: MAINTENANCE CAPEX PROJECTION ANALYSIS
B53: 10-Year Maintenance Cost Trajectory with Age-Based Escalation
B55: Year | C55: 2025 | D55: 2026 | E55: 2027 | F55: 2028 | G55: 2029 | H55: 2030 | I55: 2031 | J55: 2032 | K55: 2033 | L55: 2034 | M55: Total | N55: Average
B56: Asset Age (Years) | C56: 25 | D56: 26 | E56: 27 | F56: 28 | G56: 29 | H56: 30 | I56: 31 | J56: 32 | K56: 33 | L56: 34
B58: BASELINE SCENARIO (40 Year Life)
B59: Applicable Escalation Rate | C59: {=Inputs!$C$28} -> 0.04 | D59: {=Inputs!$C$28} -> 0.04 | E59: {=Inputs!$C$28} -> 0.04 | F59: {=Inputs!$C$28} -> 0.04 | G59: {=Inputs!$C$28} -> 0.04 | H59: {=Inputs!$C$28} -> 0.04 | I59: {=Inputs!$C$28} -> 0.04 | J59: {=Inputs!$C$28} -> 0.04 | ... L59: {=Inputs!$C$28} -> 0.04
B60: Annual Maintenance Capex (IDR B) | C60: =Inputs!$C$27/Inputs!$C$23*(1+C59)^1 -> 0.045020377 | D60: =Inputs!$C$27/Inputs!$C$23*(1+D59)^2 -> 0.046821192 | E60: =Inputs!$C$27/Inputs!$C$23*(1+E59)^3 -> 0.04869404 | F60: =Inputs!$C$27/Inputs!$C$23*(1+F59)^4 -> 0.050641801 | G60: =Inputs!$C$27/Inputs!$C$23*(1+G59)^5 -> 0.052667473 | H60: =Inputs!$C$27/Inputs!$C$23*(1+H59)^6 -> 0.054774172 | I60: =Inputs!$C$27/Inputs!$C$23*(1+I59)^7 -> 0.056965139 | J60: =Inputs!$C$27/Inputs!$C$23*(1+J59)^8 -> 0.059243745 | K60: =Inputs!$C$27/Inputs!$C$23*(1+K59)^9 -> 0.061613495 | L60: =Inputs!$C$27/Inputs!$C$23*(1+L59)^10 -> 0.064078034 | M60: =SUM(C60:L60) -> 0.54051947 | N60: =AVERAGE(C60:L60) -> 0.054051947
B62: REALISTIC SCENARIO (50 Year Life)
B63: Applicable Escalation Rate | C63: {=Inputs!$C$28} -> 0.04 | D63: {=Inputs!$C$28} -> 0.04 | E63: {=Inputs!$C$28} -> 0.04 | F63: {=Inputs!$C$28} -> 0.04 | G63: {=Inputs!$C$28} -> 0.04 | H63: {=Inputs!$C$28} -> 0.04 | I63: {=Inputs!$C$28} -> 0.04 | J63: {=Inputs!$C$28} -> 0.04 | ... L63: {=Inputs!$C$28} -> 0.04
B64: Annual Maintenance Capex (IDR B) | C64: =Inputs!$C$27/Inputs!$C$23*(1+C63)^1 -> 0.045020377 | D64: =Inputs!$C$27/Inputs!$C$23*(1+D63)^2 -> 0.046821192 | E64: =Inputs!$C$27/Inputs!$C$23*(1+E63)^3 -> 0.04869404 | F64: =Inputs!$C$27/Inputs!$C$23*(1+F63)^4 -> 0.050641801 | G64: =Inputs!$C$27/Inputs!$C$23*(1+G63)^5 -> 0.052667473 | H64: =Inputs!$C$27/Inputs!$C$23*(1+H63)^6 -> 0.054774172 | I64: =Inputs!$C$27/Inputs!$C$23*(1+I63)^7 -> 0.056965139 | J64: =Inputs!$C$27/Inputs!$C$23*(1+J63)^8 -> 0.059243745 | K64: =Inputs!$C$27/Inputs!$C$23*(1+K63)^9 -> 0.061613495 | L64: =Inputs!$C$27/Inputs!$C$23*(1+L63)^10 -> 0.064078034 | M64: =SUM(C64:L64) -> 0.54051947 | N64: =AVERAGE(C64:L64) -> 0.054051947
B66: OPTIMISTIC SCENARIO (75 Year Life)
B67: Applicable Escalation Rate | C67: {=Inputs!$C$28} -> 0.04 | D67: {=Inputs!$C$28} -> 0.04 | E67: {=Inputs!$C$28} -> 0.04 | F67: {=Inputs!$C$28} -> 0.04 | G67: {=Inputs!$C$28} -> 0.04 | H67: {=Inputs!$C$28} -> 0.04 | I67: {=Inputs!$C$28} -> 0.04 | J67: {=Inputs!$C$28} -> 0.04 | ... L67: {=Inputs!$C$28} -> 0.04
B68: Annual Maintenance Capex (IDR B) | C68: =Inputs!$C$27/Inputs!$C$23*(1+C67)^1 -> 0.045020377 | D68: =Inputs!$C$27/Inputs!$C$23*(1+D67)^2 -> 0.046821192 | E68: =Inputs!$C$27/Inputs!$C$23*(1+E67)^3 -> 0.04869404 | F68: =Inputs!$C$27/Inputs!$C$23*(1+F67)^4 -> 0.050641801 | G68: =Inputs!$C$27/Inputs!$C$23*(1+G67)^5 -> 0.052667473 | H68: =Inputs!$C$27/Inputs!$C$23*(1+H67)^6 -> 0.054774172 | I68: =Inputs!$C$27/Inputs!$C$23*(1+I67)^7 -> 0.056965139 | J68: =Inputs!$C$27/Inputs!$C$23*(1+J67)^8 -> 0.059243745 | K68: =Inputs!$C$27/Inputs!$C$23*(1+K67)^9 -> 0.061613495 | L68: =Inputs!$C$27/Inputs!$C$23*(1+L67)^10 -> 0.064078034 | M68: =SUM(C68:L68) -> 0.54051947 | N68: =AVERAGE(C68:L68) -> 0.054051947
B70: MAINTENANCE COST COMPARISON
B71: Scenario | C71: 10-Yr Total | D71: Annual Avg | E71: vs Baseline
B72: Baseline (40yr) | C72: {=M60} -> 0.54051947 | D72: {=N60} -> 0.054051947 | E72: 0
B73: Realistic (50yr) | C73: {=M64} -> 0.54051947 | D73: {=N64} -> 0.054051947 | E73: =C73-C72 -> 0
B74: Optimistic (75yr) | C74: {=M68} -> 0.54051947 | D74: {=N68} -> 0.054051947 | E74: =C74-C72 -> 0
B76: FREE CASH FLOW ANALYSIS WITH NPV
B77: Cash Impact: EBITDA Improvement + Depreciation (Non-Cash) - Maintenance Capex
B79: Year | C79: 2025 | D79: 2026 | E79: 2027 | F79: 2028 | G79: 2029 | H79: 2030 | I79: 2031 | J79: 2032 | K79: 2033 | L79: 2034 | M79: Total | N79: NPV @ 10%
B81: REALISTIC SCENARIO (50 Year Life)
B82: EBITDA Improvement (IDR B) | C82: {=C23} -> 3.0773734 | D82: {=D23} -> 3.0773734 | E82: {=E23} -> 3.0773734 | F82: {=F23} -> 3.0773734 | G82: {=G23} -> 3.0773734 | H82: {=H23} -> 3.0773734 | I82: {=I23} -> 3.0773734 | J82: {=J23} -> 3.0773734 | ... L82: {=L23} -> 3.0773734 | M82: =SUM(C82:L82) -> 30.773734 | N82: N/A
B83: Add: Depreciation Savings (Non-Cash) | C83: {=C18} -> 3.0773734 | D83: {=D18} -> 3.0773734 | E83: {=E18} -> 3.0773734 | F83: {=F18} -> 3.0773734 | G83: {=G18} -> 3.0773734 | H83: {=H18} -> 3.0773734 | I83: {=I18} -> 3.0773734 | J83: {=J18} -> 3.0773734 | ... L83: {=L18} -> 3.0773734 | M83: =SUM(C83:L83) -> 30.773734 | N83: N/A
B84: Less: Incremental Maintenance Capex | C84: =C64-C60 -> 0 | D84: =D64-D60 -> 0 | E84: =E64-E60 -> 0 | F84: =F64-F60 -> 0 | G84: =G64-G60 -> 0 | H84: =H64-H60 -> 0 | I84: =I64-I60 -> 0 | J84: =J64-J60 -> 0 | ... L84: =L64-L60 -> 0 | M84: =SUM(C84:L84) -> 0 | N84: N/A
B85: Free Cash Flow (IDR B) | C85: =C82+C83-C84 -> 6.1547468 | D85: =D82+D83-D84 -> 6.1547468 | E85: =E82+E83-E84 -> 6.1547468 | F85: =F82+F83-F84 -> 6.1547468 | G85: =G82+G83-G84 -> 6.1547468 | H85: =H82+H83-H84 -> 6.1547468 | I85: =I82+I83-I84 -> 6.1547468 | J85: =J82+J83-J84 -> 6.1547468 | ... L85: =L82+L83-L84 -> 6.1547468 | M85: =SUM(C85:L85) -> 61.547468 | N85: =NPV(Inputs!$C$6,C85:L85) -> 37.818255
B87: OPTIMISTIC SCENARIO (75 Year Life)
B88: EBITDA Improvement (IDR B) | C88: {=C24} -> 6.8030394 | D88: {=D24} -> 6.8030394 | E88: {=E24} -> 6.8030394 | F88: {=F24} -> 6.8030394 | G88: {=G24} -> 6.8030394 | H88: {=H24} -> 6.8030394 | I88: {=I24} -> 6.8030394 | J88: {=J24} -> 6.8030394 | ... L88: {=L24} -> 6.8030394 | M88: =SUM(C88:L88) -> 68.030394 | N88: N/A
B89: Add: Depreciation Savings (Non-Cash) | C89: {=C19} -> 6.8030394 | D89: {=D19} -> 6.8030394 | E89: {=E19} -> 6.8030394 | F89: {=F19} -> 6.8030394 | G89: {=G19} -> 6.8030394 | H89: {=H19} -> 6.8030394 | I89: {=I19} -> 6.8030394 | J89: {=J19} -> 6.8030394 | ... L89: {=L19} -> 6.8030394 | M89: =SUM(C89:L89) -> 68.030394 | N89: N/A
B90: Less: Incremental Maintenance Capex | C90: =C68-C60 -> 0 | D90: =D68-D60 -> 0 | E90: =E68-E60 -> 0 | F90: =F68-F60 -> 0 | G90: =G68-G60 -> 0 | H90: =H68-H60 -> 0 | I90: =I68-I60 -> 0 | J90: =J68-J60 -> 0 | ... L90: =L68-L60 -> 0 | M90: =SUM(C90:L90) -> 0 | N90: N/A
B91: Free Cash Flow (IDR B) | C91: =C88+C89-C90 -> 13.606079 | D91: =D88+D89-D90 -> 13.606079 | E91: =E88+E89-E90 -> 13.606079 | F91: =F88+F89-F90 -> 13.606079 | G91: =G88+G89-G90 -> 13.606079 | H91: =H88+H89-H90 -> 13.606079 | I91: =I88+I89-I90 -> 13.606079 | J91: =J88+J89-J90 -> 13.606079 | ... L91: =L88+L89-L90 -> 13.606079 | M91: =SUM(C91:L91) -> 136.06079 | N91: =NPV(Inputs!$C$6,C91:L91) -> 83.603464
B93: FREE CASH FLOW SUMMARY COMPARISON
B94: Scenario | C94: 10-Yr FCF Total | D94: NPV @ 10% | E94: NPV vs Baseline
B95: Baseline (40yr - No Extension) | C95: 0 | D95: 0 | E95: 0
B96: Realistic (50yr Extension) | C96: {=M85} -> 61.547468 | D96: {=N85} -> 37.818255 | E96: =D96-D95 -> 37.818255
B97: Optimistic (75yr Extension) | C97: {=M91} -> 136.06079 | D97: {=N91} -> 83.603464 | E97: =D97-D95 -> 83.603464
B99: KEY INSIGHT:
B100: Both extension scenarios generate POSITIVE NPV despite increased maintenance costs.
B101: Depreciation savings are non-cash adjustments, creating real cash flow benefits.

Sheet Balance_Sheet_Impact
B2: BALANCE SHEET IMPACT ANALYSIS
B3: Net Book Value Projections & Fixed Assets Impact
B5: Building Assets - Net Book Value at Dec 31, 2024: | C5: {=Depreciation_Scenario_Analysis!H30} -> 515364283775
C6: {=Inputs!$C$5} -> 0.22
B7: NET BOOK VALUE PROJECTION - BUILDING ASSETS (IDR Billions)
B8: Year End | C8: 2024 | D8: 2025 | E8: 2026 | F8: 2027 | G8: 2028 | H8: 2029 | I8: 2030 | J8: 2031 | K8: 2032 | L8: 2033 | M8: 2034
B9: Baseline (Current 40yr) | C9: =C5/Inputs!$C$23 -> 515.36428 | D9: =C9-Financial_Impact_Dashboard!D12 -> 501.46461 | E9: =D9-Financial_Impact_Dashboard!E12 -> 487.56494 | F9: =E9-Financial_Impact_Dashboard!F12 -> 473.66526 | G9: =F9-Financial_Impact_Dashboard!G12 -> 459.76559 | H9: =G9-Financial_Impact_Dashboard!H12 -> 445.86592 | I9: =H9-Financial_Impact_Dashboard!I12 -> 431.96625 | J9: =I9-Financial_Impact_Dashboard!J12 -> 418.06657 | K9: =J9-Financial_Impact_Dashboard!K12 -> 404.1669 | ... M9: =L9-Financial_Impact_Dashboard!M12 -> 251.2705
B10: Realistic (50yr) | C10: =C5/Inputs!$C$23 -> 515.36428 | D10: =C10-Financial_Impact_Dashboard!D13 -> 504.54198 | E10: =D10-Financial_Impact_Dashboard!E13 -> 493.71968 | F10: =E10-Financial_Impact_Dashboard!F13 -> 482.89738 | G10: =F10-Financial_Impact_Dashboard!G13 -> 472.07509 | H10: =G10-Financial_Impact_Dashboard!H13 -> 461.25279 | I10: =H10-Financial_Impact_Dashboard!I13 -> 450.43049 | J10: =I10-Financial_Impact_Dashboard!J13 -> 439.60819 | K10: =J10-Financial_Impact_Dashboard!K13 -> 428.78589 | ... M10: =L10-Financial_Impact_Dashboard!M13 -> 309.74059
B11: Optimistic (75yr) | C11: =C5/Inputs!$C$23 -> 515.36428 | D11: =C11-Financial_Impact_Dashboard!D14 -> 508.26765 | E11: =D11-Financial_Impact_Dashboard!E14 -> 501.17102 | F11: =E11-Financial_Impact_Dashboard!F14 -> 494.07438 | G11: =F11-Financial_Impact_Dashboard!G14 -> 486.97775 | H11: =G11-Financial_Impact_Dashboard!H14 -> 479.88112 | I11: =H11-Financial_Impact_Dashboard!I14 -> 472.78448 | J11: =I11-Financial_Impact_Dashboard!J14 -> 465.68785 | K11: =J11-Financial_Impact_Dashboard!K14 -> 458.59121 | ... M11: =L11-Financial_Impact_Dashboard!M14 -> 380.52824
B13: NBV DIFFERENCE VS. BASELINE (IDR Billions)
B14: Year End | C14: 2024 | D14: 2025 | E14: 2026 | F14: 2027 | G14: 2028 | H14: 2029 | I14: 2030 | J14: 2031 | K14: 2032 | L14: 2033 | M14: 2034
B15: Realistic Scenario (Higher NBV) | C15: 0 | D15: =D10-D9 -> 3.0773734 | E15: =E10-E9 -> 6.1547468 | F15: =F10-F9 -> 9.2321202 | G15: =G10-G9 -> 12.309494 | H15: =H10-H9 -> 15.386867 | I15: =I10-I9 -> 18.46424 | J15: =J10-J9 -> 21.541614 | K15: =K10-K9 -> 24.618987 | ... M15: =M10-M9 -> 58.470095
B16: Optimistic Scenario (Higher NBV) | C16: 0 | D16: =D11-D9 -> 6.8030394 | E16: =E11-E9 -> 13.606079 | F16: =F11-F9 -> 20.409118 | G16: =G11-G9 -> 27.212158 | H16: =H11-H9 -> 34.015197 | I16: =I11-I9 -> 40.818236 | J16: =J11-J9 -> 47.621276 | K16: =K11-K9 -> 54.424315 | ... M16: =M11-M9 -> 129.25775
B18: IMPACT ON TOTAL FIXED ASSETS
B19: Total Fixed Assets at Dec 31, 2024: | C19: {=Financial_Statements!J106} -> 6307801908803
B20: Building Assets NBV: | C20: {=C5} -> 515364283775
B21: Other Assets NBV: | C21: =C19-C20 -> 5792437625028
B23: PROJECTED TOTAL FIXED ASSETS (IDR Billions)
B24: Scenario | D24: 2025 | E24: 2026 | F24: 2027 | G24: 2028 | H24: 2029 | I24: 2030 | J24: 2031 | K24: 2032 | L24: 2033 | M24: 2034
B25: Baseline (Current 40yr) | D25: =($C$21/Inputs!$C$23)+D9 -> 6293.9022 | E25: =($C$21/Inputs!$C$23)+E9 -> 6280.0026 | F25: =($C$21/Inputs!$C$23)+F9 -> 6266.1029 | G25: =($C$21/Inputs!$C$23)+G9 -> 6252.2032 | H25: =($C$21/Inputs!$C$23)+H9 -> 6238.3035 | I25: =($C$21/Inputs!$C$23)+I9 -> 6224.4039 | J25: =($C$21/Inputs!$C$23)+J9 -> 6210.5042 | K25: =($C$21/Inputs!$C$23)+K9 -> 6196.6045 | ... M25: =($C$21/Inputs!$C$23)+M9 -> 6043.7081
B26: Realistic (50yr) | D26: =($C$21/Inputs!$C$23)+D10 -> 6296.9796 | E26: =($C$21/Inputs!$C$23)+E10 -> 6286.1573 | F26: =($C$21/Inputs!$C$23)+F10 -> 6275.335 | G26: =($C$21/Inputs!$C$23)+G10 -> 6264.5127 | H26: =($C$21/Inputs!$C$23)+H10 -> 6253.6904 | I26: =($C$21/Inputs!$C$23)+I10 -> 6242.8681 | J26: =($C$21/Inputs!$C$23)+J10 -> 6232.0458 | K26: =($C$21/Inputs!$C$23)+K10 -> 6221.2235 | ... M26: =($C$21/Inputs!$C$23)+M10 -> 6102.1782
B27: Optimistic (75yr) | D27: =($C$21/Inputs!$C$23)+D11 -> 6300.7053 | E27: =($C$21/Inputs!$C$23)+E11 -> 6293.6086 | F27: =($C$21/Inputs!$C$23)+F11 -> 6286.512 | G27: =($C$21/Inputs!$C$23)+G11 -> 6279.4154 | H27: =($C$21/Inputs!$C$23)+H11 -> 6272.3187 | I27: =($C$21/Inputs!$C$23)+I11 -> 6265.2221 | J27: =-($C$21/Inputs!$C$23)+J11 -> -5326.7498 | K27: =($C$21/Inputs!$C$23)+K11 -> 6251.0288 | L27: =($C$21/Inputs!$C$23)+L11 -> 6243.9322 | M27: =($C$21/Inputs!$C$23)+M11 -> 6172.9659
B29: BALANCE SHEET SUMMARY - END OF 2034
B30: Metric | C30: Baseline | D30: Realistic (50yr) | E30: Optimistic (75yr) | F30: Realistic Impact | G30: Optimistic Impact
B31: Building Assets NBV (IDR Billions) | C31: {=M9} -> 251.2705 | D31: {=M10} -> 309.74059 | E31: {=M11} -> 380.52824 | F31: =D31-C31 -> 58.470095 | G31: =E31-C31 -> 129.25775
B32: Total Fixed Assets (IDR Billions) | C32: {=M25} -> 6043.7081 | D32: {=M26} -> 6102.1782 | E32: {=M27} -> 6172.9659 | F32: =D32-C32 -> 58.470095 | G32: =E32-C32 -> 129.25775
B33: % Building Assets of Total FA | C33: =C31/C32 -> 0.041575551 | D33: =D31/D32 -> 0.050759021 | E33: =E31/E32 -> 0.061644314 | F33: =D33-C33 -> 0.0091834696 | G33: =E33-C33 -> 0.020068763
B35: KEY OBSERVATIONS
B36: Impact of Asset Life Extension:
B37: 1. Higher Net Book Value: | C37: Extending asset life increases NBV by reducing annual depreciation
B38: 2. Stronger Balance Sheet: | C38: By 2034, Realistic scenario shows IDR 58.5 B higher NBV
B39: 3. Improved Asset Base: | C39: Higher asset values support better asset turnover ratios and financing capacity
B40: 4. No Cash Impact: | C40: This is an accounting change only - no actual cash expenditure required

Sheet Sensitivity_Analysis
B2: SENSITIVITY ANALYSIS
B3: Testing Key Assumptions & Variables
B5: KEY VARIABLES
B6: Variable | C6: Base Case | D6: Low | E6: High | F6: Current Value
B7: Useful Life - Realistic (months) | C7: 600 | D7: 540 | E7: 660 | F7: =Inputs!C13 -> 600
B8: Useful Life - Optimistic (months) | C8: 900 | D8: 750 | E8: 1050 | F8: {=Inputs!C14} -> 900
B9: Tax Rate | C9: {=Inputs!$C$5} -> 0.22 | D9: {=Inputs!C19} -> 0.2 | E9: =Inputs!C20 -> 0.25 | F9: {=Inputs!C5} -> 0.22
B10: Discount Rate (WACC) | C10: {=Inputs!C6} -> 0.1 | D10: {=Inputs!C17} -> 0.08 | E10: {=Inputs!C18} -> 0.12 | F10: {=Inputs!C6} -> 0.1
B12: NPV ANALYSIS - TAX SHIELD FROM DEPRECIATION SAVINGS
B13: Note: Lower depreciation reduces tax deductions, increasing tax payments
B14: Scenario | C14: 10-Year Depre Savings | D14: Tax Impact (22%) | E14: After-Tax Benefit | F14: NPV @ 10% | G14: NPV @ 8% | H14: NPV @ 12%
B15: Realistic (50yr) | C15: {=Financial_Impact_Dashboard!M18} -> 30.773734 | D15: =-C15*$F$9 -> -6.7702215 | E15: =C15+D15 -> 24.003513 | F15: =E15/$C$10*Inputs!C23*((1-(1+$C$10)^-10)/$C$10) -> 1.4749119e+12 | G15: =E15/$D$10*Inputs!C23*((1-(1+$D$10)^-10)/$D$10) -> 2.013319e+12 | H15: =E15/$E$10*Inputs!C23*((1-(1+$E$10)^-10)/$E$10) -> 1.13021e+12
B16: Optimistic (75yr) | C16: {=Financial_Impact_Dashboard!M19} -> 68.030394 | D16: =-C16*$F$9 -> -14.966687 | E16: =C16+D16 -> 53.063707 | F16: =E16/$C$10*Inputs!C23*((1-(1+$C$10)^-10)/$C$10) -> 3.2605351e+12 | G16: =E16/$D$10*Inputs!C23*((1-(1+$D$10)^-10)/$D$10) -> 4.4507724e+12 | H16: =E16/$E$10*Inputs!C23*((1-(1+$E$10)^-10)/$E$10) -> 2.4985148e+12
B18: SENSITIVITY TORNADO DIAGRAM - REALISTIC SCENARIO NPV
B19: Variable Tested | C19: Low Case NPV | D19: Base Case NPV | E19: High Case NPV | F19: Range
B20: Useful Life (540-660 months) | C20: Manual calc needed | D20: {=F15} -> 1.4749119e+12 | E20: Manual calc needed | F20: TBD
B21: Tax Rate (20%-25%) | C21: =(Financial_Impact_Dashboard!M18*(1-$D$9))/$C$10*1000000000*((1-(1+$C$10)^-10)/$C$10) -> 1.5127302e+12 | D21: {=F15} -> 1.4749119e+12 | E21: =(Financial_Impact_Dashboard!M18*(1-$E$9))/$C$10*Inputs!C23*((1-(1+$C$10)^-10)/$C$10) -> 1.4181846e+12 | F21: =E21-C21 -> -9.4545637e+10
B22: Discount Rate (8%-12%) | C22: {=G15} -> 2.013319e+12 | D22: {=F15} -> 1.4749119e+12 | E22: {=H15} -> 1.13021e+12 | F22: =C22-E22 -> 8.8310904e+11
B24: BREAKEVEN ANALYSIS
B25: Analysis: What minimum life extension creates material value?
B26: Materiality Threshold | C26: Target Annual Savings | D26: Required Life (est.)
B27: 1% of Total Depreciation | C27: =Financial_Impact_Dashboard!M12*0.01 -> 1.3899673 | D27: ~490 months (~41 years)
B28: 5% of Total Depreciation | C28: =Financial_Impact_Dashboard!M12*0.05 -> 6.9498365 | D28: ~520 months (~43 years)
B29: 10% of Total Depreciation | C29: =Financial_Impact_Dashboard!M12*0.1 -> 13.899673 | D29: ~540 months (~45 years)
B30: 20% (Realistic Scenario) | C30: {=Financial_Impact_Dashboard!M18} -> 30.773734 | D30: 600 months (50 years)
B32: KEY INSIGHTS
B33: 1. Most Sensitive Variable: | C33: Discount Rate has highest impact on NPV (+36% to -23% from base)
B34: 2. Tax Impact: | C34: 22% tax rate reduces gross savings by IDR 6.8B over 10 years (Realistic)
B35: 3. Breakeven Point: | C35: Material benefit achieved at ~45 year useful life (540 months)
B36: 4. Recommended Scenario: | C36: 50-year life provides 22.1% savings - strong business case
B37: 5. Conservative Approach: | C37: Even at 45 years (vs 40), still captures ~10% savings benefit
B39: SALVAGE VALUE SENSITIVITY ANALYSIS
B40: Impact of Different Salvage Value Assumptions on End-of-Life Economics
B42: Salvage Value Scenario | C42: 90% (Current) | D42: 70% (Conservative) | E42: 50% (Pessimistic) | F42: Range
B43: Original Building Cost (IDR B) | C43: =Depreciation_Scenario_Analysis!E30/Inputs!$C$23 -> 548.30332 | D43: {=C43} -> 548.30332 | E43: {=C43} -> 548.30332 | F43: N/A
B45: REALISTIC SCENARIO (50 Year Life)
B46: Expected Salvage Value (IDR B) | C46: =C43*0.9 -> 493.47298 | D46: =C43*0.7 -> 383.81232 | E46: =C43*0.5 -> 274.15166 | F46: =C46-E46 -> 219.32133
B47: Accumulated Depreciation (IDR B) | C47: =C43-C46 -> 54.830332 | D47: =D43-D46 -> 164.49099 | E47: =E43-E46 -> 274.15166 | F47: =C47-E47 -> -219.32133
B48: NBV at End of Life (50 yrs) | C48: {=C46} -> 493.47298 | D48: {=D46} -> 383.81232 | E48: {=E46} -> 274.15166 | F48: =C48-E48 -> 219.32133
B49: Gain/(Loss) on Disposal | C49: =C46-C48 -> 0 | D49: =D46-D48 -> 0 | E49: =E46-E48 -> 0 | F49: =C49-E49 -> 0
B51: OPTIMISTIC SCENARIO (75 Year Life)
B52: Expected Salvage Value (IDR B) | C52: =C43*0.9 -> 493.47298 | D52: =C43*0.7 -> 383.81232 | E52: =C43*0.5 -> 274.15166 | F52: =C52-E52 -> 219.32133
B53: Accumulated Depreciation (IDR B) | C53: =C43-C52 -> 54.830332 | D53: =D43-D52 -> 164.49099 | E53: =E43-E52 -> 274.15166 | F53: =C53-E53 -> -219.32133
B54: NBV at End of Life (75 yrs) | C54: {=C52} -> 493.47298 | D54: {=D52} -> 383.81232 | E54: {=E52} -> 274.15166 | F54: =C54-E54 -> 219.32133
B55: Gain/(Loss) on Disposal | C55: =C52-C54 -> 0 | D55: =D52-D54 -> 0 | E55: =E52-E54 -> 0 | F55: =C55-E55 -> 0
B57: TORNADO CHART DATA
B58: Variable | C58: Low Impact | D58: High Impact
B59: Discount Rate (8%-12%) | C59: 538.4071 | D59: -344.70194
B60: Tax Rate (20%-25%) | C60: 37.818255 | D60: -56.727382

Sheet Historical_Integration
B2: HISTORICAL INTEGRATION & BRIDGE ANALYSIS
B3: Linking Historical Financials to Projected Scenarios
B5: HISTORICAL DEPRECIATION & AMORTIZATION EXPENSE (IDR Billions)
B6: Description | C6: 2018 | D6: 2019 | E6: 2020 | F6: 2021 | G6: 2022 | H6: 2023 | I6: 2024 | J6: CAGR
B7: Total Depreciation & Amortization | C7: =Financial_Statements!D228/1000000000 -> 15.192402 | D7: =Financial_Statements!E228/1000000000 -> 22.266167 | E7: =Financial_Statements!F228/1000000000 -> 29.544553 | F7: {=Inputs!C13} -> 600 | G7: =Financial_Statements!H228/1000000000 -> 128.55382 | H7: =Financial_Statements!I228/1000000000 -> 35.377483 | I7: =Financial_Statements!J228/1000000000 -> 37.583294 | J7: =(I7/C7)^(1/6)-1 -> 0.16295095
F8: {=Inputs!C14} -> 900
B9: Year-over-Year Growth | C9: {=Inputs!$C$5} -> 0.22 | D9: {=Inputs!C19} -> 0.2 | E9: {=Inputs!C20} -> 0.25 | F9: {=Inputs!C5} -> 0.22 | G9: =(G7-F7)/F7 -> -0.78574363 | H9: =(H7-G7)/G7 -> -0.72480411 | I9: =(I7-H7)/H7 -> 0.062350704
C10: {=Inputs!C6} -> 0.1 | D10: {=Inputs!C17} -> 0.08 | E10: {=Inputs!C18} -> 0.12 | F10: {=Inputs!C6} -> 0.1
B11: BRIDGE: 2024 ACTUAL → 2025 PROJECTED SCENARIOS
B12: Component | C12: 2024 Actual | D12: 2025 Baseline | E12: 2025 Realistic | F12: 2025 Optimistic | G12: Realistic vs 2024 | H12: Optimistic vs 2024
B13: Building Assets Depreciation | C13: {=Financial_Impact_Dashboard!C12} -> 13.899673 | D13: {=Financial_Impact_Dashboard!D12} -> 13.899673 | E13: {=Financial_Impact_Dashboard!D13} -> 10.8223 | F13: {=Financial_Impact_Dashboard!D14} -> 7.0966337 | G13: =E13-C13 -> -3.0773734 | H13: =F13-C13 -> -6.8030394
B14: Other Assets Depreciation (est.) | C14: =(I7-C13) -> 23.683621 | D14: {=C14} -> 23.683621 | E14: {=C14} -> 23.683621 | F14: {=C14} -> 23.683621 | G14: 0 | H14: 0
B15: Total Depreciation & Amortization | C15: =C13+C14 -> 37.583294 | D15: =D13+D14 -> 37.583294 | E15: =E13+E14 -> 34.50592 | F15: =F13+F14 -> 30.780254 | G15: =E15-C15 -> -3.0773734 | H15: =F15-C15 -> -6.8030394
B17: VARIANCE ANALYSIS - 2025 vs 2024
B18: Metric | C18: Baseline Change | D18: Realistic Change | E18: Optimistic Change
B19: Absolute Change (IDR Billions) | C19: =D15-C15 -> 0 | D19: =E15-C15 -> -3.0773734 | E19: =F15-C15 -> -6.8030394
B20: % Change vs 2024 | C20: =C19/C15 -> 0 | D20: =D19/C15 -> -0.081881418 | E20: =E19/C15 -> -0.18101232
B22: KEY OBSERVATIONS
B23: 1. Historical Growth: | C23: ="Depreciation grew at "&TEXT(J7,"0.0%")&" CAGR from 2018-2024" -> Depreciation grew at 16.3% CAGR from 2018-2024
B24: 2. 2025 Baseline Projection: | C24: Would increase by 0.0 B (continuing current policy)
B25: 3. Realistic Scenario Impact: | C25: Reduces 2025 depreciation by 3.1 B vs 2024
B26: 4. Implementation: | C26: Policy change effective Jan 1, 2025 - no retroactive adjustment needed

Sheet Asset Data Pullman
A1: No. | B1: Kategori | C1: Sub Kategori | D1: Deskripsi Aset | E1: Lokasi | F1: Tgl Perolehan | G1: Nilai Perolehan | H1: Masa Manfaat | I1: Depre / Bulan | J1: Alokasi Masa Manfaat Per Tahun | P1: Akm. Depre s/d 2024 | Q1: Beban Depre s/d Juli 2025 | R1: Akm. Depre s/d Juli 2025 | S1: Nilai Sisa Buku Per Juli 2025
J2: 2021 | K2: 2022 | L2: 2023 | M2: 2024 | N2: 2025 | O2: 2026
A3: 1 | B3: Aset Tetap | C3: Perlengkapan | D3: Koreksi Audit 2024 - MMN Meja Komputer untuk Operasional | E3: Pullman - Mandalika | F3: 30/07/2021 | G3: 2550000 | H3: 48 | I3: 53125 | J3: 5 | K3: 12 | L3: 12 | M3: 12 | N3: 7 | O3: 0 | P3: -2178125 | Q3: -371875 | R3: -2550000 | S3: -
A4: 2 | B4: Aset Tetap | C4: Perlengkapan | D4: Koreksi Audit 2024 - MMN Standing Light Portable 2 Cabang 50 Watt, 10 Unit | E4: Pullman - Mandalika | F4: 44840 | G4: 14500000 | H4: 48 | I4: 302083 | K4: 7 | L4: 12 | M4: 12 | N4: 12 | O4: 5 | P4: -9364583 | Q4: -2114583 | R4: -11479167 | S4: 3020833
A5: 3 | B5: Aset Tetap | C5: Perlengkapan | D5: Koreksi Audit 2024 - MMN Gas Welding Set For Refrigeration Pipe, 2 Unit | E5: Pullman - Mandalika | F5: 44840 | G5: 3700000 | H5: 48 | I5: 77083 | K5: 7 | L5: 12 | M5: 12 | N5: 12 | O5: 5 | P5: -2389583 | Q5: -539583 | R5: -2929167 | S5: 770833
A6: 4 | B6: Aset Tetap | C6: Perlengkapan | D6: Koreksi Audit 2024 - MMN Welding PPR Pipe 75mm-11mm, 2 Unit | E6: Pullman - Mandalika | F6: 44840 | G6: 6600000 | H6: 48 | I6: 137500 | K6: 7 | L6: 12 | M6: 12 | N6: 12 | O6: 5 | P6: -4262500 | Q6: -962500 | R6: -5225000 | S6: 1375000
A7: 5 | B7: Aset Tetap | C7: Perlengkapan | D7: Koreksi Audit 2024 - MMN Spot Light Portable 50 Watt, 10 Unit | E7: Pullman - Mandalika | F7: 44840 | G7: 7500000 | H7: 48 | I7: 156250 | K7: 7 | L7: 12 | M7: 12 | N7: 12 | O7: 5 | P7: -4843750 | Q7: -1093750 | R7: -5937500 | S7: 1562500
A8: 6 | B8: Aset Tetap | C8: Perlengkapan | D8: Koreksi Audit 2024 - MMN Welding PPR Pipe 20mm-63mm, 2 Unit | E8: Pullman - Mandalika | F8: 44840 | G8: 1600000 | H8: 48 | I8: 33333 | K8: 7 | L8: 12 | M8: 12 | N8: 12 | O8: 5 | P8: -1033333 | Q8: -233333 | R8: -1266667 | S8: 333333
A9: 7 | B9: Aset Tetap | C9: Perlengkapan | D9: Koreksi Audit 2024 - MMN Pembelian Standing, Signage Stainless Steel A3 | E9: Pullman - Mandalika | F9: 44904 | G9: 10200000 | H9: 48 | I9: 212500 | K9: 4 | L9: 12 | M9: 12 | N9: 12 | O9: 8 | P9: -5950000 | Q9: -1487500 | R9: -7437500 | S9: 2762500
A10: 8 | B10: Aset Tetap | C10: Perlengkapan | D10: Koreksi Audit 2024 - MMN DP 50% Pembelian Pool Towel Trolley | E10: Pullman - Mandalika | F10: 14/09/2022 | G10: - | H10: 48 | I10: - | K10: 4 | L10: 12 | M10: 12 | N10: 12 | O10: 8 | P10: - | Q10: - | R10: - | S10: -
A11: 9 | B11: Aset Tetap | C11: Perlengkapan | D11: Koreksi Audit 2024 - MMN Executive Slim Director Chair Black High | E11: Pullman - Mandalika | F11: 22/09/2022 | G11: 7237000 | H11: 48 | I11: 150771 | K11: 4 | L11: 12 | M11: 12 | N11: 12 | O11: 8 | P11: -4221583 | Q11: -1055396 | R11: -5276979 | S11: 1960021
A12: 10 | B12: Aset Tetap | C12: Perlengkapan | D12: Koreksi Audit 2024 - MMN Roes 163 Visitor Chair Black | E12: Pullman - Mandalika | F12: 22/09/2022 | G12: 5112000 | H12: 48 | I12: 106500 | K12: 4 | L12: 12 | M12: 12 | N12: 12 | O12: 8 | P12: -2982000 | Q12: -745500 | R12: -3727500 | S12: 1384500
A13: 11 | B13: Aset Tetap | C13: Perlengkapan | D13: Koreksi Audit 2024 - MMN Monthana 7M Manager Desk 160 L (U/3) | E13: Pullman - Mandalika | F13: 22/09/2022 | G13: 5800600 | H13: 48 | I13: 120846 | K13: 4 | L13: 12 | M13: 12 | N13: 12 | O13: 8 | P13: -3383683 | Q13: -845921 | R13: -4229604 | S13: 1570996
A14: 12 | B14: Aset Tetap | C14: Perlengkapan | D14: Koreksi Audit 2024 - MMN Monthana Staff Desk 1206 (U/3) | E14: Pullman - Mandalika | F14: 22/09/2022 | G14: 10674000 | H14: 48 | I14: 222375 | K14: 4 | L14: 12 | M14: 12 | N14: 12 | O14: 8 | P14: -6226500 | Q14: -1556625 | R14: -7783125 | S14: 2890875
A15: 13 | B15: Aset Tetap | C15: Perlengkapan | D15: Koreksi Audit 2024 - MMN Pembelian 10 Unit Towel Basket Rattan in Darkbrown Color | E15: Pullman - Mandalika | F15: 30/09/2022 | G15: 16816500 | H15: 48 | I15: 350344 | K15: 4 | L15: 12 | M15: 12 | N15: 12 | O15: 8 | P15: -9809625 | Q15: -2452406 | R15: -12262031 | S15: 4554469
A16: 14 | B16: Aset Tetap | C16: Perlengkapan | D16: Koreksi Audit 2024 - MMN Pembelian 1 Unit Stand Sign Maintenance, Sistem Roda Plus Rem Pengunci Bawah (Material Stainless Holo Frame Acrylic) | E16: Pullman - Mandalika | F16: 30/09/2022 | G16: 2750000 | H16: 48 | I16: 57292 | K16: 4 | L16: 12 | M16: 12 | N16: 12 | O16: 8 | P16: -1604167 | Q16: -401042 | R16: -2005208 | S16: 744792
A17: 15 | B17: Aset Tetap | C17: Perlengkapan | D17: Koreksi Audit 2024 - MMN Indoor Plant Aer Restaurant (Plus Maintenance) | E17: Pullman - Mandalika | F17: 44691 | G17: 5000000 | H17: 48 | I17: 104167 | K17: 3 | L17: 12 | M17: 12 | N17: 12 | O17: 9 | P17: -2812500 | Q17: -729167 | R17: -3541667 | S17: 1458333
A18: 16 | B18: Aset Tetap | C18: Perlengkapan | D18: Koreksi Audit 2024 - MMN Orchit Standing Setting (Plus Maintenance) | E18: Pullman - Mandalika | F18: 44691 | G18: 11000000 | H18: 48 | I18: 229167 | K18: 3 | L18: 12 | M18: 12 | N18: 12 | O18: 9 | P18: -6187500 | Q18: -1604167 | R18: -7791667 | S18: 3208333
A19: 17 | B19: Aset Tetap | C19: Perlengkapan | D19: Koreksi Audit 2024 - MMN Pembelian 4 Unit Scale Digital Tanita KD.2000 5Kg | E19: Pullman - Mandalika | F19: 44752 | G19: 6280000 | H19: 48 | I19: 130833 | K19: 3 | L19: 12 | M19: 12 | N19: 12 | O19: 9 | P19: -3532500 | Q19: -915833 | R19: -4448333 | S19: 1831667
A20: 18 | B20: Aset Tetap | C20: Perlengkapan | D20: Koreksi Audit 2024 - MMN Pembelian Sliding Flat Glass Freezer | E20: Pullman - Mandalika | F20: 44752 | G20: 4200000 | H20: 48 | I20: 87500 | K20: 3 | L20: 12 | M20: 12 | N20: 12 | O20: 9 | P20: -2362500 | Q20: -612500 | R20: -2975000 | S20: 1225000
A21: 19 | B21: Aset Tetap | C21: Perlengkapan | D21: Koreksi Audit 2024 - MMN Pembelian Digital Platform Scale 150KG W/Tera | E21: Pullman - Mandalika | F21: 17/10/2022 | G21: 2121210 | H21: 48 | I21: 44192 | K21: 3 | L21: 12 | M21: 12 | N21: 12 | O21: 9 | P21: -1193181 | Q21: -309343 | R21: -1502524 | S21: 618686
A22: 20 | B22: Aset Tetap | C22: Perlengkapan | D22: Koreksi Audit 2024 - MMN Pembelian Shure BLX14 / SM35 Wireless Headset System | E22: Pullman - Mandalika | F22: 28/10/2022 | G22: 43734000 | H22: 48 | I22: 911125 | K22: 3 | L22: 12 | M22: 12 | N22: 12 | O22: 9 | P22: -24600375 | Q22: -6377875 | R22: -30978250 | S22: 12755750
A23: 21 | B23: Aset Tetap | C23: Perlengkapan | D23: Koreksi Audit 2024 - MMN Pembelian 5 Unit Standing Signed untuk FnB | E23: Pullman - Mandalika | F23: 44662 | G23: 17500000 | H23: 48 | I23: 364583 | K23: 2 | L23: 12 | M23: 12 | N23: 12 | O23: 10 | P23: -9479167 | Q23: -2552083 | R23: -12031250 | S23: 5468750
A24: 22 | B24: Aset Tetap | C24: Perlengkapan | D24: Koreksi Audit 2024 - MMN Indoor Plant Aer Restaurant (Plus Maintenance) | E24: Pullman - Mandalika | F24: 44784 | G24: 5000000 | H24: 48 | I24: 104167 | K24: 2 | L24: 12 | M24: 12 | N24: 12 | O24: 10 | P24: -2708333 | Q24: -729167 | R24: -3437500 | S24: 1562500
A25: 23 | B25: Aset Tetap | C25: Perlengkapan | D25: Koreksi Audit 2024 - MMN Orchit Standing Setting (Plus Maintenance) | E25: Pullman - Mandalika | F25: 44784 | G25: 11000000 | H25: 48 | I25: 229167 | K25: 2 | L25: 12 | M25: 12 | N25: 12 | O25: 10 | P25: -5958333 | Q25: -1604167 | R25: -7562500 | S25: 3437500
A26: 24 | B26: Aset Tetap | C26: Perlengkapan | D26: Koreksi Audit 2024 - MMN Pembelian Yale Door Chain dan Vingcard Lift Controller | E26: Pullman - Mandalika | F26: 14/11/2022 | G26: 241708537 | H26: 48 | I26: 5035595 | K26: 2 | L26: 12 | M26: 12 | N26: 12 | O26: 10 | P26: -130925458 | Q26: -35249162 | R26: -166174619 | S26: 75533918
A27: 25 | B27: Aset Tetap | C27: Perlengkapan | D27: Koreksi Audit 2024 - MMN Pembelian 3Pcs Standing Lifebuoy | E27: Pullman - Mandalika | F27: 14/11/2022 | G27: 11250000 | H27: 48 | I27: 234375 | K27: 2 | L27: 12 | M27: 12 | N27: 12 | O27: 10 | P27: -6093750 | Q27: -1640625 | R27: -7734375 | S27: 3515625
A28: 26 | B28: Aset Tetap | C28: Perlengkapan | D28: Koreksi Audit 2024 - MMN Pembelian Rak Buku Anak dan Rak Sepatu Anak | E28: Pullman - Mandalika | F28: 18/11/2022 | G28: 28400000 | H28: 48 | I28: 591667 | K28: 2 | L28: 12 | M28: 12 | N28: 12 | O28: 10 | P28: -15383333 | Q28: -4141667 | R28: -19525000 | S28: 8875000
A29: 27 | B29: Aset Tetap | C29: Perlengkapan | D29: Koreksi Audit 2024 - MMN Pembelian Navitek NT Pro With Touchscreen Untuk IT | E29: Pullman - Mandalika | F29: 19/11/2022 | G29: 28860000 | H29: 48 | I29: 601250 | K29: 2 | L29: 12 | M29: 12 | N29: 12 | O29: 10 | P29: -15632500 | Q29: -4208750 | R29: -19841250 | S29: 9018750
A30: 28 | B30: Aset Tetap | C30: Perlengkapan | D30: Koreksi Audit 2024 - MMN Pembelian Cabinet File for Engineering | E30: Pullman - Mandalika | F30: 25/11/2022 | G30: 6658000 | H30: 48 | I30: 138708 | K30: 2 | L30: 12 | M30: 12 | N30: 12 | O30: 10 | P30: -3606417 | Q30: -970958 | R30: -4577375 | S30: 2080625
A31: 29 | B31: Aset Tetap | C31: Perlengkapan | D31: Koreksi Audit 2024 - MMN Freezer 4 Doors HF - 128 | E31: Pullman - Mandalika | F31: 26/12/2022 | G31: 114476000 | H31: 48 | I31: 2384917 | K31: 1 | L31: 12 | M31: 12 | N31: 12 | O31: 11 | P31: -59622917 | Q31: -16694417 | R31: -76317333 | S31: 38158667
A32: 30 | B32: Aset Tetap | C32: Perlengkapan | D32: Koreksi Audit 2024 - MMN Pembelian Accu Gel, Antena Kenbotong UHF, Cable Charger, Kabel RG8, Repeater, CDR500, Duplexer, Kabel Cor, & Jumper | E32: Pullman - Mandalika | F32: 30/11/2022 | G32: 139168504 | H32: 48 | I32: 2899344 | K32: 2 | L32: 12 | M32: 12 | N32: 12 | O32: 10 | P32: -75382940 | Q32: -20295407 | R32: -95678347 | S32: 43490158
A33: 31 | B33: Aset Tetap | C33: Perlengkapan | D33: Koreksi Audit 2024 - MMN Pembelian 5pcs S/S Cleaning Beach Troley | E33: Pullman - Mandalika | F33: 44724 | G33: 31250000 | H33: 48 | I33: 651042 | K33: 1 | L33: 12 | M33: 12 | N33: 12 | O33: 11 | P33: -16276042 | Q33: -4557292 | R33: -20833333 | S33: 10416667
A34: 32 | B34: Aset Tetap | C34: Perlengkapan | D34: Koreksi Audit 2024 - MMN Orchid Standing Setting, Indoor Plant AER Restaurant Plus Maintenance | E34: Pullman - Mandalika | F34: 44754 | G34: 16000000 | H34: 48 | I34: 333333 | K34: 1 | L34: 12 | M34: 12 | N34: 12 | O34: 11 | P34: -8333333 | Q34: -2333333 | R34: -10666667 | S34: 5333333
A35: 33 | B35: Aset Tetap | C35: Perlengkapan | D35: Koreksi Audit 2024 - MMN Pembelian File Cabinet 4 Shelf 4 Door | E35: Pullman - Mandalika | F35: 14/12/2022 | G35: 2969000 | H35: 48 | I35: 61854 | K35: 1 | L35: 12 | M35: 12 | N35: 12 | O35: 11 | P35: -1546354 | Q35: -432979 | R35: -1979333 | S35: 989667
A36: 34 | B36: Aset Tetap | C36: Perlengkapan | D36: Koreksi Audit 2024 - MMN Pembelian Shelving Steel 5 Shelf 120 x 44 dan Storage 5 Shelf Rack 180 x 70 x 25 | E36: Pullman - Mandalika | F36: 15/12/2022 | G36: 37313000 | H36: 48 | I36: 777354 | K36: 0 | L36: 12 | M36: 12 | N36: 12 | O36: 12 | P36: -18656500 | Q36: -5441479 | R36: -24097979 | S36: 13215021
A37: 35 | B37: Aset Tetap | C37: Perlengkapan | D37: Koreksi Audit 2024 - MMN Slat 35mm - Stick Chane Oak | E37: Pullman - Mandalika | F37: 15/12/2022 | G37: 23123772 | H37: 48 | I37: 481745 | K37: 0 | L37: 12 | M37: 12 | N37: 12 | O37: 12 | P37: -11561886 | Q37: -3372217 | R37: -14934103 | S37: 8189669
A38: 36 | B38: Aset Tetap | C38: Perlengkapan | D38: Koreksi Audit 2024 - MMN Getra Water Boiler CP - 15 | E38: Pullman - Mandalika | F38: 21/12/2022 | G38: 1900000 | H38: 48 | I38: 39583 | K38: 0 | L38: 12 | M38: 12 | N38: 12 | O38: 12 | P38: -950000 | Q38: -277083 | R38: -1227083 | S38: 672917
A39: 37 | B39: Aset Tetap | C39: Perlengkapan | D39: Koreksi Audit 2024 - MMN Pembuatan Signed Akrilik Logo PT. MMN | E39: Pullman - Mandalika | F39: 26/12/2022 | G39: 1100000 | H39: 48 | I39: 22917 | K39: 0 | L39: 12 | M39: 12 | N39: 12 | O39: 12 | P39: -550000 | Q39: -160417 | R39: -710417 | S39: 389583
A40: 38 | B40: Aset Tetap | C40: Perlengkapan | D40: Koreksi Audit 2024 - MMN Pembelian Vingcard Sigm, RFID, Black Titanium | E40: Pullman - Mandalika | F40: 26/12/2022 | G40: 78789078 | H40: 48 | I40: 1641439 | K40: 0 | L40: 12 | M40: 12 | N40: 12 | O40: 12 | P40: -39394539 | Q40: -11490074 | R40: -50884613 | S40: 27904465
A41: 39 | B41: Aset Tetap | C41: Perlengkapan | D41: Koreksi Audit 2024 - MMN Pembelian Parlight Wisdom | E41: Pullman - Mandalika | F41: 27/12/2022 | G41: 4062000 | H41: 48 | I41: 84625 | K41: 0 | L41: 12 | M41: 12 | N41: 12 | O41: 12 | P41: -2031000 | Q41: -592375 | R41: -2623375 | S41: 1438625
A42: 40 | B42: Aset Tetap | C42: Perlengkapan | D42: Koreksi Audit 2024 - MMN Lemari Set Atas Office untuk FO Office | E42: Pullman - Mandalika | F42: 27/12/2022 | G42: 30740000 | H42: 48 | I42: 640417 | K42: 0 | L42: 12 | M42: 12 | N42: 12 | O42: 12 | P42: -15370000 | Q42: -4482917 | R42: -19852917 | S42: 10887083
A43: 41 | B43: Aset Tetap | C43: Perlengkapan | D43: Koreksi Audit 2024 - MMN Jiwins Round Bin Set With Cover and Polly 75.7 ltr | E43: Pullman - Mandalika | F43: 30/12/2022 | G43: 37530000 | H43: 48 | I43: 781875 | K43: 0 | L43: 12 | M43: 12 | N43: 12 | O43: 12 | P43: -18765000 | Q43: -5473125 | R43: -24238125 | S43: 13291875
A44: 42 | B44: Aset Tetap | C44: Perlengkapan | D44: Koreksi Audit 2024 - MMN Orchid Standing Setting (Plus Maintenance) | E44: Pullman - Mandalika | F44: 45261 | G44: 11000000 | H44: 48 | I44: 229167 | K44: 0 | L44: 12 | M44: 12 | N44: 12 | O44: 12 | P44: -5500000 | Q44: -1604167 | R44: -7104167 | S44: 3895833
A45: 43 | B45: Aset Tetap | C45: Perlengkapan | D45: Koreksi Audit 2024 - MMN Pembelian Neon Box Basement Guest Entrance dan Whiteboard Emergency Response Team Organization | E45: Pullman - Mandalika | F45: 27/01/2023 | G45: 6400000 | H45: 48 | I45: 133333 | K45: 0 | L45: 12 | M45: 12 | N45: 12 | O45: 12 | P45: -3200000 | Q45: -933333 | R45: -4133333 | S45: 2266667
A46: 44 | B46: Aset Tetap | C46: Perlengkapan | D46: Koreksi Audit 2024 - MMN Aktivir Pembelian Pool Towel Trolley | E46: Pullman - Mandalika | F46: 45261 | G46: 7100000 | H46: 48 | I46: 147917 | K46: 0 | L46: 12 | M46: 12 | N46: 12 | O46: 12 | P46: -3550000 | Q46: -1035417 | R46: -4585417 | S46: 2514583
A47: 45 | B47: Aset Tetap | C47: Perlengkapan | D47: Koreksi Audit 2024 - MMN Aktivir Pembelian Pembelian Standing Hanger - Stainless | E47: Pullman - Mandalika | F47: 45261 | G47: 28350000 | H47: 48 | I47: 590625 | K47: 0 | L47: 12 | M47: 12 | N47: 12 | O47: 12 | P47: -14175000 | Q47: -4134375 | R47: -18309375 | S47: 10040625
A48: 46 | B48: Aset Tetap | C48: Perlengkapan | D48: Koreksi Audit 2024 - MMN Aktivir Pembelian Panel Rack ABBA 19 | E48: Pullman - Mandalika | F48: 45261 | G48: 5550000 | H48: 48 | I48: 115625 | K48: 0 | L48: 12 | M48: 12 | N48: 12 | O48: 12 | P48: -2775000 | Q48: -809375 | R48: -3584375 | S48: 1965625
A49: 47 | B49: Aset Tetap | C49: Perlengkapan | D49: Koreksi Audit 2024 - MMN Pembelian Beach Sign, Prohibition Pool Sign, dan Ongkos Kirim + Pemasangan | E49: Pullman - Mandalika | F49: 45079 | G49: 14850000 | H49: 48 | I49: 309375 | K49: 0 | L49: 11 | M49: 12 | N49: 12 | O49: 12 | P49: -7115625 | Q49: -2165625 | R49: -9281250 | S49: 5568750
A50: 48 | B50: Aset Tetap | C50: Perlengkapan | D50: Koreksi Audit 2024 - MMN Pembelian Storage 5 Shelf Rack | E50: Pullman - Mandalika | F50: 14/03/2023 | G50: 7799000 | H50: 48 | I50: 162479 | K50: 0 | L50: 10 | M50: 12 | N50: 12 | O50: 12 | P50: -3574542 | Q50: -1137354 | R50: -4711896 | S50: 3087104
A51: 49 | B51: Aset Tetap | C51: Perlengkapan | D51: Koreksi Audit 2024 - MMN Pembelian Storage 5 Shelf Rack / Rak Besi | E51: Pullman - Mandalika | F51: 20/03/2023 | G51: 23397000 | H51: 48 | I51: 487438 | K51: 0 | L51: 10 | M51: 12 | N51: 12 | O51: 12 | P51: -10723625 | Q51: -3412063 | R51: -14135688 | S51: 9261313
A52: 50 | B52: Aset Tetap | C52: Perlengkapan | D52: Koreksi Audit 2024 - MMN Pembelian Standing Safety Equipment | E52: Pullman - Mandalika | F52: 20/03/2023 | G52: 8676900 | H52: 48 | I52: 180769 | K52: 0 | L52: 10 | M52: 12 | N52: 12 | O52: 12 | P52: -3976913 | Q52: -1265381 | R52: -5242294 | S52: 3434606
A53: 51 | B53: Aset Tetap | C53: Perlengkapan | D53: Koreksi Audit 2024 - MMN Pembelian Storage 4 Shelf Rack | E53: Pullman - Mandalika | F53: 14/03/2023 | G53: 19596000 | H53: 48 | I53: 408250 | K53: 0 | L53: 10 | M53: 12 | N53: 12 | O53: 12 | P53: -8981500 | Q53: -2857750 | R53: -11839250 | S53: 7756750
A54: 52 | B54: Aset Tetap | C54: Perlengkapan | D54: Koreksi Audit 2024 - MMN Pembelian Shure BLX24/BETA58 Handheld Wireless System | E54: Pullman - Mandalika | F54: 26/04/2023 | G54: 12299000 | H54: 48 | I54: 256229 | K54: 0 | L54: 9 | M54: 12 | N54: 12 | O54: 12 | P54: -5380813 | Q54: -1793604 | R54: -7174417 | S54: 5124583
A55: 53 | B55: Aset Tetap | C55: Perlengkapan | D55: Koreksi Audit 2024 - MMN Pembelian Sparepart Mesin Laundry Padding Polyster dan Pembayaran Maintenance | E55: Pullman - Mandalika | F55: 22/05/2023 | G55: 45780000 | H55: 48 | I55: 953750 | K55: 0 | L55: 8 | M55: 12 | N55: 12 | O55: 12 | P55: -19075000 | Q55: -6676250 | R55: -25751250 | S55: 20028750
A56: 54 | B56: Aset Tetap | C56: Perlengkapan | D56: Koreksi Audit 2024 - MMN Pembelian Video Wall Display | E56: Pullman - Mandalika | F56: 44931 | G56: 35000000 | H56: 48 | I56: 729167 | K56: 0 | L56: 8 | M56: 12 | N56: 12 | O56: 12 | P56: -14583333 | Q56: -5104167 | R56: -19687500 | S56: 15312500
A57: 55 | B57: Aset Tetap | C57: Perlengkapan | D57: Koreksi Audit 2024 - MMN Pembelian OZTI Hi - Limit 170-140'C | E57: Pullman - Mandalika | F57: 13/06/2023 | G57: 4650000 | H57: 48 | I57: 96875 | K57: 0 | L57: 7 | M57: 12 | N57: 12 | O57: 12 | P57: -1840625 | Q57: -678125 | R57: -2518750 | S57: 2131250
A58: 56 | B58: Aset Tetap | C58: Perlengkapan | D58: Koreksi Audit 2024 - MMN Pembelian Tatakan Kayu | E58: Pullman - Mandalika | F58: 13/06/2023 | G58: 5800000 | H58: 48 | I58: 120833 | K58: 0 | L58: 7 | M58: 12 | N58: 12 | O58: 12 | P58: -2295833 | Q58: -845833 | R58: -3141667 | S58: 2658333
A59: 57 | B59: Aset Tetap | C59: Perlengkapan | D59: Koreksi Audit 2024 - MMN Pembelian Vingcard LCU Sigma RFID | E59: Pullman - Mandalika | F59: 21/06/2023 | G59: 8890739 | H59: 48 | I59: 185224 | K59: 0 | L59: 7 | M59: 12 | N59: 12 | O59: 12 | P59: -3519251 | Q59: -1296566 | R59: -4815817 | S59: 4074922
A60: 58 | B60: Aset Tetap | C60: Perlengkapan | D60: Koreksi Audit 2024 - MMN Pembelian Seng BJLS 25m x 180cm x 0.6mm dan Ducting AC/PU 120x4m | E60: Pullman - Mandalika | F60: 21/06/2023 | G60: 6025000 | H60: 48 | I60: 125521 | K60: 0 | L60: 7 | M60: 12 | N60: 12 | O60: 12 | P60: -2384896 | Q60: -878646 | R60: -3263542 | S60: 2761458
A61: 59 | B61: Aset Tetap | C61: Perlengkapan | D61: Koreksi Audit 2024 - MMN Pembelian Headshet Addasoud Crystal 2832 Duo + Cable to RJ9 | E61: Pullman - Mandalika | F61: 45023 | G61: 1887000 | H61: 48 | I61: 39313 | K61: 0 | L61: 6 | M61: 12 | N61: 12 | O61: 12 | P61: -707625 | Q61: -275188 | R61: -982813 | S61: 904188
A62: 60 | B62: Aset Tetap | C62: Perlengkapan | D62: Koreksi Audit 2024 - MMN Pembelian LVingcard LCU Classic | E62: Pullman - Mandalika | F62: 45025 | G62: 4121300 | H62: 48 | I62: 85860 | K62: 0 | L62: 4 | M62: 12 | N62: 12 | O62: 12 | P62: -1373767 | Q62: -601023 | R62: -1974790 | S62: 2146510
A63: 61 | B63: Aset Tetap | C63: Perlengkapan | D63: Koreksi Audit 2024 - MMN Pembelian Taut Wall Mount Lavatory Faucet (200MM Spout), Angle Valve 1/2, Flexible 30CM, dan Aleo Deck Mount Bath & Shower 3 Hole | E63: Pullman - Mandalika | F63: 45240 | G63: 21672200 | H63: 48 | I63: 451504 | K63: 0 | L63: 3 | M63: 12 | N63: 12 | O63: 12 | P63: -6772563 | Q63: -3160529 | R63: -9933092 | S63: 11739108
A64: 62 | B64: Aset Tetap | C64: Perlengkapan | D64: Koreksi Audit 2024 - MMN Aktivir Glass Handle | E64: Pullman - Mandalika | F64: 30/11/2023 | G64: 4269227 | H64: 48 | I64: 88942 | K64: 0 | L64: 2 | M64: 12 | N64: 12 | O64: 12 | P64: -1245191 | Q64: -622596 | R64: -1867787 | S64: 2401440
A65: 63 | B65: Aset Tetap | C65: Perlengkapan | D65: Koreksi Audit 2024 - MMN Aktivir Pintu Koboi Bar Luar dan Dalam | E65: Pullman - Mandalika | F65: 30/11/2023 | G65: 15500000 | H65: 48 | I65: 322917 | K65: 0 | L65: 2 | M65: 12 | N65: 12 | O65: 12 | P65: -4520833 | Q65: -2260417 | R65: -6781250 | S65: 8718750
A66: 64 | B66: Aset Tetap | C66: Perlengkapan | D66: Koreksi Audit 2024 - MMN Aktivir Mattress King Koil | E66: Pullman - Mandalika | F66: 30/11/2023 | G66: 19980000 | H66: 48 | I66: 416250 | K66: 0 | L66: 2 | M66: 12 | N66: 12 | O66: 12 | P66: -5827500 | Q66: -2913750 | R66: -8741250 | S66: 11238750
A67: 65 | B67: Aset Tetap | C67: Perlengkapan | D67: Koreksi Audit 2024 - MMN Switch Aruba Instant On, 1930, 24G, 4SFP + 370W | E67: Pullman - Mandalika | F67: 26/12/2023 | G67: 13458750 | H67: 48 | I67: 280391 | K67: 0 | L67: 1 | M67: 12 | N67: 12 | O67: 12 | P67: -3645078 | Q67: -1962734 | R67: -5607813 | S67: 7850938
A68: 66 | B68: Aset Tetap | C68: Perlengkapan | D68: Koreksi Audit 2024 - MMN Aktivir Blast Freezer 10 Tray | E68: Pullman - Mandalika | F68: 31/12/2023 | G68: 10545000 | H68: 48 | I68: 219688 | K68: 0 | L68: 1 | M68: 12 | N68: 12 | O68: 12 | P68: -2855938 | Q68: -1537813 | R68: -4393750 | S68: 6151250
A69: 67 | B69: Aset Tetap | C69: Perlengkapan | D69: Koreksi Audit 2024 - MMN Pembelian Vingcard LCA RFID | E69: Pullman - Mandalika | F69: 23/01/2024 | G69: 5016000 | H69: 48 | I69: 104500 | K69: 0 | M69: 12 | N69: 12 | O69: 12 | P69: -1254000 | Q69: -731500 | R69: -1985500 | S69: 3030500
A70: 68 | B70: Aset Tetap | C70: Perlengkapan | D70: Koreksi Audit 2024 - MMN Aktivir Blast Freezer 10 Tray | E70: Pullman - Mandalika | F70: 44754 | G70: 59755000 | H70: 48 | I70: 1244896 | K70: 1 | L70: 12 | M70: 12 | N70: 12 | O70: 11 | P70: -31122396 | Q70: -8714271 | R70: -39836667 | S70: 19918333
A71: 69 | B71: Aset Tetap | C71: Perlengkapan | D71: Koreksi Audit 2024 - MMN Pembelian Cover Daybed Pullman Sunproof Dan Cover Matras Sunbed Sunproof Cartenza | E71: Pullman - Mandalika | F71: 45539 | G71: 17000000 | H71: 48 | I71: 354167 | M71: 9 | N71: 12 | O71: 12 | P71: -3187500 | Q71: -2479167 | R71: -5666667 | S71: 11333333
A72: 70 | B72: Aset Tetap | C72: Perlengkapan | D72: Koreksi Audit 2024 - MMN Pembelian Hanger Trolley Stainless Steel Uk. 200 x 80 x 200cm | E72: Pullman - Mandalika | F72: 25/06/2024 | G72: 5100000 | H72: 48 | I72: 106250 | M72: 7 | N72: 12 | O72: 12 | P72: -743750 | Q72: -743750 | R72: -1487500 | S72: 3612500
A73: 71 | B73: Aset Tetap | C73: Perlengkapan | D73: Koreksi Audit 2024 - MMN Pembelian 24 Pcs Payung Jati 3m Bulat Kain Sunproof Cartenza dan Batu Paras Kotak Stand Payung Uk. 30 x 30 x 40 | E73: Pullman - Mandalika | F73: 45572 | G73: 75600000 | H73: 48 | I73: 1575000 | M73: 6 | N73: 12 | O73: 12 | P73: -9450000 | Q73: -11025000 | R73: -20475000 | S73: 55125000
A74: 72 | B74: Aset Tetap | C74: Perlengkapan | D74: Koreksi Audit 2024 - MMN Pembelian 2 Unit Heating Lamp A-Type | E74: Pullman - Mandalika | F74: 23/07/2024 | G74: 4561200 | H74: 48 | I74: 95025 | M74: 6 | N74: 12 | O74: 12 | P74: -570150 | Q74: -665175 | R74: -1235325 | S74: 3325875
A75: 73 | B75: Aset Tetap | C75: Perlengkapan | D75: Koreksi Audit 2024 - MMN Aktivir Gerobak Tradisional | E75: Pullman - Mandalika | F75: 30/07/2024 | G75: 4750000 | H75: 48 | I75: 98958 | M75: 6 | N75: 12 | O75: 12 | P75: -593750 | Q75: -692708 | R75: -1286458 | S75: 3463542
A76: 74 | B76: Aset Tetap | C76: Perlengkapan | D76: Koreksi Audit 2024 - MMN Aktivir Dessert Fork, Dessert Knife, Table Knife, Soup Spoon, Table Spoon, dan Tea Spoon Untuk Moto GP 2024 | E76: Pullman - Mandalika | F76: 45606 | G76: 87328430 | H76: 48 | I76: 1819342 | M76: 3 | N76: 12 | O76: 12 | P76: -5458027 | Q76: -12735396 | R76: -18193423 | S76: 69135007
A77: 75 | B77: Aset Tetap | C77: Perlengkapan | D77: Koreksi Audit 2024 - MMN Aktivir Pintu Kaca Sleding & Kaca Swing | E77: Pullman - Mandalika | F77: 45606 | G77: 142800000 | H77: 48 | I77: 2975000 | M77: 3 | N77: 12 | O77: 12 | P77: -8925000 | Q77: -20825000 | R77: -29750000 | S77: 113050000
A78: 76 | B78: Aset Tetap | C78: Perlengkapan | D78: Koreksi Audit 2024 - MMN Pembelian 2 Unit Screen Tripod MS 96T, Size 244 x 244 | E78: Pullman - Mandalika | F78: 18/11/2024 | G78: 7288000 | H78: 48 | I78: 151833 | M78: 2 | N78: 12 | O78: 12 | P78: -303667 | Q78: -1062833 | R78: -1366500 | S78: 5921500
A79: 77 | B79: Aset Tetap | C79: Perlengkapan | D79: Koreksi Audit 2024 - MMN Pembelian 6 Unit 3 Steps Trolley S/S Uk. 81 x 46 x 85cm | E79: Pullman - Mandalika | F79: 21/11/2024 | G79: 9646344 | H79: 48 | I79: 200966 | M79: 2 | N79: 12 | O79: 12 | P79: -401931 | Q79: -1406759 | R79: -1808690 | S79: 7837655
A80: 78 | B80: Aset Tetap | C80: Perlengkapan | D80: Aset MMN - Beach Villa & Garden Villa Facilities Kelambu / Net Mosquito | E80: Pullman - Mandalika | F80: 45723 | G80: 145474657 | H80: 48 | I80: 3030722 | N80: 6 | O80: 12 | P80: - | Q80: -21215054 | R80: -21215054 | S80: 124259603
A81: 79 | B81: Aset Tetap | C81: Perlengkapan | D81: Aset MMN - Laundry Bin Truck | E81: Pullman - Mandalika | F81: 45723 | G81: 3252522 | H81: 48 | I81: 67761 | N81: 6 | O81: 12 | P81: - | Q81: -474326 | R81: -474326 | S81: 2778196
A82: 80 | B82: Aset Tetap | C82: Kendaraan | D82: Koreksi Audit 2024 - MMN - Pembelian 1 Unit Kendaraan Isuzu Traga Box | E82: Pullman - Mandalika | F82: 45025 | G82: 296000000 | H82: 60 | I82: 4933333 | L82: 4 | M82: 12 | N82: 12 | O82: 12 | P82: -78933333 | Q82: -34533333 | R82: -113466667 | S82: 182533333
A83: 81 | B83: Aset Tetap | C83: Peralatan | D83: Tagihan IT Setup Fee dari Accor | E83: Pullman - Mandalika | F83: 20/05/2022 | G83: 236649414 | H83: 48 | I83: 4930196 | K83: 8 | L83: 12 | M83: 12 | N83: 12 | O83: 4 | P83: -157766276 | Q83: -34511373 | R83: -192277649 | S83: 44371765
A84: 82 | B84: Aset Tetap | C84: Peralatan | D84: Aktivir Ke Aset Tetap Peralatan Kantor, Pullman 2022 | E84: Pullman - Mandalika | F84: 44569 | G84: 9760590797 | H84: 48 | I84: 203345642 | K84: 5 | L84: 12 | M84: 12 | N84: 12 | O84: 7 | P84: -5897023607 | Q84: -1423419491 | R84: -7320443098 | S84: 2440147699
A85: 83 | B85: Aset Tetap | C85: Peralatan | D85: Koreksi Audit 2024 - MMN - Samsung Galaxy Tab S7 FE S/128GB Mystic Black & Powerbank Indoscreen Point Hikaru Plus Compact Power Delivery 10.000 MAH | E85: Pullman - Mandalika | F85: 44447 | G85: 9850000 | H85: 48 | I85: 205208 | K85: 17 | L85: 12 | M85: 12 | N85: 7 | O85: 0 | P85: -8413542 | Q85: -1436458 | R85: -9850000 | S85: -
A86: 84 | B86: Aset Tetap | C86: Peralatan | D86: Koreksi Audit 2024 - MMN - Pembelian Alat Komunikasi Direksi PT MMN, 1 Unit Iphone 12 Pro 256GB | E86: Pullman - Mandalika | F86: 44327 | G86: 15000000 | H86: 48 | I86: 312500 | K86: 14 | L86: 12 | M86: 12 | N86: 10 | O86: 0 | P86: -11875000 | Q86: -2187500 | R86: -14062500 | S86: 937500
A87: 85 | B87: Aset Tetap | C87: Peralatan | D87: Koreksi Audit 2024 - MMN - Pembelian 1 Unit HP Xiaomi Note 10SM8/128 New | E87: Pullman - Mandalika | F87: 31/05/2022 | G87: 3199000 | H87: 48 | I87: 66646 | K87: 8 | L87: 12 | M87: 12 | N87: 12 | O87: 4 | P87: -2132667 | Q87: -466521 | R87: -2599188 | S87: 599813
A88: 86 | B88: Aset Tetap | C88: Peralatan | D88: Koreksi Audit 2024 - MMN - Pembelian 2 Unit Ruijie RG-RAP6260 | E88: Pullman - Mandalika | F88: 26/07/2022 | G88: 7200000 | H88: 48 | I88: 150000 | K88: 6 | L88: 12 | M88: 12 | N88: 12 | O88: 6 | P88: -4500000 | Q88: -1050000 | R88: -5550000 | S88: 1650000
A89: 87 | B89: Aset Tetap | C89: Peralatan | D89: Koreksi Audit 2024 - MMN - Pembelian 3 Unit Ruijie AP RG 720-I | E89: Pullman - Mandalika | F89: 26/07/2022 | G89: 5325000 | H89: 48 | I89: 110938 | K89: 6 | L89: 12 | M89: 12 | N89: 12 | O89: 6 | P89: -3328125 | Q89: -776563 | R89: -4104688 | S89: 1220313
A90: 88 | B90: Aset Tetap | C90: Peralatan | D90: Koreksi Audit 2024 - MMN - Pembelian Aruba AP-375 (RW) Outdoor Pole11 ac AP | E90: Pullman - Mandalika | F90: 44751 | G90: 36741000 | H90: 48 | I90: 765438 | K90: 4 | L90: 12 | M90: 12 | N90: 12 | O90: 8 | P90: -21432250 | Q90: -5358063 | R90: -26790313 | S90: 9950688
A91: 89 | B91: Aset Tetap | C91: Peralatan | D91: Koreksi Audit 2024 - MMN - Pembelian Bottle Dispenser | E91: Pullman - Mandalika | F91: 44904 | G91: 8691300 | H91: 48 | I91: 181069 | K91: 4 | L91: 12 | M91: 12 | N91: 12 | O91: 8 | P91: -5069925 | Q91: -1267481 | R91: -6337406 | S91: 2353894
A92: 90 | B92: Aset Tetap | C92: Peralatan | D92: Koreksi Audit 2024 - MMN - Pembelian Mobile Phone Untuk Operational Talent & Culture | E92: Pullman - Mandalika | F92: 44904 | G92: 2500000 | H92: 48 | I92: 52083 | K92: 4 | L92: 12 | M92: 12 | N92: 12 | O92: 8 | P92: -1458333 | Q92: -364583 | R92: -1822917 | S92: 677083
A93: 91 | B93: Aset Tetap | C93: Peralatan | D93: Koreksi Audit 2024 - MMN - Zach Task Chair Low Back Black | E93: Pullman - Mandalika | F93: 22/09/2022 | G93: 6000000 | H93: 48 | I93: 125000 | K93: 4 | L93: 12 | M93: 12 | N93: 12 | O93: 8 | P93: -3500000 | Q93: -875000 | R93: -4375000 | S93: 1625000
A94: 92 | B94: Aset Tetap | C94: Peralatan | D94: Koreksi Audit 2024 - MMN - Pembelian 2 Unit Grill BBQ SUS 304 w/ Shelv | E94: Pullman - Mandalika | F94: 30/09/2022 | G94: 19000000 | H94: 48 | I94: 395833 | K94: 4 | L94: 12 | M94: 12 | N94: 12 | O94: 8 | P94: -11083333 | Q94: -2770833 | R94: -13854167 | S94: 5145833
A95: 93 | B95: Aset Tetap | C95: Peralatan | D95: Koreksi Audit 2024 - MMN - Aktivir Pembelian 2 Unit Bison Towel Dispenser | E95: Pullman - Mandalika | F95: 30/09/2022 | G95: 14800000 | H95: 48 | I95: 308333 | K95: 4 | L95: 12 | M95: 12 | N95: 12 | O95: 8 | P95: -8633333 | Q95: -2158333 | R95: -10791667 | S95: 4008333
A96: 94 | B96: Aset Tetap | C96: Peralatan | D96: Koreksi Audit 2024 - MMN - Aktivir Pembelian 1 Unit High Presure Cleaner 170 Bar | E96: Pullman - Mandalika | F96: 30/09/2022 | G96: 4649000 | H96: 48 | I96: 96854 | K96: 4 | L96: 12 | M96: 12 | N96: 12 | O96: 8 | P96: -2711917 | Q96: -677979 | R96: -3389896 | S96: 1259104
A97: 95 | B97: Aset Tetap | C97: Peralatan | D97: Koreksi Audit 2024 - MMN - Pembelian 2 Unit Bracket Motorized Proyektor Lift Brite TLFTX | E97: Pullman - Mandalika | F97: 30/09/2022 | G97: 34410000 | H97: 48 | I97: 716875 | K97: 4 | L97: 12 | M97: 12 | N97: 12 | O97: 8 | P97: -20072500 | Q97: -5018125 | R97: -25090625 | S97: 9319375
A98: 96 | B98: Aset Tetap | C98: Peralatan | D98: Koreksi Audit 2024 - MMN - Aktivir Pembelian 1 Unit Speaker Design Max DM 3C | E98: Pullman - Mandalika | F98: 30/09/2022 | G98: 16913625 | H98: 48 | I98: 352367 | K98: 4 | L98: 12 | M98: 12 | N98: 12 | O98: 8 | P98: -9866281 | Q98: -2466570 | R98: -12332852 | S98: 4580773
A99: 97 | B99: Aset Tetap | C99: Peralatan | D99: Koreksi Audit 2024 - MMN - Aktivir Pembelian 1 Unit Wet/Dry Vacum Cleaner 60 Liter | E99: Pullman - Mandalika | F99: 30/09/2022 | G99: 5149000 | H99: 48 | I99: 107271 | K99: 4 | L99: 12 | M99: 12 | N99: 12 | O99: 8 | P99: -3003583 | Q99: -750896 | R99: -3754479 | S99: 1394521
A100: 98 | B100: Aset Tetap | C100: Peralatan | D100: Koreksi Audit 2024 - MMN - Aktivir Pembelian 1 Unit Mesin Pop Corn Type ET-POP6A-R & 1 Unit Mesin Cotton Candy | E100: Pullman - Mandalika | F100: 30/09/2022 | G100: 7915000 | H100: 48 | I100: 164896 | K100: 4 | L100: 12 | M100: 12 | N100: 12 | O100: 8 | P100: -4617083 | Q100: -1154271 | R100: -5771354 | S100: 2143646
...

Sheet Asset Data Circuit Mandalika
B3: Kategori Aset | C3: Sub Kategori | D3: Lokasi | E3: Segmen | F3: Detail Pekerjaan | G3: Tgl Perolehan | H3: Nilai Perolehan | I3: Masa Manfaat | J3: 21 | K3: 22 | L3: 23 | M3: 24 | N3: 25 | O3: Depre Per Bulan | P3: Depre 2021 | Q3: Depre 2022 | R3: Depre 2023 | S3: Depre 2024 | T3: Depre s/d Agst 2025 | U3: Acc. Depre s/d Agst 2025
B4: Bangunan | C4: Jalan Sirkuit | D4: Mandalika | E4: Race | F4: Jalan Kawasan Khusus (JKK) Sirkuit Mandalika (PHO 5-10-2021), Kantor Pusat | G4: 44326 | H4: 907693537223 | I4: 360 | J4: 3 | K4: 12 | L4: 12 | M4: 12 | N4: 12 | O4: 2521370937 | P4: 7.5641128e+09 | Q4: 3.0256451e+10 | R4: 3.0256451e+10 | S4: 3.0256451e+10 | T4: -9.455141e+09 | U4: 88878325520 | V4: Kunci saldo s/d 2024, Dampak Perubahan Masa Manfaat pada Tahun Berjalan 2025 (kertas kerja s/d Mei 2025)
B5: Bangunan | C5: Jalan Sirkuit | D5: Mandalika | E5: Race | F5: Jalan Kawasan Khusus (JKK) Sirkuit Mandalika (PHO 5-10-2021), Project Mandalika | G5: 44326 | H5: 199319801280 | I5: 360 | J5: 3 | K5: 12 | L5: 12 | M5: 12 | N5: 12 | O5: 553666115 | P5: 1660998344 | Q5: 6643993376 | R5: 6643993376 | S5: 6643993376 | T5: -2076247930 | U5: 19516730542 | V5: Kunci saldo s/d 2024, Dampak Perubahan Masa Manfaat pada Tahun Berjalan 2025 (kertas kerja s/d Mei 2025)
B6: Sub Total | H6: 1107013338503 | O6: 3075037051 | P6: 9225111154 | Q6: 36900444617 | R6: 36900444617 | S6: 36900444617 | T6: -11531388943 | U6: 108395056062
B9: Kategori Aset | C9: Sub Kategori | D9: Lokasi | E9: Segmen | F9: Detail Pekerjaan | G9: Tgl Perolehan | H9: Nilai Perolehan | I9: Masa Manfaat | J9: 21 | K9: 22 | L9: 23 | M9: 24 | N9: 25 | O9: Depre Per Bulan | P9: Depre 2021 | Q9: Depre 2022 | R9: Depre 2023 | S9: Depre 2024 | T9: Depre s/d Juni 2025 | U9: Acc. Depre s/d Juni 2025
B10: Bangunan | C10: Jalan Sirkuit | D10: Mandalika | E10: Race | F10: Jalan Kawasan Khusus (JKK) Sirkuit Mandalika (PHO 5-10-2021), Kantor Pusat | G10: 44326 | H10: 907693537223 | I10: 480 | J10: 3 | K10: 12 | L10: 12 | M10: 12 | N10: 12 | O10: 1891028203 | P10: 5.6730846e+09 | Q10: 2.2692338e+10 | R10: 2.2692338e+10 | S10: 2.2692338e+10 | T10: 1.5128226e+10 | U10: 88878325520 | V10: Adjustment total dari awal (hitungan baru)
B11: Bangunan | C11: Jalan Sirkuit | D11: Mandalika | E11: Race | F11: Jalan Kawasan Khusus (JKK) Sirkuit Mandalika (PHO 5-10-2021), Project Mandalika | G11: 44326 | H11: 199319801280 | I11: 480 | J11: 3 | K11: 12 | L11: 12 | M11: 12 | N11: 12 | O11: 415249586 | P11: 1245748758 | Q11: 4982995032 | R11: 4982995032 | S11: 4982995032 | T11: 3321996688 | U11: 19516730542 | V11: Adjustment total dari awal (hitungan baru)
H12: 1107013338503 | J12: Beban Depresiasi Re-kalkulasi | O12: 2306277789 | P12: 6918833366 | Q12: 27675333463 | R12: 27675333463 | S12: 27675333463 | T12: 18450222308 | U12: 108395056062
J15: Selisih Beban Depresiasi Per Tahun | P15: 2306277789 | Q15: 9225111154 | R15: 9225111154 | S15: 9225111154 | T15: -29981611251 | U15: 0
P16: v | Q16: v | R16: v | S16: v | T16: v
U17: 0 | V17: 24583366633 | W17: % Item 1 atas Dampak Perubahan Umur, Masuk Tahun berjalan
U18: 0 | V18: 5398244618 | W18: % Item 2 atas Dampak Perubahan Umur, Masuk Tahun berjalan
U19: 0 | V19: 29981611251

Sheet Maintenance History
A1: NO | B1: Description | C1: Month | D1: Amount
B3: Perbaikan
A4: 1 | B4: Pemasangan Floor Tiles, Niro Granite, Lux GLX34, Explosion Bl - Ballroom | C4: 45413 | D4: 32546258
A5: 2 | B5: Floor Tiles, Grandeur GDR04 Pietra Black Hi Gloss - Ballroom | C5: 45413 | D5: 227344965
A6: 3 | B6: Pemasangan Granit GDR04 Pietra Black Hi Gloss 120c Kawan Rinjani Teknik - Ballroom | C6: 45444 | D6: 74602007
A7: 6 | B7: Pembuatan Cover AC - Villa 119 -117 | C7: 45474 | D7: 17316000
A8: 15 | B8: AC, Gree, Mitsubishi, split wall, MS-JR24VF, 2.5PK Villa | C8: 45474 | D8: 50782500
A9: 19 | B9: Air Curtain, kitchen asian, GK-2509YS2-CE, 900x1 | C9: 45474 | D9: 39294000
A10: 20 | B10: Air Curtain, kitchen indonesia, GK-2512AS2-CE, 119 | C10: 45474 | D10: 7326000
A11: 21 | B11: Sliding Glass Door, Living Room, 228x224cm villa | C11: 45474 | D11: 12000000
A12: 22 | B12: Sliding Glass Door, Bed Room, 252x264cm Villa | C12: 45474 | D12: 18907000
A13: 23 | B13: Pintu kaca Swing, Bathroom G116, T251 cm, P262.3 c | C13: 45566 | D13: 18700000
A14: 24 | B14: Sliding Glass Door for Bathroom G109, 110, 111, 112, 113, 115, 116 | C14: 45566 | D14: 112200000
A15: 25 | B15: Sliding Glass Door for Living Room G 109, 110, 111, 112, 113, 115, 116 | C15: 45566 | D15: 59500000
A16: 26 | B16: Instalation UPS PLN | C16: 45597 | D16: 37615000
A17: 27 | B17: Blade, Fan Cooling Tower & Service | C17: December2024 | D17: 27000000
A18: 28 | B18: Blade, Fan Cooling Tower 2 & Service | C18: December2024 | D18: 13500000
A19: 29 | B19: Pulley Fan Cooling Tower, Bearing, Bubut shaft, & | C19: December2024 | D19: 28500000
A20: 30 | B20: Sand Filters, P Series, 145kg, 1.5inch, 0.31m2 | C20: December2024 | D20: 8745000
A21: 31 | B21: Sand Filters, P Series, 145kg, 1.5inch, 0.31m2 | C21: December2024 | D21: 8745000
A22: 32 | B22: Penguatan, Cooling, Tower 2 | C22: December2024 | D22: 9000000
A23: 33 | B23: Sand Filter, Kolam, Emaux P650 | C23: December2024 | D23: 16800000
A24: 34 | B24: Pengerjaan Blade Cooling tower, 24,27,30, & Motor | C24: December2024 | D24: 9000000
A25: 35 | B25: AC for Chill Out & SPA | C25: January2025 | D25: 110573205
A26: 36 | B26: Sand Filter, Kolam, Emaux P650 | C26: January2025 | D26: 8400000
A27: 37 | B27: Sand Filter, Kolam, Emaux P650 | C27: January2025 | D27: 8400000
A28: 38 | B28: Sand Filter, Kolam, Dab V650 | C28: 45689 | D28: 16800000
A29: 40 | B29: Blade cooling Tower, 3 | C29: 45717 | D29: 22000000
A30: 41 | B30: Welding, the cooling tower fan, support frame, CT | C30: 45717 | D30: 4000000
A31: 42 | B31: Preliminary, Cooling Tower 1, & Cooling Tower 3 | C31: 45717 | D31: 3000000
A32: 43 | B32: Patching, of cooling tower, fiber covers, CT 1&3 | C32: 45717 | D32: 6000000
A33: 44 | B33: Addition of cooling fan support frame towers, CT 1 | C33: 45717 | D33: 5000000
A34: 45 | B34: Pembuatan Cover AC | C34: 45717 | D34: 24242400
A35: 56 | B35: AC, Mitsubishi, split wall, MS-JR24VF, 2.5PK | C35: 45748 | D35: 32800500
A36: 60 | B36: Pembelian kayu Ulin untuk penggantian pool deck | D36: 229640180
A37: 61 | B37: Perbaikan pool - injeksi kebocoran | D37: 171540000
B39: TOTAL

Sheet Financial_Statements
B2: PT PENGEMBANGAN PARIWISATA INDONESIA (PERSERO)
B3: KOMPARASI SALDO
D4: 4 | E4: 5 | F4: 6 | G4: 7 | H4: 8 | I4: 9 | J4: 11
D5: KONSOLIDASI | E5: KONSOLIDASI | F5: KONSOLIDASI | G5: KONSOLIDASI | H5: KONSOLIDASI | I5: KONSOLIDASI | J5: KONSOLIDASI
B6: NO. | C6: URAIAN | D6: AUDITED | E6: AUDITED | F6: AUDITED | G6: AUDITED | H6: AUDITED | I6: AUDITED | J6: AUDITED
D7: TAHUN 2018 | E7: TAHUN 2019 | F7: TAHUN 2020 | G7: TAHUN 2021* | H7: TAHUN 2022 | I7: TAHUN 2023 | J7: TAHUN 2024
D8: 7 | E8: 8 | F8: 9 | G8: Penyajian Kembali
B9: A. | C9: LABA (RUGI) KOMPREHENSIF
C10: PENDAPATAN OPERASI
C11: Kompensasi Lahan
A12: LB-R-001 | C12: Kompensasi Minimum | D12: 154250348121 | E12: 164136662173 | F12: 168022939374 | G12: 181564663610 | H12: 237984752684 | I12: 282402822733 | J12: 250532564911
A13: LB-R-002 | C13: Kompensasi Persentase | D13: 68079728829 | E13: 87433983846 | F13: 28218685371 | G13: 1175444403 | H13: 5107184611 | I13: 44680082518 | J13: 122895584306
A14: LB-R-003 | C14: Kompensasi Sekaligus | D14: 4146445105 | E14: 2492644851 | F14: 2482149727 | G14: 2269482203 | H14: 2518238243 | I14: 21279633396 | J14: 19339082396
A15: LB-R-004 | C15: Penggantian Asosiasi | D15: 30090992792 | E15: 30830120393 | F15: 31802859227 | G15: 24259317871 | H15: 36537703976 | I15: 33753722089 | J15: 32904103224 | L15: 4
A16: LB-R-005 | C16: Kompensasi Lainnya | D16: 3705134739 | E16: 4290242594 | F16: 3927361184 | G16: 3793209434 | H16: 4074711680 | I16: 4834387185 | J16: 3480547899
C17: Jumlah Pendapatan Kompensasi Lahan | D17: 260272649587 | E17: 289183653857 | F17: 234453994883 | G17: 213062117521 | H17: 286222591194 | I17: 386950647921 | J17: 429151882737
C19: Pendapatan Tambahan
A20: LB-R-006 | C20: Jasa Pengelolaan Air | D20: 18124376468 | E20: 18178661109 | F20: 5725506882 | G20: 3330691690 | H20: 3105774662 | I20: 12819044201 | J20: 16824536519
A21: LB-R-007 | C21: Pendapatan Lainnya | D21: 11419417405 | E21: 8553223831 | F21: 1452897308 | G21: 6501319391 | H21: 31428678010 | I21: 21826467191 | J21: 10056206241
A22: LB-R-027 | C22: Pendapatan Sirkuit Lainnya | J22: 70427859563
A23: LB-R-014 | C23: Jasa Akomodasi | D23: - | E23: 110743376 | F23: 43066086 | G23: 2128125855 | H23: 4455793824 | I23: 2489584648 | J23: -
A24: LB-R-015 | C24: Pendapatan BBM | D24: - | E24: - | F24: - | G24: 26651076900 | H24: 52428311203 | I24: 68356058786 | J24: 78481732951
A25: LB-R-028 | C25: Pendapatan Aquabike | J25: 30318367056
A26: LB-R-016 | C26: Watersport | D26: - | E26: - | F26: - | G26: - | H26: - | I26: - | J26: -
A27: LB-R-017 | C27: Air Bersih Nusa Dua | D27: - | E27: - | F27: - | G27: - | H27: - | I27: 48355653
A28: LB-R-022 | C28: Air Bersih Mandalika | D28: - | E28: - | F28: - | G28: - | H28: 2510014596 | I28: 3685324009 | J28: 5237085673
A29: LB-R-018 | C29: ICT Nusa Dua | D29: - | E29: - | F29: - | G29: 350000000 | H29: 600000000 | I29: 1190234274
A30: LB-R-023 | C30: ICT Mandalika | E30: - | F30: - | G30: - | H30: 1071284996 | I30: 596040634 | J30: 819485447
A31: LB-R-019 | C31: Agen Distributor | D31: - | E31: - | F31: - | G31: 897363419 | H31: 11433931715 | I31: 1724058742 | J31: 3065132766
A32: LB-R-020 | C32: Jasa Owner Rep | D32: - | E32: - | F32: - | G32: - | H32: - | I32: - | J32: -
A33: LB-R-024 | C33: Pendapatan Penjualan Lahan | J33: 2593762500000
A34: LB-R-025 | C34: Destination Management | J34: -
A35: LB-R-026 | C35: MICE Golo Mori | J35: 1699678128
A36: LB-R-021 | C36: Jasa Pengelolaan (Management Fee) | D36: - | E36: - | F36: - | G36: - | H36: 959039204 | I36: - | J36: -
A37: LB-R-009 | C37: Pendapatan Hotel Pullman | D37: - | E37: - | F37: - | G37: - | H37: 16190010784 | I37: 75301278218 | J37: 104501617428
A38: LB-R-008 | C38: Penyelenggaraan Event MotoGP | D38: - | E38: - | F38: - | G38: - | H38: 194876857906 | I38: 285161655904 | J38: 220771070185
A39: LB-R-010 | C39: Penyelenggaraan Event WSBK | D39: - | E39: - | F39: - | G39: 69862253476 | H39: 52205363844 | I39: 25065061602 | J39: -
C40: Jumlah Pendapatan Tambahan | D40: 29543793872 | E40: 26842628316 | F40: 7221470276 | G40: 109720830731 | H40: 371265060744 | I40: 498263163862 | J40: 3135965271958
C42: Jumlah Pendapatan Operasional | D42: 289816443459 | E42: 316026282173 | F42: 241675465159 | G42: 322782948252 | H42: 657487651938 | I42: 885213811783 | J42: 3565117154694
A44: LB-E-022 | C44: HPP Motogp | D44: - | E44: - | F44: - | G44: - | H44: 209289112225 | I44: 311323528882 | J44: 427652339696
A45: LB-E-023 | C45: HPP WSBK | D45: - | E45: - | F45: - | G45: 216404713145 | H45: 43039168422 | I45: 84204781525 | J45: -
A46: LB-E-024 | C46: HPP Bisnis Lainnya | D46: - | E46: - | F46: - | G46: 289155139 | H46: 31552072981 | I46: 17918366707 | J46: 62115720424
A47: LB-E-032 | C47: BPP Aquabike | J47: 67274538020
A48: LB-E-031 | C48: BPP Penjualan Lahan | J48: 41535935402
A49: LB-E-025 | C49: HPP Hotel | D49: - | E49: - | F49: - | G49: - | H49: 19374800057 | I49: 43478861348 | J49: 55140301161
A50: LB-E-026 | C50: HPP SPBU | D50: - | E50: - | F50: - | G50: 25615283126 | H50: 50471513305 | I50: 66595632631 | J50: 76496154773
A51: LB-E-027 | C51: HPP Watersport | D51: - | E51: - | F51: - | G51: - | H51: - | I51: - | J51: -
A52: LB-E-028 | C52: HPP Akomodasi | D52: - | E52: - | F52: - | G52: - | H52: - | I52: - | J52: -
A53: LB-E-029 | C53: HPP Air Bersih | D53: - | E53: - | F53: - | G53: - | H53: 4104499987 | I53: 3310179685 | J53: 4872710624
A54: LB-E-030 | C54: BPP Golomori | D54: - | E54: - | F54: - | G54: - | H54: - | I54: 5938006248 | J54: 3205314596
C55: HPP Depresiasi | I55: 128544940920 | J55: 218078987293
C56: HARGA POKOK PENJUALAN | D56: - | E56: - | F56: - | G56: 242309151410 | H56: 357831166977 | I56: 661314297946 | J56: 956372001988
C58: LABA (RUGI) KOTOR | D58: 289816443459 | E58: 316026282173 | F58: 241675465159 | G58: 80473796842 | H58: 299656484961 | I58: 223899513837 | J58: 2608745152706
C60: Jumlah Beban Operasi | D60: 201763954920 | E60: 232558258002 | F60: 217863587524 | G60: 234405755433 | H60: 319283729608 | I60: 305165278465 | J60: 545744859628
C62: LABA (RUGI) OPERASI | D62: 88052488539 | E62: 83468024171 | F62: 23811877635 | G62: -153931958591 | H62: -19627244646 | I62: -81265764628 | J62: 2063000293077
C64: Jumlah Pendapatan (Beban) Non Operasional | D64: 14601002068 | E64: -8534333586 | F64: 24890261335 | G64: -1121769607 | H64: -160021149117 | I64: -148089575517 | J64: -251643905874
C66: LABA (RUGI) SEBELUM PAJAK | D66: 102653490607 | E66: 74933690586 | F66: 48702138970 | G66: -155053728197 | H66: -179648393764 | I66: -229355340145 | J66: 1811356387203
C68: MANFAAT (BEBAN) PAJAK PENGHASILAN
A69: LB-E-009 | C69: Pajak Final | D69: 26564646779 | E69: 29060676422 | F69: 21864265041 | G69: 21809304579 | H69: 30502008841 | I69: 49717257119 | J69: 107115165465
A70: LB-E-010 | C70: Pajak Kini | D70: 2919420809 | E70: 2844482782 | F70: 3977487940 | G70: 2636811358 | H70: - | I70: -
A71: LB-E-011 | C71: Pajak Tangguhan | D71: 128347057 | E71: -347205510 | F71: -104276871 | G71: -75655472 | H71: -184035362 | I71: -655124952 | J71: 27669692707
C72: Jumlah Manfaat (Beban) Pajak Penghasilan | D72: 29612414645 | E72: 31557953694 | F72: 25737476110 | G72: 24370460465 | H72: 30317973479 | I72: 49062132167 | J72: 134784858172
C74: LABA (RUGI) BERSIH | D74: 73041075962 | E74: 43375736892 | F74: 22964662860 | G74: -179424188662 | H74: -209966367242 | I74: -278417472312 | J74: 1676571529031
A75: LB-NCI-001 | C75: Diatribusikan ke Kepentingan Pengendali | D75: -164159910883 | E75: -164159910883 | F75: -164159910883 | G75: -164159910883 | H75: -209887974415 | I75: -280492115735 | J75: 1677252400257
A76: LB-NCI-002 | C76: Diatribusikan ke Kepentingan Non Pengendali | D76: 252842226 | E76: 252842226 | F76: 252842226 | G76: 252842226 | H76: -78392827 | I76: 449822131 | J76: -680871225
C78: PENGHASILAN (KERUGIAN) KOMPREHENSIF LAIN
C79: Pos yang Tidak akan direklasifikasi ke Laba (Rugi)
A80: LB-K-012 | C80: Perubahan Nilai Wajar atas Investasi Saham | D80: - | E80: - | F80: 14568022250 | G80: -11235556655 | H80: 1758444000 | I80: 3686578336 | J80: 18309506145
A81: LB-K-014 | C81: Kerugian Pengukuran Kembali atas Liabilitas Imbalan Kerja | D81: 5480581090 | E81: -2862725873 | F81: -5448711 | G81: 3399271825 | H81: 11800325084 | I81: -2061757244 | J81: 2223887942
A82: LB-K-013 | C82: Keuntungan Bersih yang Belum Direalisasi dari kenaikan nilai wajar surat berharga yang tersedia untuk dijual | D82: -2027999875 | E82: -3471900072 | F82: - | G82: - | H82: - | I82: - | J82: -
C84: Pos yang akan direklasifikasi ke Laba (Rugi)
C85: - | D85: - | E85: - | F85: - | G85: - | H85: - | I85: - | J85: -
C87: LABA (RUGI) BERSIH KOMPREHENSIF | D87: 76493657177 | E87: 37041110947 | F87: 37527236399 | G87: -187260473492 | H87: -196407598158 | I87: -276792651220 | J87: 1697104923118
B90: B. | C90: POSISI KEUANGAN
C91: Total Aset Lancar | D91: 383742146744 | E91: 288231254130 | F91: 911647412471 | G91: 1166481162701 | H91: 1012162546480 | I91: 947119548338 | J91: 2800786113862 | L91: 19202308527
C93: Total Nilai Penyertaan | D93: 40454000000 | E93: 40704000000 | F93: 56040000000 | G93: 44675000000 | H93: 46473000000 | I93: 50244712000 | J93: 68952158547
A95: PS-A-020 | C95: PROPERTI INVESTASI | D95: 575863255423 | E95: 575863255423 | F95: 628330825865 | G95: 628330825864 | H95: 628330825865 | I95: 628277091013 | J95: 781429677719
C97: ASET TETAP
A98: PS-A-021 | C98: T a n a h | D98: 4334516103 | E98: 4334516103 | F98: 4334516103 | G98: 4334516100 | H98: 4334516103 | I98: 4334516103 | J98: 4204153475
A99: PS-A-022 | C99: Landscaping & Gardening | D99: 17822445313 | E99: 25657931607 | F99: 26446364632 | G99: 26887278260 | H99: 39182318989 | I99: 39753345821 | J99: 40074239174
A100: PS-A-023 | C100: Bangunan | D100: 148430651452 | E100: 222911155534 | F100: 241090035422 | G100: 1389910855434 | H100: 2415407893753 | I100: 2840089331298 | J100: 4505511813975
A101: PS-A-024 | C101: Mesin dan peralatan | D101: 14539226517 | E101: 16866209103 | F101: 18078013050 | G101: 61424850215 | H101: 257378909618 | I101: 259309639097 | J101: 262612731032
A102: PS-A-025 | C102: Peralatan Kantor dan Rekreasi | D102: 34029717902 | E102: 44374284740 | F102: 48327270521 | G102: 50233323491 | H102: 127945083923 | I102: 138987488213 | J102: 158966732861
A103: PS-A-026 | C103: Perlengkapan Kantor | D103: 6802848112 | E103: 6653574053 | F103: 6757990003 | G103: 6760540003 | H103: 7616491432 | I103: 8251758570 | J103: 9224904077
A104: PS-A-027 | C104: Kendaraan Bermotor | D104: 8658417772 | E104: 12286640351 | F104: 12286640351 | G104: 12286640351 | H104: 12286640351 | I104: 14059541251 | J104: 17278460186
A105: PS-A-028 | C105: Aktiva dalam Penyelesaian | D105: 662092995848 | E105: 838395148832 | F105: 1140422085637 | G105: 2262130794622 | H105: 2359465528610 | I105: 2578967586104 | J105: 1309928874023
C106: Total Aset Tetap | D106: 896710819019 | E106: 1171479460324 | F106: 1497742915719 | G106: 3813968798476 | H106: 5223617382779 | I106: 5883753206455 | J106: 6307801908803
A107: PS-A-029 | C107: Akumulasi Penyusutan | D107: -75494813586 | E107: -94408275856 | F107: -119778147004 | G107: -153067217527 | H107: -256914782264 | I107: -402309259559 | J107: -637902745932
A108: PS-A-030 | C108: Penurunan Nilai | D108: -2134107889 | E108: -2134107889 | F108: -2134107889 | G108: -2134107889 | H108: -2134107888 | I108: -
C109: Nilai Bersih Aset Tetap | D109: 819081897544 | E109: 1074937076579 | F109: 1375830660826 | G109: 3658767473060 | H109: 4964568492627 | I109: 5481443946896 | J109: 5669899162871
C111: BIAYA DITANGGUHKAN | D111: - | E111: - | F111: - | G111: - | H111: - | I111: - | J111: -
C113: ASET LAIN-LAIN
A114: PS-A-031 | C114: Aset Hak-Guna (nilai bersih) | D114: - | E114: - | F114: 510638840 | G114: 219278215268 | H114: 198623599852 | I114: 179468984443 | J114: 169081258293
A115: PS-A-032 | C115: Kas yang Dibatasi Penggunaannya | D115: 2000000000 | E115: 2000000000 | F115: 2000000000 | G115: 2000000000 | H115: 2000000000 | I115: 2000000000 | J115: 2000000000
A116: PS-A-033 | C116: Aset Tidak Berwujud | D116: 11053155606 | E116: 8449383479 | F116: 5553125807 | G116: 6382681054 | H116: 2192741469 | I116: 2271874535 | J116: 6858887266
A117: PS-A-034 | C117: Uang Jaminan | D117: 336850000 | E117: 36850000 | F117: 36850000 | G117: 36850000 | H117: 36850000 | I117: 36850000 | J117: 36850000
A118: PS-A-035 | C118: Surat Berharga - Neto dari Bagian Lancar | D118: 4080385420 | E118: - | F118: - | G118: 2913844422 | H118: 2963797698 | I118: 2820273502 | J118: 2269102750
A119: PS-A-036 | C119: Aset lainnya | D119: 9894374227 | E119: 16106650062 | F119: 1110154627 | G119: 1110154628 | H119: 1110154626 | I119: 1110154626 | J119: 10514859357
A120: PS-A-037 | C120: Cadangan Kerugian Penurunan Nilai | D120: -1000000000 | E120: -1000000000 | F120: -1000000000 | G120: -1000000000 | H120: -1000000000 | I120: -1000000000 | J120: -5500000000
A121: PS-A-038 | C121: Aktiva Pajak Tangguhan | D121: 1366953921 | E121: 1787562659 | F121: 1818214934 | G121: 2067434169 | H121: 1946466546 | I121: 2562908739 | J121: 357116264
...

Sheet ESL_Analysis_Pullman
B2: ECONOMIC SERVICE LIFE (ESL) ANALYSIS - PULLMAN
B4: INPUT ASSUMPTIONS
B6: Inflation Rate (Annual) | D6: {=Inputs!C7} -> 0.0406 | E6: Based on Bank Indonesia historical data
B7: Confidence Level | D7: {=Inputs!C8} -> 0.9 | E7: Used for O&M cost standard deviation calculations
B8: Discount Rate | D8: {=Inputs!C7} -> 0.0406
B9: Analysis Base Year | D9: 2024
B11: ASSET INFORMATION
B13: Asset Category | C13: Total Value (IDR) | D13: Useful Life (Years) | E13: Acquisition Year
B14: Building & Equipment (Pullman) | C14: {='Asset Data Pullman'!G235} -> 768913758683 | D14: {=SUMPRODUCT('Asset Data Pullman'!G3:G234,'Asset Data Pullman'!H3:H234/12)/SUM('Asset Data Pullman'!G3:G234)} -> 30.900719 | E14: 2021
B17: O&M COST STATISTICS
B19: Number of Observations | D19: =COUNT('Maintenance History'!D4:D37) -> 34
B20: Mean Annual O&M Cost | D20: =Inputs!C27 -> 43288824
B21: Standard Deviation (±) | D21: =_xlfn.STDEV.S('Maintenance History'!D4:D37) -> 59501277
B22: Std Dev (%) | D22: =D21/D20 -> 1.3745182
B23: Upper Bound (Mean + StdDev) | D23: =D20+D21 -> 1.027901e+08
B24: Lower Bound (Mean - StdDev) | D24: =D20-D21 -> -16212453
B26: ESL CALCULATION TABLE
B28: Year | C28: Age | D28: Annual Investment Cost (AIC) | E28: Annual O&M Cost (AOC) | F28: Total Annual Cost (TAC) | H28: INTERPRETATION NOTES:
B29: {=D9} -> 2024 | C29: 1 | D29: =C14*(D8*(1+D8)^D14)/((1+D8)^D14-1) -> 4.4115489e+10 | E29: =D20*(1+D6)^(C29-1)*(1+(C29-1)*0.5/D14) -> 43288824 | F29: =D29+E29 -> 4.4158778e+10 | G29: ← Minimum TAC occurs around this age | H29: • TAC (Total Annual Cost) = AIC + AOC
B30: =B29+1 -> 2025 | C30: =C29+1 -> 2 | D30: =D29*(1+D6) -> 4.5906578e+10 | E30: =D20*(1+D6)^(C30-1)*(1+(C30-1)*0.5/D14) -> 45775239 | F30: =D30+E30 -> 4.5952353e+10 | H30: • AIC (Annual Investment Cost) represents capital recovery and depreciation
B31: =B30+1 -> 2026 | C31: =C30+1 -> 3 | D31: =D30*(1+$D$6) -> 4.7770385e+10 | E31: =$D$20*(1+$D$6)^(C31-1)*(1+(C31-1)*0.5/$D$14) -> 48392195 | F31: =D31+E31 -> 4.7818777e+10 | H31: • ESL occurs at the minimum point of the TAC curve
B32: =B31+1 -> 2027 | C32: =C31+1 -> 4 | D32: =D31*(1+$D$6) -> 4.9709863e+10 | E32: =$D$20*(1+$D$6)^(C32-1)*(1+(C32-1)*0.5/$D$14) -> 51146193 | F32: =D32+E32 -> 4.9761009e+10 | H32: • The optimal replacement year is when TAC is minimized
B33: =B32+1 -> 2028 | C33: =C32+1 -> 5 | D33: =D32*(1+$D$6) -> 5.1728083e+10 | E33: =$D$20*(1+$D$6)^(C33-1)*(1+(C33-1)*0.5/$D$14) -> 54044049 | F33: =D33+E33 -> 5.1782127e+10
B34: =B33+1 -> 2029 | C34: =C33+1 -> 6 | D34: =D33*(1+$D$6) -> 5.3828243e+10 | E34: =$D$20*(1+$D$6)^(C34-1)*(1+(C34-1)*0.5/$D$14) -> 57092903 | F34: =D34+E34 -> 5.3885336e+10
B35: =B34+1 -> 2030 | C35: =C34+1 -> 7 | D35: =D34*(1+$D$6) -> 5.601367e+10 | E35: =$D$20*(1+$D$6)^(C35-1)*(1+(C35-1)*0.5/$D$14) -> 60300240 | F35: =D35+E35 -> 5.607397e+10 | H35: MINIMUM TAC ANALYSIS:
B36: =B35+1 -> 2031 | C36: =C35+1 -> 8 | D36: =D35*(1+$D$6) -> 5.8287825e+10 | E36: =$D$20*(1+$D$6)^(C36-1)*(1+(C36-1)*0.5/$D$14) -> 63673903 | F36: =D36+E36 -> 5.8351499e+10 | H36: Minimum TAC Value: | J36: =MIN(F29:F88) -> 4.4158778e+10
B37: =B36+1 -> 2032 | C37: =C36+1 -> 9 | D37: =D36*(1+$D$6) -> 6.0654311e+10 | E37: =$D$20*(1+$D$6)^(C37-1)*(1+(C37-1)*0.5/$D$14) -> 67222111 | F37: =D37+E37 -> 6.0721533e+10 | H37: Year at Minimum TAC: | J37: {=INDEX(B29:B88,MATCH(MIN(F29:F88),F29:F88,0))} -> 2024
B38: =B37+1 -> 2033 | C38: =C37+1 -> 10 | D38: =D37*(1+$D$6) -> 6.3116876e+10 | E38: =$D$20*(1+$D$6)^(C38-1)*(1+(C38-1)*0.5/$D$14) -> 70953476 | F38: =D38+E38 -> 6.3187829e+10 | H38: Asset Age at ESL: | J38: {=INDEX(C29:C88,MATCH(MIN(F29:F88),F29:F88,0))} -> 1
B39: =B38+1 -> 2034 | C39: =C38+1 -> 11 | D39: =D38*(1+$D$6) -> 6.5679421e+10 | E39: =$D$20*(1+$D$6)^(C39-1)*(1+(C39-1)*0.5/$D$14) -> 74877022 | F39: =D39+E39 -> 6.5754298e+10 | H39: Remaining Economic Life: | J39: {=J38} -> 1 | K39: years from base year
B40: =B39+1 -> 2035 | C40: =C39+1 -> 12 | D40: =D39*(1+$D$6) -> 6.8346005e+10 | E40: =$D$20*(1+$D$6)^(C40-1)*(1+(C40-1)*0.5/$D$14) -> 79002203 | F40: =D40+E40 -> 6.8425007e+10
B41: =B40+1 -> 2036 | C41: =C40+1 -> 13 | D41: =D40*(1+$D$6) -> 7.1120853e+10 | E41: =$D$20*(1+$D$6)^(C41-1)*(1+(C41-1)*0.5/$D$14) -> 83338924 | F41: =D41+E41 -> 7.1204192e+10 | H41: ESL RESULTS SUMMARY
B42: =B41+1 -> 2037 | C42: =C41+1 -> 14 | D42: =D41*(1+$D$6) -> 7.400836e+10 | E42: =$D$20*(1+$D$6)^(C42-1)*(1+(C42-1)*0.5/$D$14) -> 87897563 | F42: =D42+E42 -> 7.4096257e+10
B43: =B42+1 -> 2038 | C43: =C42+1 -> 15 | D43: =D42*(1+$D$6) -> 7.7013099e+10 | E43: =$D$20*(1+$D$6)^(C43-1)*(1+(C43-1)*0.5/$D$14) -> 92688991 | F43: =D43+E43 -> 7.7105788e+10 | H43: Asset Category | I43: Assumed Life | J43: ESL (Years) | K43: ESL Year Range | L43: Status
B44: =B43+1 -> 2039 | C44: =C43+1 -> 16 | D44: =D43*(1+$D$6) -> 8.0139831e+10 | E44: =$D$20*(1+$D$6)^(C44-1)*(1+(C44-1)*0.5/$D$14) -> 97724596 | F44: =D44+E44 -> 8.0237555e+10 | H44: Building & Equipment (Pullman) | I44: =TEXT(D14,"0.0")&" years" -> 30.9 years | J44: {=J38} -> 1 | K44: =J37&"-"&(J37+J38) -> 2024-2025 | L44: Within Design Life
B45: =B44+1 -> 2040 | C45: =C44+1 -> 17 | D45: =D44*(1+$D$6) -> 8.3393508e+10 | E45: =$D$20*(1+$D$6)^(C45-1)*(1+(C45-1)*0.5/$D$14) -> 1.0301631e+08 | F45: =D45+E45 -> 8.3496524e+10
B46: =B45+1 -> 2041 | C46: =C45+1 -> 18 | D46: =D45*(1+$D$6) -> 8.6779284e+10 | E46: =$D$20*(1+$D$6)^(C46-1)*(1+(C46-1)*0.5/$D$14) -> 1.0857662e+08 | F46: =D46+E46 -> 8.6887861e+10
B47: =B46+1 -> 2042 | C47: =C46+1 -> 19 | D47: =D46*(1+$D$6) -> 9.0302523e+10 | E47: =$D$20*(1+$D$6)^(C47-1)*(1+(C47-1)*0.5/$D$14) -> 1.1441862e+08 | F47: =D47+E47 -> 9.0416942e+10 | H47: PROPOSED STANDARDS (Chapter VI):
B48: =B47+1 -> 2043 | C48: =C47+1 -> 20 | D48: =D47*(1+$D$6) -> 9.3968806e+10 | E48: =$D$20*(1+$D$6)^(C48-1)*(1+(C48-1)*0.5/$D$14) -> 1.2055602e+08 | F48: =D48+E48 -> 9.4089362e+10 | H48: • Pavement Assets (Runway, Taxiway, Apron): | I48: 60 years | J48: With minimum 4x overlay in 20 years
B49: =B48+1 -> 2044 | C49: =C48+1 -> 21 | D49: =D48*(1+$D$6) -> 9.7783939e+10 | E49: =$D$20*(1+$D$6)^(C49-1)*(1+(C49-1)*0.5/$D$14) -> 1.2700317e+08 | F49: =D49+E49 -> 9.7910943e+10 | H49: • Building Structures (Terminal, Cargo, etc): | I49: 50 years | J49: As per initial design specification
B50: =B49+1 -> 2045 | C50: =C49+1 -> 22 | D50: =D49*(1+$D$6) -> 1.0175397e+11 | E50: =$D$20*(1+$D$6)^(C50-1)*(1+(C50-1)*0.5/$D$14) -> 1.3377512e+08 | F50: =D50+E50 -> 1.0188774e+11
B51: =B50+1 -> 2046 | C51: =C50+1 -> 23 | D51: =D50*(1+$D$6) -> 1.0588518e+11 | E51: =$D$20*(1+$D$6)^(C51-1)*(1+(C51-1)*0.5/$D$14) -> 1.4088759e+08 | F51: =D51+E51 -> 1.0602607e+11 | H51: KEY FINDINGS:
B52: =B51+1 -> 2047 | C52: =C51+1 -> 24 | D52: =D51*(1+$D$6) -> 1.1018412e+11 | E52: =$D$20*(1+$D$6)^(C52-1)*(1+(C52-1)*0.5/$D$14) -> 1.4835709e+08 | F52: =D52+E52 -> 1.1033247e+11 | H52: ✓ ESL calculations show assets can exceed design life with proper O&M
B53: =B52+1 -> 2048 | C53: =C52+1 -> 25 | D53: =D52*(1+$D$6) -> 1.1465759e+11 | E53: =$D$20*(1+$D$6)^(C53-1)*(1+(C53-1)*0.5/$D$14) -> 1.5620089e+08 | F53: =D53+E53 -> 1.1481379e+11 | H53: ✓ Current PT Injourney maintenance strategy effectively extends asset life
B54: =B53+1 -> 2049 | C54: =C53+1 -> 26 | D54: =D53*(1+$D$6) -> 1.1931269e+11 | E54: =$D$20*(1+$D$6)^(C54-1)*(1+(C54-1)*0.5/$D$14) -> 1.6443705e+08 | F54: =D54+E54 -> 1.1947713e+11 | H54: ✓ Pullman Building & Equipment ESL: 1 year vs. 30.9 year design standard
B55: =B54+1 -> 2050 | C55: =C54+1 -> 27 | D55: =D54*(1+$D$6) -> 1.2415679e+11 | E55: =$D$20*(1+$D$6)^(C55-1)*(1+(C55-1)*0.5/$D$14) -> 1.7308451e+08 | F55: =D55+E55 -> 1.2432987e+11 | H55: ✓ Low ESL indicates high initial capital recovery cost relative to O&M
B56: =B55+1 -> 2051 | C56: =C55+1 -> 28 | D56: =D55*(1+$D$6) -> 1.2919755e+11 | E56: =$D$20*(1+$D$6)^(C56-1)*(1+(C56-1)*0.5/$D$14) -> 1.8216309e+08 | F56: =D56+E56 -> 1.2937971e+11
B57: =B56+1 -> 2052 | C57: =C56+1 -> 29 | D57: =D56*(1+$D$6) -> 1.3444297e+11 | E57: =$D$20*(1+$D$6)^(C57-1)*(1+(C57-1)*0.5/$D$14) -> 1.9169355e+08 | F57: =D57+E57 -> 1.3463466e+11
B58: =B57+1 -> 2053 | C58: =C57+1 -> 30 | D58: =D57*(1+$D$6) -> 1.3990136e+11 | E58: =$D$20*(1+$D$6)^(C58-1)*(1+(C58-1)*0.5/$D$14) -> 2.0169761e+08 | F58: =D58+E58 -> 1.4010305e+11
B59: =B58+1 -> 2054 | C59: =C58+1 -> 31 | D59: =D58*(1+$D$6) -> 1.4558135e+11 | E59: =$D$20*(1+$D$6)^(C59-1)*(1+(C59-1)*0.5/$D$14) -> 2.1219803e+08 | F59: =D59+E59 -> 1.4579355e+11
B60: =B59+1 -> 2055 | C60: =C59+1 -> 32 | D60: =D59*(1+$D$6) -> 1.5149195e+11 | E60: =$D$20*(1+$D$6)^(C60-1)*(1+(C60-1)*0.5/$D$14) -> 2.232186e+08 | F60: =D60+E60 -> 1.5171517e+11
B61: =B60+1 -> 2056 | C61: =C60+1 -> 33 | D61: =D60*(1+$D$6) -> 1.5764253e+11 | E61: =$D$20*(1+$D$6)^(C61-1)*(1+(C61-1)*0.5/$D$14) -> 2.3478427e+08 | F61: =D61+E61 -> 1.5787731e+11
B62: =B61+1 -> 2057 | C62: =C61+1 -> 34 | D62: =D61*(1+$D$6) -> 1.6404281e+11 | E62: =$D$20*(1+$D$6)^(C62-1)*(1+(C62-1)*0.5/$D$14) -> 2.4692112e+08 | F62: =D62+E62 -> 1.6428973e+11
B63: =B62+1 -> 2058 | C63: =C62+1 -> 35 | D63: =D62*(1+$D$6) -> 1.7070295e+11 | E63: =$D$20*(1+$D$6)^(C63-1)*(1+(C63-1)*0.5/$D$14) -> 2.5965648e+08 | F63: =D63+E63 -> 1.7096261e+11
B64: =B63+1 -> 2059 | C64: =C63+1 -> 36 | D64: =D63*(1+$D$6) -> 1.7763349e+11 | E64: =$D$20*(1+$D$6)^(C64-1)*(1+(C64-1)*0.5/$D$14) -> 2.7301894e+08 | F64: =D64+E64 -> 1.7790651e+11
B65: =B64+1 -> 2060 | C65: =C64+1 -> 37 | D65: =D64*(1+$D$6) -> 1.8484541e+11 | E65: =$D$20*(1+$D$6)^(C65-1)*(1+(C65-1)*0.5/$D$14) -> 2.8703841e+08 | F65: =D65+E65 -> 1.8513245e+11
B66: =B65+1 -> 2061 | C66: =C65+1 -> 38 | D66: =D65*(1+$D$6) -> 1.9235014e+11 | E66: =$D$20*(1+$D$6)^(C66-1)*(1+(C66-1)*0.5/$D$14) -> 3.0174624e+08 | F66: =D66+E66 -> 1.9265188e+11
B67: =B66+1 -> 2062 | C67: =C66+1 -> 39 | D67: =D66*(1+$D$6) -> 2.0015955e+11 | E67: =$D$20*(1+$D$6)^(C67-1)*(1+(C67-1)*0.5/$D$14) -> 3.171752e+08 | F67: =D67+E67 -> 2.0047673e+11
... B88: =B87+1 -> 2083 | C88: =C87+1 -> 60 | D88: =D87*(1+$D$6) -> 4.6167523e+11 | E88: =$D$20*(1+$D$6)^(C88-1)*(1+(C88-1)*0.5/$D$14) -> 8.8551268e+08 | F88: =D88+E88 -> 4.6256074e+11
B90: METHODOLOGY NOTES
B91: 1. AIC (Annual Investment Cost): Represents capital recovery based on asset value, depreciation, and sinking fund calculations
B92: 2. AOC (Annual O&M Cost): Operating and maintenance costs adjusted for inflation and age deterioration factor
B93: 3. TAC (Total Annual Cost): Sum of AIC and AOC, minimum point indicates optimal economic service life
B94: 4. Inflation Rate: 4.06% based on Bank Indonesia historical data
B95: 5. Age Factor: O&M costs increase with asset age due to deterioration (up to 50% over design life)
B96: 6. Data Source: Maintenance History from actual operations, Asset Data from capitalization records

Sheet Market_Value_Pullman
B2: PULLMAN HOTEL - MARKET VALUE PROJECTION ANALYSIS
B3: Categorical Depreciation Approach (2025-2045)
B4: Baseline Date: July 2025
B5: ="Total Portfolio Value: "&TEXT(D17,"0.0")&" Billion IDR" -> Total Portfolio Value: 644.1 Billion IDR
B7: CATEGORY AGGREGATION SUMMARY
B8: Sub Kategori | C8: Asset Count | D8: Current NBV (B IDR) | E8: Total Acq Cost (B IDR) | F8: Avg Life (Months) | G8: Avg Life (Years) | H8: Current Depre % | I8: Remaining Life (Months) | J8: Remaining Life (Years) | K8: Annual Depre (B IDR) | L8: Monthly Depre (B IDR)
B9: Bangunan | C9: =COUNTIF('Asset Data Pullman'!$C$3:$C$234,B9) -> 10 | D9: =SUMIF('Asset Data Pullman'!$C$3:$C$234,B9,'Asset Data Pullman'!$S$3:$S$234)/1000000000 -> 507.38318 | E9: =SUMIF('Asset Data Pullman'!$C$3:$C$234,B9,'Asset Data Pullman'!$G$3:$G$234)/1000000000 -> 548.30332 | F9: 475.83082 | G9: =F9/12 -> 39.652569 | H9: =IF(E9>0,(E9-D9)/E9,0) -> 0.074630463 | I9: =F9*(1-H9) -> 440.31935 | J9: =I9/12 -> 36.693279 | K9: =IF(J9>0,D9/J9,0) -> 13.827687 | L9: =K9/12 -> 1.1523073
B10: Mesin | C10: =COUNTIF('Asset Data Pullman'!$C$3:$C$234,B10) -> 1 | D10: =SUMIF('Asset Data Pullman'!$C$3:$C$234,B10,'Asset Data Pullman'!$S$3:$S$234)/1000000000 -> 121.87595 | E10: =SUMIF('Asset Data Pullman'!$C$3:$C$234,B10,'Asset Data Pullman'!$G$3:$G$234)/1000000000 -> 195.00153 | F10: 96 | G10: =F10/12 -> 8 | H10: =IF(E10>0,(E10-D10)/E10,0) -> 0.375 | I10: =F10*(1-H10) -> 60 | J10: =I10/12 -> 5 | K10: =IF(J10>0,D10/J10,0) -> 24.375191 | L10: =K10/12 -> 2.0312659
B11: Landscape | C11: =COUNTIF('Asset Data Pullman'!$C$3:$C$234,B11) -> 1 | D11: =SUMIF('Asset Data Pullman'!$C$3:$C$234,B11,'Asset Data Pullman'!$S$3:$S$234)/1000000000 -> 9.1371862 | E11: =SUMIF('Asset Data Pullman'!$C$3:$C$234,B11,'Asset Data Pullman'!$G$3:$G$234)/1000000000 -> 9.8780392 | F11: 480 | G11: =F11/12 -> 40 | H11: =IF(E11>0,(E11-D11)/E11,0) -> 0.075 | I11: =F11*(1-H11) -> 444 | J11: =I11/12 -> 37 | K11: =IF(J11>0,D11/J11,0) -> 0.24695098 | L11: =K11/12 -> 0.020579248
B12: Peralatan | C12: =COUNTIF('Asset Data Pullman'!$C$3:$C$234,B12) -> 136 | D12: =SUMIF('Asset Data Pullman'!$C$3:$C$234,B12,'Asset Data Pullman'!$S$3:$S$234)/1000000000 -> 4.1153555 | E12: =SUMIF('Asset Data Pullman'!$C$3:$C$234,B12,'Asset Data Pullman'!$G$3:$G$234)/1000000000 -> 12.568145 | F12: 48 | G12: =F12/12 -> 4 | H12: =IF(E12>0,(E12-D12)/E12,0) -> 0.67255664 | I12: =F12*(1-H12) -> 15.717281 | J12: =I12/12 -> 1.3097734 | K12: =IF(J12>0,D12/J12,0) -> 3.1420361 | L12: =K12/12 -> 0.26183635
B13: Perlengkapan | C13: =COUNTIF('Asset Data Pullman'!$C$3:$C$234,B13) -> 79 | D13: =SUMIF('Asset Data Pullman'!$C$3:$C$234,B13,'Asset Data Pullman'!$S$3:$S$234)/1000000000 -> 0.90372445 | E13: =SUMIF('Asset Data Pullman'!$C$3:$C$234,B13,'Asset Data Pullman'!$G$3:$G$234)/1000000000 -> 1.9463425 | F13: 48 | G13: =F13/12 -> 4 | H13: =IF(E13>0,(E13-D13)/E13,0) -> 0.53568066 | I13: =F13*(1-H13) -> 22.287328 | J13: =I13/12 -> 1.8572774 | K13: =IF(J13>0,D13/J13,0) -> 0.48658562 | L13: =K13/12 -> 0.040548801
B14: Kendaraan | C14: =COUNTIF('Asset Data Pullman'!$C$3:$C$234,B14) -> 1 | D14: =SUMIF('Asset Data Pullman'!$C$3:$C$234,B14,'Asset Data Pullman'!$S$3:$S$234)/1000000000 -> 0.18253333 | E14: =SUMIF('Asset Data Pullman'!$C$3:$C$234,B14,'Asset Data Pullman'!$G$3:$G$234)/1000000000 -> 0.296 | F14: 60 | G14: =F14/12 -> 5 | H14: =IF(E14>0,(E14-D14)/E14,0) -> 0.38333333 | I14: =F14*(1-H14) -> 37 | J14: =I14/12 -> 3.0833333 | K14: =IF(J14>0,D14/J14,0) -> 0.0592 | L14: =K14/12 -> 0.0049333333
B15: Lisensi | C15: =COUNTIF('Asset Data Pullman'!$C$3:$C$234,B15) -> 1 | D15: =SUMIF('Asset Data Pullman'!$C$3:$C$234,B15,'Asset Data Pullman'!$S$3:$S$234)/1000000000 -> 0.024963438 | E15: =SUMIF('Asset Data Pullman'!$C$3:$C$234,B15,'Asset Data Pullman'!$G$3:$G$234)/1000000000 -> 0.070485 | F15: 48 | G15: =F15/12 -> 4 | H15: =IF(E15>0,(E15-D15)/E15,0) -> 0.64583333 | I15: =F15*(1-H15) -> 17 | J15: =I15/12 -> 1.4166667 | K15: =IF(J15>0,D15/J15,0) -> 0.01762125 | L15: =K15/12 -> 0.0014684375
B16: Sistem | C16: =COUNTIF('Asset Data Pullman'!$C$3:$C$234,B16) -> 3 | D16: =SUMIF('Asset Data Pullman'!$C$3:$C$234,B16,'Asset Data Pullman'!$S$3:$S$234)/1000000000 -> 0.50359222 | E16: =SUMIF('Asset Data Pullman'!$C$3:$C$234,B16,'Asset Data Pullman'!$G$3:$G$234)/1000000000 -> 0.84990438 | F16: 48 | G16: =F16/12 -> 4 | H16: =IF(E16>0,(E16-D16)/E16,0) -> 0.40747191 | I16: =F16*(1-H16) -> 28.441348 | J16: =I16/12 -> 2.3701124 | K16: =IF(J16>0,D16/J16,0) -> 0.21247609 | L16: =K16/12 -> 0.017706341
B17: TOTAL PORTFOLIO | C17: =SUM(C9:C16) -> 232 | D17: =SUM(D9:D16) -> 644.12649 | E17: =SUM(E9:E16) -> 768.91376 | F17: =SUMPRODUCT(E9:E16,F9:F16)/SUM(E9:E16) -> 370.80863 | G17: =F17/12 -> 30.900719 | H17: =(E17-D17)/E17 -> 0.16229032 | I17: =SUMPRODUCT(E9:E16,I9:I16)/SUM(E9:E16) -> 335.26743 | J17: =I17/12 -> 27.938952 | K17: =SUM(K9:K16) -> 42.367748 | L17: =K17/12 -> 3.5306457
B19: MARKET VALUE PROJECTION BY CATEGORY (2025-2045)
B20: Year | C20: Bangunan | D20: Mesin | E20: Landscape | F20: Peralatan | G20: Perlengkapan | H20: Kendaraan | I20: Lisensi | J20: Sistem | K20: Total Portfolio | L20: % of Original
B21: 2025 | C21: =MAX(0,D9-(K9*(B21-2025))) -> 507.38318 | D21: =MAX(0,D10-(K10*(B21-2025))) -> 121.87595 | E21: =MAX(0,D11-(K11*(B21-2025))) -> 9.1371862 | F21: =MAX(0,D12-(K12*(B21-2025))) -> 4.1153555 | G21: =MAX(0,D13-(K13*(B21-2025))) -> 0.90372445 | H21: =MAX(0,D14-(K14*(B21-2025))) -> 0.18253333 | I21: =MAX(0,D15-(K15*(B21-2025))) -> 0.024963438 | J21: =MAX(0,D16-(K16*(B21-2025))) -> 0.50359222 | K21: =SUM(C21:J21) -> 644.12649 | L21: =K21/D17 -> 1
B22: 2026 | C22: =MAX(0,D9-(K9*(B22-2025))) -> 493.5555 | D22: =MAX(0,D10-(K10*(B22-2025))) -> 97.500764 | E22: =MAX(0,D11-(K11*(B22-2025))) -> 8.8902353 | F22: =MAX(0,D12-(K12*(B22-2025))) -> 0.97331931 | G22: =MAX(0,D13-(K13*(B22-2025))) -> 0.41713883 | H22: =MAX(0,D14-(K14*(B22-2025))) -> 0.12333333 | I22: =MAX(0,D15-(K15*(B22-2025))) -> 0.007342188 | J22: =MAX(0,D16-(K16*(B22-2025))) -> 0.29111612 | K22: =SUM(C22:J22) -> 601.75875 | L22: =K22/D17 -> 0.93422449
B23: 2027 | C23: =MAX(0,D9-(K9*(B23-2025))) -> 479.72781 | D23: =MAX(0,D10-(K10*(B23-2025))) -> 73.125573 | E23: =MAX(0,D11-(K11*(B23-2025))) -> 8.6432843 | F23: =MAX(0,D12-(K12*(B23-2025))) -> 0 | G23: =MAX(0,D13-(K13*(B23-2025))) -> 0 | H23: =MAX(0,D14-(K14*(B23-2025))) -> 0.064133333 | I23: =MAX(0,D15-(K15*(B23-2025))) -> 0 | J23: =MAX(0,D16-(K16*(B23-2025))) -> 0.078640029 | K23: =SUM(C23:J23) -> 561.63944 | L23: =K23/D17 -> 0.87193967
B24: 2028 | C24: =MAX(0,D9-(K9*(B24-2025))) -> 465.90012 | D24: =MAX(0,D10-(K10*(B24-2025))) -> 48.750382 | E24: =MAX(0,D11-(K11*(B24-2025))) -> 8.3963333 | F24: =MAX(0,D12-(K12*(B24-2025))) -> 0 | G24: =MAX(0,D13-(K13*(B24-2025))) -> 0 | H24: =MAX(0,D14-(K14*(B24-2025))) -> 0.004933333 | I24: =MAX(0,D15-(K15*(B24-2025))) -> 0 | J24: =MAX(0,D16-(K16*(B24-2025))) -> 0 | K24: =SUM(C24:J24) -> 523.05177 | L24: =K24/D17 -> 0.81203269
B25: 2029 | C25: =MAX(0,D9-(K9*(B25-2025))) -> 452.07244 | D25: =MAX(0,D10-(K10*(B25-2025))) -> 24.375191 | E25: =MAX(0,D11-(K11*(B25-2025))) -> 8.1493823 | F25: =MAX(0,D12-(K12*(B25-2025))) -> 0 | G25: =MAX(0,D13-(K13*(B25-2025))) -> 0 | H25: =MAX(0,D14-(K14*(B25-2025))) -> 0 | I25: =MAX(0,D15-(K15*(B25-2025))) -> 0 | J25: =MAX(0,D16-(K16*(B25-2025))) -> 0 | K25: =SUM(C25:J25) -> 484.59701 | L25: =K25/D17 -> 0.75233205
B26: 2030 | C26: =MAX(0,D9-(K9*(B26-2025))) -> 438.24475 | D26: =MAX(0,D10-(K10*(B26-2025))) -> 3.7499603e-10 | E26: =MAX(0,D11-(K11*(B26-2025))) -> 7.9024313 | F26: =MAX(0,D12-(K12*(B26-2025))) -> 0 | G26: =MAX(0,D13-(K13*(B26-2025))) -> 0 | H26: =MAX(0,D14-(K14*(B26-2025))) -> 0 | I26: =MAX(0,D15-(K15*(B26-2025))) -> 0 | J26: =MAX(0,D16-(K16*(B26-2025))) -> 0 | K26: =SUM(C26:J26) -> 446.14718 | L26: =K26/D17 -> 0.69263908
B27: 2031 | C27: =MAX(0,D9-(K9*(B27-2025))) -> 424.41706 | D27: =MAX(0,D10-(K10*(B27-2025))) -> 0 | E27: =MAX(0,D11-(K11*(B27-2025))) -> 7.6554804 | F27: =MAX(0,D12-(K12*(B27-2025))) -> 0 | G27: =MAX(0,D13-(K13*(B27-2025))) -> 0 | H27: =MAX(0,D14-(K14*(B27-2025))) -> 0 | I27: =MAX(0,D15-(K15*(B27-2025))) -> 0 | J27: =MAX(0,D16-(K16*(B27-2025))) -> 0 | K27: =SUM(C27:J27) -> 432.07254 | L27: =K27/D17 -> 0.67078834
B28: 2032 | C28: =MAX(0,D9-(K9*(B28-2025))) -> 410.58937 | D28: =MAX(0,D10-(K10*(B28-2025))) -> 0 | E28: =MAX(0,D11-(K11*(B28-2025))) -> 7.4085294 | F28: =MAX(0,D12-(K12*(B28-2025))) -> 0 | G28: =MAX(0,D13-(K13*(B28-2025))) -> 0 | H28: =MAX(0,D14-(K14*(B28-2025))) -> 0 | I28: =MAX(0,D15-(K15*(B28-2025))) -> 0 | J28: =MAX(0,D16-(K16*(B28-2025))) -> 0 | K28: =SUM(C28:J28) -> 417.9979 | L28: =K28/D17 -> 0.6489376
B29: 2033 | C29: =MAX(0,D9-(K9*(B29-2025))) -> 396.76169 | D29: =MAX(0,D10-(K10*(B29-2025))) -> 0 | E29: =MAX(0,D11-(K11*(B29-2025))) -> 7.1615784 | F29: =MAX(0,D12-(K12*(B29-2025))) -> 0 | G29: =MAX(0,D13-(K13*(B29-2025))) -> 0 | H29: =MAX(0,D14-(K14*(B29-2025))) -> 0 | I29: =MAX(0,D15-(K15*(B29-2025))) -> 0 | J29: =MAX(0,D16-(K16*(B29-2025))) -> 0 | K29: =SUM(C29:J29) -> 403.92327 | L29: =K29/D17 -> 0.62708687
B30: 2034 | C30: =MAX(0,D9-(K9*(B30-2025))) -> 382.934 | D30: =MAX(0,D10-(K10*(B30-2025))) -> 0 | E30: =MAX(0,D11-(K11*(B30-2025))) -> 6.9146274 | F30: =MAX(0,D12-(K12*(B30-2025))) -> 0 | G30: =MAX(0,D13-(K13*(B30-2025))) -> 0 | H30: =MAX(0,D14-(K14*(B30-2025))) -> 0 | I30: =MAX(0,D15-(K15*(B30-2025))) -> 0 | J30: =MAX(0,D16-(K16*(B30-2025))) -> 0 | K30: =SUM(C30:J30) -> 389.84863 | L30: =K30/D17 -> 0.60523613
B31: 2035 | C31: =MAX(0,D9-(K9*(B31-2025))) -> 369.10631 | D31: =MAX(0,D10-(K10*(B31-2025))) -> 0 | E31: =MAX(0,D11-(K11*(B31-2025))) -> 6.6676765 | F31: =MAX(0,D12-(K12*(B31-2025))) -> 0 | G31: =MAX(0,D13-(K13*(B31-2025))) -> 0 | H31: =MAX(0,D14-(K14*(B31-2025))) -> 0 | I31: =MAX(0,D15-(K15*(B31-2025))) -> 0 | J31: =MAX(0,D16-(K16*(B31-2025))) -> 0 | K31: =SUM(C31:J31) -> 375.77399 | L31: =K31/D17 -> 0.58338539
B32: 2036 | C32: =MAX(0,D9-(K9*(B32-2025))) -> 355.27863 | D32: =MAX(0,D10-(K10*(B32-2025))) -> 0 | E32: =MAX(0,D11-(K11*(B32-2025))) -> 6.4207255 | F32: =MAX(0,D12-(K12*(B32-2025))) -> 0 | G32: =MAX(0,D13-(K13*(B32-2025))) -> 0 | H32: =MAX(0,D14-(K14*(B32-2025))) -> 0 | I32: =MAX(0,D15-(K15*(B32-2025))) -> 0 | J32: =MAX(0,D16-(K16*(B32-2025))) -> 0 | K32: =SUM(C32:J32) -> 361.69935 | L32: =K32/D17 -> 0.56153466
B33: 2037 | C33: =MAX(0,D9-(K9*(B33-2025))) -> 341.45094 | D33: =MAX(0,D10-(K10*(B33-2025))) -> 0 | E33: =MAX(0,D11-(K11*(B33-2025))) -> 6.1737745 | F33: =MAX(0,D12-(K12*(B33-2025))) -> 0 | G33: =MAX(0,D13-(K13*(B33-2025))) -> 0 | H33: =MAX(0,D14-(K14*(B33-2025))) -> 0 | I33: =MAX(0,D15-(K15*(B33-2025))) -> 0 | J33: =MAX(0,D16-(K16*(B33-2025))) -> 0 | K33: =SUM(C33:J33) -> 347.62471 | L33: =K33/D17 -> 0.53968392
B34: 2038 | C34: =MAX(0,D9-(K9*(B34-2025))) -> 327.62325 | D34: =MAX(0,D10-(K10*(B34-2025))) -> 0 | E34: =MAX(0,D11-(K11*(B34-2025))) -> 5.9268235 | F34: =MAX(0,D12-(K12*(B34-2025))) -> 0 | G34: =MAX(0,D13-(K13*(B34-2025))) -> 0 | H34: =MAX(0,D14-(K14*(B34-2025))) -> 0 | I34: =MAX(0,D15-(K15*(B34-2025))) -> 0 | J34: =MAX(0,D16-(K16*(B34-2025))) -> 0 | K34: =SUM(C34:J34) -> 333.55007 | L34: =K34/D17 -> 0.51783319
B35: 2039 | C35: =MAX(0,D9-(K9*(B35-2025))) -> 313.79556 | D35: =MAX(0,D10-(K10*(B35-2025))) -> 0 | E35: =MAX(0,D11-(K11*(B35-2025))) -> 5.6798725 | F35: =MAX(0,D12-(K12*(B35-2025))) -> 0 | G35: =MAX(0,D13-(K13*(B35-2025))) -> 0 | H35: =MAX(0,D14-(K14*(B35-2025))) -> 0 | I35: =MAX(0,D15-(K15*(B35-2025))) -> 0 | J35: =MAX(0,D16-(K16*(B35-2025))) -> 0 | K35: =SUM(C35:J35) -> 319.47544 | L35: =K35/D17 -> 0.49598245
B36: 2040 | C36: =MAX(0,D9-(K9*(B36-2025))) -> 299.96788 | D36: =MAX(0,D10-(K10*(B36-2025))) -> 0 | E36: =MAX(0,D11-(K11*(B36-2025))) -> 5.4329216 | F36: =MAX(0,D12-(K12*(B36-2025))) -> 0 | G36: =MAX(0,D13-(K13*(B36-2025))) -> 0 | H36: =MAX(0,D14-(K14*(B36-2025))) -> 0 | I36: =MAX(0,D15-(K15*(B36-2025))) -> 0 | J36: =MAX(0,D16-(K16*(B36-2025))) -> 0 | K36: =SUM(C36:J36) -> 305.4008 | L36: =K36/D17 -> 0.47413171
B37: 2041 | C37: =MAX(0,D9-(K9*(B37-2025))) -> 286.14019 | D37: =MAX(0,D10-(K10*(B37-2025))) -> 0 | E37: =MAX(0,D11-(K11*(B37-2025))) -> 5.1859706 | F37: =MAX(0,D12-(K12*(B37-2025))) -> 0 | G37: =MAX(0,D13-(K13*(B37-2025))) -> 0 | H37: =MAX(0,D14-(K14*(B37-2025))) -> 0 | I37: =MAX(0,D15-(K15*(B37-2025))) -> 0 | J37: =MAX(0,D16-(K16*(B37-2025))) -> 0 | K37: =SUM(C37:J37) -> 291.32616 | L37: =K37/D17 -> 0.45228098
B38: 2042 | C38: =MAX(0,D9-(K9*(B38-2025))) -> 272.3125 | D38: =MAX(0,D10-(K10*(B38-2025))) -> 0 | E38: =MAX(0,D11-(K11*(B38-2025))) -> 4.9390196 | F38: =MAX(0,D12-(K12*(B38-2025))) -> 0 | G38: =MAX(0,D13-(K13*(B38-2025))) -> 0 | H38: =MAX(0,D14-(K14*(B38-2025))) -> 0 | I38: =MAX(0,D15-(K15*(B38-2025))) -> 0 | J38: =MAX(0,D16-(K16*(B38-2025))) -> 0 | K38: =SUM(C38:J38) -> 277.25152 | L38: =K38/D17 -> 0.43043024
B39: 2043 | C39: =MAX(0,D9-(K9*(B39-2025))) -> 258.48481 | D39: =MAX(0,D10-(K10*(B39-2025))) -> 0 | E39: =MAX(0,D11-(K11*(B39-2025))) -> 4.6920686 | F39: =MAX(0,D12-(K12*(B39-2025))) -> 0 | G39: =MAX(0,D13-(K13*(B39-2025))) -> 0 | H39: =MAX(0,D14-(K14*(B39-2025))) -> 0 | I39: =MAX(0,D15-(K15*(B39-2025))) -> 0 | J39: =MAX(0,D16-(K16*(B39-2025))) -> 0 | K39: =SUM(C39:J39) -> 263.17688 | L39: =K39/D17 -> 0.4085795
B40: 2044 | C40: =MAX(0,D9-(K9*(B40-2025))) -> 244.65713 | D40: =MAX(0,D10-(K10*(B40-2025))) -> 0 | E40: =MAX(0,D11-(K11*(B40-2025))) -> 4.4451176 | F40: =MAX(0,D12-(K12*(B40-2025))) -> 0 | G40: =MAX(0,D13-(K13*(B40-2025))) -> 0 | H40: =MAX(0,D14-(K14*(B40-2025))) -> 0 | I40: =MAX(0,D15-(K15*(B40-2025))) -> 0 | J40: =MAX(0,D16-(K16*(B40-2025))) -> 0 | K40: =SUM(C40:J40) -> 249.10225 | L40: =K40/D17 -> 0.38672877
B41: 2045 | C41: =MAX(0,D9-(K9*(B41-2025))) -> 230.82944 | D41: =MAX(0,D10-(K10*(B41-2025))) -> 0 | E41: =MAX(0,D11-(K11*(B41-2025))) -> 4.1981667 | F41: =MAX(0,D12-(K12*(B41-2025))) -> 0 | G41: =MAX(0,D13-(K13*(B41-2025))) -> 0 | H41: =MAX(0,D14-(K14*(B41-2025))) -> 0 | I41: =MAX(0,D15-(K15*(B41-2025))) -> 0 | J41: =MAX(0,D16-(K16*(B41-2025))) -> 0 | K41: =SUM(C41:J41) -> 235.02761 | L41: =K41/D17 -> 0.36487803
B43: KEY METRICS & MILESTONES
B44: Current Total Market Value (July 2025): | C44: {=K21} -> 644.12649
B45: Projected Value - 2030: | C45: {=K26} -> 446.14718
B46: Projected Value - 2035: | C46: {=K31} -> 375.77399
B47: Projected Value - 2040: | C47: {=K36} -> 305.4008
B48: Projected Value - 2045: | C48: {=K41} -> 235.02761
B50: Total Depreciation (2025-2045): | C50: =K21-K41 -> 409.09889
B51: Total Depreciation %: | C51: =(K21-K41)/K21 -> 0.63512197
B52: Average Annual Depreciation: | C52: =(K21-K41)/20 -> 20.454944
B53: Average Annual Depreciation Rate: | C53: =((K21-K41)/K21)/20 -> 0.031756098
B55: ASSET REPLACEMENT REQUIREMENTS BY DECADE
B56: Period | C56: Years | D56: Market Value Decline (B IDR) | E56: % of Total Value Lost | F56: Primary Categories Affected
B57: 2025-2030 | C57: 2025-2030 | D57: =K21-K26 -> 197.97931 | E57: =(K21-K26)/K21 -> 0.30736092 | F57: Equipment, Perlengkapan, Systems
B58: 2030-2035 | C58: 2030-2035 | D58: =K26-K31 -> 70.373191 | E58: =(K26-K31)/K21 -> 0.10925368 | F58: Machinery fully depreciated
B59: 2035-2040 | C59: 2035-2040 | D59: =K31-K36 -> 70.373191 | E59: =(K31-K36)/K21 -> 0.10925368 | F59: Continued building decline
B60: 2040-2045 | C60: 2040-2045 | D60: =K36-K41 -> 70.373191 | E60: =(K36-K41)/K21 -> 0.10925368 | F60: Buildings & Landscape only
B62: Total 2025-2045 | C62: 20 years | D62: =K21-K41 -> 409.09889 | E62: =(K21-K41)/K21 -> 0.63512197 | F62: All categories
B64: METHODOLOGY & NOTES
B65: 1. Baseline: July 2025 Net Book Value of 644.1 Billion IDR
B66: 2. Depreciation Method: Straight-line depreciation based on weighted average remaining useful life per category
B67: 3. Category Weighting: Average useful life calculated using acquisition cost as weight factor
B68: 4. Remaining Life: Calculated as Average Life × (1 - Current Depreciation %)
B69: 5. Market Value Floor: All projections floored at zero (assets cannot have negative value)
B71: Key Findings:
B72: • Short-lived assets (Equipment, Perlengkapan, Systems, Lisensi) depreciate within 5 years (by 2029-2030)
B73: • Machinery (96-month life) fully depreciates by 2030
B74: • Buildings and Landscape (40-year useful life) drive long-term portfolio value
B75: • Portfolio retains ~36.5% of current value by 2045
B76: • Most aggressive depreciation occurs 2025-2030 (30.7% value loss)
B77: • Replacement priority: Equipment/Systems (immediate), Machinery (2028-2030), Buildings (2040+)

Sheet Executive_Summary
B2: EXECUTIVE SUMMARY
B3: Asset Life Extension Analysis - Building Assets
B5: EXECUTIVE OVERVIEW
B6: This analysis evaluates the financial impact of extending building asset useful life from the current 40-year standard to 50 or 75 years, based on industry benchmarks and asset condition assessments. The extension would reduce annual depreciation expense, improving EBITDA and Net Income over a 10-year projection period (2025-2034).
B8: KEY FINANCIAL METRICS (10-YEAR TOTALS)
B9: Metric | C9: Current (40yr) | D9: Realistic (50yr) | E9: Benefit
B10: Building Assets - Original Cost | C10: =Depreciation_Scenario_Analysis!E30/1000000000 -> 548.30332 | D10: {=C10} -> 548.30332 | E10: IDR Billions
B11: Total Depreciation (2025-2034) | C11: {=Financial_Impact_Dashboard!M12} -> 138.99673 | D11: {=Financial_Impact_Dashboard!M13} -> 108.223 | E11: {=Financial_Impact_Dashboard!M18} -> 30.773734
B12: EBITDA Improvement | C12: Baseline | D12: {=Financial_Impact_Dashboard!M23} -> 30.773734 | E12: {=D12} -> 30.773734
B13: Net Income Improvement (After Tax) | C13: Baseline | D13: {=Financial_Impact_Dashboard!M28} -> 24.003513 | E13: {=D13} -> 24.003513
B14: NPV of Savings @ 10% Discount | C14: N/A | D14: =Sensitivity_Analysis!F15/1000000000 -> 1474.9119 | E14: {=D14} -> 1474.9119
B15: Depreciation Savings % | C15: 0 | D15: {=Financial_Impact_Dashboard!D42} -> 0.22139898 | E15: {=D15} -> 0.22139898
B17: RECOMMENDATION
B18: RECOMMENDED SCENARIO: 50-YEAR USEFUL LIFE (REALISTIC)
B19: Rationale:
B20: • Industry Standard: 50-year life aligns with commercial real estate industry standards
B21: • Asset Condition: Maintenance history supports extended useful life (see Maintenance History sheet)
B22: • Material Benefit: IDR 30.8 billion savings over 10 years (22.1% reduction)
B23: • Conservative Approach: More defensible than 75-year extension for audit purposes
B24: • Immediate Impact: Improves 2025 EBITDA by IDR 3.1 billion annually
B26: IMPLEMENTATION TIMELINE
B27: Phase | C27: Action | D27: Responsible | E27: Timeline
B28: 1. Policy Approval | C28: Board/Management approval of accounting policy change | D28: CFO / Finance | E28: Q4 2024
B29: 2. Documentation | C29: Document rationale, asset condition, industry benchmarks | D29: Finance / Engineering | E29: Q4 2024
B30: 3. System Update | C30: Update asset management system with new useful life parameters | D30: IT / Finance | E30: Dec 2024
B31: 4. Implementation | C31: Apply new depreciation rates effective January 1, 2025 | D31: Finance | E31: Jan 1, 2025
B32: 5. Disclosure | C32: Update financial statement footnotes for accounting policy change | D32: Finance / Audit | E32: Q1 2025
B34: RISK CONSIDERATIONS & MITIGATION
B35: Risk | C35: Mitigation
B36: Auditor Challenge | C36: Document asset condition assessments, maintenance records, and industry comparables
B37: Stakeholder Perception | C37: Communicate as industry alignment, not earnings manipulation
B38: Future Impairment Risk | C38: Annual impairment testing, maintain strong maintenance program
B39: Tax Authority Review | C39: Ensure consistent treatment for tax vs book purposes, document rationale
B41: DATA SOURCES & SUPPORTING DOCUMENTATION
B42: Source | C42: Reference
B43: Building Asset Data | C43: Asset Data Pullman sheet, rows 221-230 (10 building assets)
B44: Historical Financials | C44: Financial_Statements sheet, 2018-2024 depreciation (row 228)
B45: Industry Benchmark | C45: Asset Data Circuit Mandalika sheet, 480-month (40-year) precedent
B46: Asset Condition | C46: Maintenance History sheet, supporting extended life assessment
B47: Calculation Models | C47: See detailed sheets: Depreciation_Scenario_Analysis, Financial_Impact_Dashboard
B49: KEY ASSUMPTIONS & METHODOLOGY
B50: • Accumulated depreciation through Dec 31, 2024 is locked - no retroactive adjustments
B51: • New depreciation rates apply prospectively from Jan 1, 2025
B52: • Remaining useful life calculated as: New Total Life - Months Used Through 2024
B53: • Tax rate: 22% applied to calculate after-tax Net Income impact
B54: • Discount rate: 10% WACC for NPV calculations
B55: • Other assets (non-building) maintain current depreciation schedules
B56: • Straight-line depreciation method, no salvage value assumed
B58: RECOMMENDED NEXT STEPS
B59: 1. Review analysis with CFO and Finance Leadership
B60: 2. Engage external auditors for preliminary feedback on 50-year life extension
B61: 3. Obtain engineering/technical assessment supporting extended useful life
... B70: MAINTENANCE COST TRAJECTORY
B71: Metric | C71: Baseline (40yr) | D71: Realistic (50yr) | E71: Variance
B72: 10-Yr Maintenance Capex (IDR B) | C72: {=Financial_Impact_Dashboard!M60} -> 0.54051947 | D72: {=Financial_Impact_Dashboard!M64} -> 0.54051947 | E72: =D72-C72 -> 0
B73: Annual Average Maintenance | C73: {=Financial_Impact_Dashboard!N60} -> 0.054051947 | D73: {=Financial_Impact_Dashboard!N64} -> 0.054051947 | E73: =D73-C73 -> 0
B74: Key Finding: Maintenance costs remain flat in 10-year window (assets age 25-34 years)
B76: FREE CASH FLOW NPV ANALYSIS @ 10% DISCOUNT RATE
B77: Scenario | C77: 10-Yr FCF Total | D77: NPV @ 10% | E77: NPV Benefit
B78: Realistic (50yr Extension) | C78: {=Financial_Impact_Dashboard!M85} -> 61.547468 | D78: {=Financial_Impact_Dashboard!N85} -> 37.818255 | E78: {=D78} -> 37.818255
B79: Optimistic (75yr Extension) | C79: {=Financial_Impact_Dashboard!M91} -> 136.06079 | D79: {=Financial_Impact_Dashboard!N91} -> 83.603464 | E79: {=D79} -> 83.603464
B80: FCF Formula: EBITDA Improvement + Depreciation Savings (Non-Cash) - Incremental Maintenance
B81: Critical Insight: Both scenarios generate POSITIVE NPV despite increased maintenance costs
B83: SALVAGE VALUE RISK ASSESSMENT
B84: Salvage Value Scenario | C84: 90% (Current) | D84: 70% (Conservative) | E84: 50% (Pessimistic)
B85: End-of-Life NBV (50yrs) (IDR B) | C85: {=Sensitivity_Analysis!C48} -> 493.47298 | D85: {=Sensitivity_Analysis!D48} -> 383.81232 | E85: {=Sensitivity_Analysis!E48} -> 274.15166
B86: Salvage Value Range (IDR B) | C86: {=Sensitivity_Analysis!F48} -> 219.32133 | D86: 40% variance | E86: 0
B87: Impact on 10-Year Analysis: MINIMAL - Salvage value affects end-of-life (2060+), not 2025-2034 period
B89: COMPREHENSIVE RECOMMENDATION
B90: ✓ Asset Life Extension Creates Real Economic Value
B92: Three-Pillar Financial Case:
B93: 1. CASH FLOW POSITIVE: NPV of IDR 37.8B (Realistic) to IDR 83.6B (Optimistic) over 10 years
B94: 2. MAINTENANCE NEUTRAL: No incremental maintenance costs in near-term (years 25-34 of asset life)
B95: 3. SALVAGE VALUE INSENSITIVE: End-of-life disposal risks are 35+ years away, minimal P&L impact
B97: Key Decision Criteria:
B98: • Free Cash Flow analysis confirms depreciation savings exceed any incremental costs
B99: • NPV analysis demonstrates value creation at 10% discount rate
B100: • Maintenance cost escalation is manageable and deferred beyond 10-year horizon
B101: • Salvage value sensitivity shows limited downside risk to 10-year projections
... B109: • Maintenance Escalation Parameters: Inputs rows 25-29

Sheet Visual_Dashboard
B2: ASSET LIFE EXTENSION
B3: Financial Impact Dashboard
B5: Total Building Assets | E5: Annual Savings (50yr) | H5: 10-Year Total Savings | K5: Savings %
B6: =Depreciation_Scenario_Analysis!E30/1000000000 -> 548.30332 | C6: IDR | D6: Billions | E6: {=Financial_Impact_Dashboard!N18} -> 3.0773734 | F6: IDR | G6: B/year | H6: {=Financial_Impact_Dashboard!M18} -> 30.773734 | I6: IDR | J6: Billions | K6: {=Financial_Impact_Dashboard!D42} -> 0.22139898 | L6: vs | M6: Baseline
B8: EBITDA Improvement | E8: Net Income Improvement | H8: NPV @ 10% | K8: Building Assets
B9: {=Financial_Impact_Dashboard!M23} -> 30.773734 | C9: IDR | D9: Billions | E9: {=Financial_Impact_Dashboard!M28} -> 24.003513 | F9: IDR | G9: Billions | H9: =Sensitivity_Analysis!F15/1000000000 -> 1474.9119 | I9: IDR | J9: Billions | K9: 10 | L9: Assets | M9: Analyzed
B11: SCENARIO COMPARISON - 10 YEAR TOTAL DEPRECIATION | F11: ANNUAL DEPRECIATION TREND (2025-2034)
B12: Scenario | C12: Total Depreciation (IDR B) | D12: Savings vs Baseline | F12: Year | G12: Baseline | H12: Realistic | I12: Optimistic
B13: Baseline (40 years) | C13: {=Financial_Impact_Dashboard!M12} -> 138.99673 | D13: 0 | F13: 2025 | G13: {=Financial_Impact_Dashboard!C12} -> 13.899673 | H13: {=Financial_Impact_Dashboard!C13} -> 10.8223 | I13: {=Financial_Impact_Dashboard!C14} -> 7.0966337
B14: Realistic (50 years) | C14: {=Financial_Impact_Dashboard!M13} -> 108.223 | D14: {=Financial_Impact_Dashboard!M18} -> 30.773734 | F14: 2026 | G14: {=Financial_Impact_Dashboard!D12} -> 13.899673 | H14: {=Financial_Impact_Dashboard!D13} -> 10.8223 | I14: {=Financial_Impact_Dashboard!D14} -> 7.0966337
B15: Optimistic (75 years) | C15: {=Financial_Impact_Dashboard!M14} -> 70.966337 | D15: {=Financial_Impact_Dashboard!M19} -> 68.030394 | F15: 2027 | G15: {=Financial_Impact_Dashboard!E12} -> 13.899673 | H15: {=Financial_Impact_Dashboard!E13} -> 10.8223 | I15: {=Financial_Impact_Dashboard!E14} -> 7.0966337
F16: 2028 | G16: {=Financial_Impact_Dashboard!F12} -> 13.899673 | H16: {=Financial_Impact_Dashboard!F13} -> 10.8223 | I16: {=Financial_Impact_Dashboard!F14} -> 7.0966337
F17: 2029 | G17: {=Financial_Impact_Dashboard!G12} -> 13.899673 | H17: {=Financial_Impact_Dashboard!G13} -> 10.8223 | I17: {=Financial_Impact_Dashboard!G14} -> 7.0966337
F18: 2030 | G18: {=Financial_Impact_Dashboard!H12} -> 13.899673 | H18: {=Financial_Impact_Dashboard!H13} -> 10.8223 | I18: {=Financial_Impact_Dashboard!H14} -> 7.0966337
F19: 2031 | G19: {=Financial_Impact_Dashboard!I12} -> 13.899673 | H19: {=Financial_Impact_Dashboard!I13} -> 10.8223 | I19: {=Financial_Impact_Dashboard!I14} -> 7.0966337
F20: 2032 | G20: {=Financial_Impact_Dashboard!J12} -> 13.899673 | H20: {=Financial_Impact_Dashboard!J13} -> 10.8223 | I20: {=Financial_Impact_Dashboard!J14} -> 7.0966337
F21: 2033 | G21: {=Financial_Impact_Dashboard!K12} -> 13.899673 | H21: {=Financial_Impact_Dashboard!K13} -> 10.8223 | I21: {=Financial_Impact_Dashboard!K14} -> 7.0966337
F22: 2034 | G22: {=Financial_Impact_Dashboard!L12} -> 13.899673 | H22: {=Financial_Impact_Dashboard!L13} -> 10.8223 | I22: {=Financial_Impact_Dashboard!L14} -> 7.0966337
B24: CUMULATIVE SAVINGS OVER TIME | F24: NET BOOK VALUE COMPARISON - 2034 | K24: FINANCIAL IMPACT SUMMARY
B25: Year | C25: Realistic Cumulative | D25: Optimistic Cumulative | F25: Scenario | G25: Building NBV (IDR B) | K25: Metric | L25: Realistic (50yr) | M25: Optimistic (75yr)
B26: 2025 | C26: {=Financial_Impact_Dashboard!C33} -> 3.0773734 | D26: {=Financial_Impact_Dashboard!C34} -> 6.8030394 | F26: Baseline (40yr) | G26: {=Balance_Sheet_Impact!M9} -> 251.2705 | K26: Annual Savings | L26: {=Financial_Impact_Dashboard!N18} -> 3.0773734 | M26: {=Financial_Impact_Dashboard!N19} -> 6.8030394
B27: 2026 | C27: {=Financial_Impact_Dashboard!D33} -> 6.1547468 | D27: {=Financial_Impact_Dashboard!D34} -> 13.606079 | F27: Realistic (50yr) | G27: {=Balance_Sheet_Impact!M10} -> 309.74059 | K27: 10-Year EBITDA + | L27: {=Financial_Impact_Dashboard!M23} -> 30.773734 | M27: {=Financial_Impact_Dashboard!M24} -> 68.030394
B28: 2027 | C28: {=Financial_Impact_Dashboard!E33} -> 9.2321202 | D28: {=Financial_Impact_Dashboard!E34} -> 20.409118 | F28: Optimistic (75yr) | G28: {=Balance_Sheet_Impact!M11} -> 380.52824 | K28: 10-Year Net Income + | L28: {=Financial_Impact_Dashboard!M28} -> 24.003513 | M28: {=Financial_Impact_Dashboard!M29} -> 53.063707
B29: 2028 | C29: {=Financial_Impact_Dashboard!F33} -> 12.309494 | D29: {=Financial_Impact_Dashboard!F34} -> 27.212158 | K29: NPV @ 10% | L29: =Sensitivity_Analysis!F15/1000000000 -> 1474.9119 | M29: =Sensitivity_Analysis!F16/1000000000 -> 3260.5351
B30: 2029 | C30: {=Financial_Impact_Dashboard!G33} -> 15.386867 | D30: {=Financial_Impact_Dashboard!G34} -> 34.015197 | K30: Savings % | L30: {=Financial_Impact_Dashboard!D42} -> 0.22139898 | M30: {=Financial_Impact_Dashboard!E42} -> 0.4894388
B31: 2030 | C31: {=Financial_Impact_Dashboard!H33} -> 18.46424 | D31: {=Financial_Impact_Dashboard!H34} -> 40.818236
B32: 2031 | C32: {=Financial_Impact_Dashboard!I33} -> 21.541614 | D32: {=Financial_Impact_Dashboard!I34} -> 47.621276 | K32: SENSITIVITY ANALYSIS
B33: 2032 | C33: {=Financial_Impact_Dashboard!J33} -> 24.618987 | D33: {=Financial_Impact_Dashboard!J34} -> 54.424315 | K33: Variable | L33: Impact Range
B34: 2033 | C34: {=Financial_Impact_Dashboard!K33} -> 27.696361 | D34: {=Financial_Impact_Dashboard!K34} -> 61.227354 | K34: Discount Rate (8%-12%) | L34: =Sensitivity_Analysis!F22/1000000000 -> 883.10904
B35: 2034 | C35: {=Financial_Impact_Dashboard!L33} -> 30.773734 | D35: {=Financial_Impact_Dashboard!L34} -> 68.030394 | K35: Tax Rate (20%-25%) | L35: =Sensitivity_Analysis!F21/1000000000 -> -94.545637
B37: RECOMMENDED SCENARIO
B38: 50-YEAR USEFUL LIFE EXTENSION (REALISTIC SCENARIO)
B39: ✓ Annual Savings: | D39: {=Financial_Impact_Dashboard!N18} -> 3.0773734 | E39: IDR Billions/year | G39: IMPLEMENTATION TIMELINE
B40: ✓ 10-Year Value: | D40: {=Financial_Impact_Dashboard!M18} -> 30.773734 | E40: IDR Billions | G40: Q4 2024 | H40: → | I40: Policy Approval & Documentation
B41: ✓ Savings Rate: | D41: {=Financial_Impact_Dashboard!D42} -> 0.22139898 | E41: vs Current Policy | G41: Jan 1, 2025 | H41: → | I41: Implement New Depreciation Rates
B42: ✓ NPV: | D42: =Sensitivity_Analysis!F15/1000000000 -> 1474.9119 | E42: IDR Billions @ 10% | G42: Q1 2025 | H42: → | I42: Financial Statement Disclosure
B44: Data Sources: Asset Data Pullman (10 building assets) | Financial Statements (2018-2024) | Maintenance History
B45: Analysis Date: November 2024 | Assumptions: 22% Tax Rate, 10% Discount Rate, Prospective Application from 2025
