Workbook

Sheet Inputs
B2: LBO MODEL - INPUTS & ASSUMPTIONS
B4: TRANSACTION ASSUMPTIONS
B5: Transaction Date | C5: 1/1/2024
B6: Enterprise Value ($mm) | C6: 500
B7: Entry EV / LTM EBITDA | C7: 10
B8: Less: Cash Acquired ($mm) | C8: 10
B9: Plus: Debt Assumed ($mm) | C9: 0
B10: Transaction Fees (% of EV) | C10: 0.02
B11: Financing Fees (% of Debt) | C11: 0.03
B13: OPERATING ASSUMPTIONS
B14: LTM Revenue ($mm) | C14: 200
B15: LTM EBITDA ($mm) | C15: 50
B16: Revenue Growth Rate (Annual) | C16: 0.05
B17: EBITDA Margin | C17: 0.25
B18: D&A (% of Revenue) | C18: 0.03
B19: CapEx (% of Revenue) | C19: 0.02
B20: NWC (% of Revenue) | C20: 0.1
B21: Tax Rate | C21: 0.25
B23: FINANCING STRUCTURE
B24: Revolver Commitment ($mm) | C24: 25
B25: Revolver Interest Rate | C25: 0.055
B26: 0
B27: Term Loan B ($mm) | C27: 250
B28: Term Loan B Interest Rate | C28: 0.065
B29: TLB Amortization (% p.a.) | C29: 0.01
B30: 0
B31: Senior Notes ($mm) | C31: 100
B32: Senior Notes Interest Rate | C32: 0.075
B33: Senior Notes Maturity (Years) | C33: 8
B34: 0
B35: Subordinated Notes ($mm) | C35: 50
B36: Subordinated Notes Interest Rate | C36: 0.095
B37: Subordinated Notes Maturity (Years) | C37: 9
B39: EXIT ASSUMPTIONS
B40: Holding Period (Years) | C40: 5
B41: Exit EV / EBITDA Multiple | C41: 10.5
B42: Exit Year Cash Balance ($mm) | C42: 15

Sheet Transaction
B2: SOURCES & USES OF FUNDS
B4: SOURCES | C4: $mm | D4: % | F4: VALUATION MULTIPLES
B5: Revolver | C5: {=Inputs!C24} -> 25 | D5: =C5/C11 -> 0.048756704 | F5: Entry EV / LTM EBITDA | G5: {=Inputs!C7} -> 10
B6: Term Loan B | C6: {=Inputs!C27} -> 250 | D6: =C6/C11 -> 0.48756704 | F6: Entry EV / LTM Revenue | G6: =C14/Inputs!C14 -> 2.5
B7: Senior Notes | C7: {=Inputs!C31} -> 100 | D7: =C7/C11 -> 0.19502682 | F7: Implied EBITDA Margin | G7: =Inputs!C15/Inputs!C14 -> 0.25
B8: Subordinated Notes | C8: {=Inputs!C35} -> 50 | D8: =C8/C11 -> 0.097513408 | F8: Total Debt / EBITDA | G8: =(C5+C6+C7+C8)/Inputs!C15 -> 8.5
B9: Sponsor Equity | C9: =C23-C5-C6-C7-C8 -> 87.75 | D9: =C9/C23 -> 0.17113603 | F9: Equity / Total Cap | G9: =C9/C11 -> 0.17113603
B10: 0 | F10: Debt / Equity | G10: =(C5+C6+C7+C8)/C9 -> 4.8433048
B11: Total Sources | C11: =C5+C6+C7+C8+C9 -> 512.75 | D11: =C11/C23 -> 1
B13: USES | C13: $mm | D13: %
B14: Purchase Enterprise Value | C14: {=Inputs!C6} -> 500 | D14: =C14/C23 -> 0.97513408
B15: Less: Cash Acquired | C15: =-Inputs!C8 -> -10 | D15: =C15/C23 -> -0.019502682
B16: Plus: Debt Assumed | C16: {=Inputs!C9} -> 0 | D16: =C16/C23 -> 0
B17: Equity Purchase Price | C17: =C14+C15+C16 -> 490 | D17: =C17/C23 -> 0.9556314
B18: 0
B19: Transaction Fees | C19: =Inputs!C6*Inputs!C10 -> 10 | D19: =C19/C23 -> 0.019502682
B20: Financing Fees | C20: =(C5+C6+C7+C8)*Inputs!C11 -> 12.75 | D20: =C20/C23 -> 0.024865919
B21: Other Fees & Expenses | C21: 0 | D21: =C21/C23 -> 0
B22: 0
B23: Total Uses | C23: =C17+C19+C20+C21 -> 512.75 | D23: =C23/C23 -> 1
B25: 0
B26: PURCHASE PRICE ALLOCATION
B27: Enterprise Value | C27: {=C14} -> 500 | D27: =C27/C32 -> 0.97513408
B28: Less: Existing Cash | C28: {=C15} -> -10 | D28: =C28/C32 -> -0.019502682
B29: Implied Equity Value | C29: =C27+C28 -> 490 | D29: =C29/C32 -> 0.9556314
B30: Plus: Net Debt Assumed | C30: {=C16} -> 0 | D30: =C30/C32 -> 0
B31: Plus: Transaction Costs | C31: =C19+C20+C21 -> 22.75 | D31: =C31/C32 -> 0.044368601
B32: Total Funds Required | C32: =C29+C30+C31 -> 512.75 | D32: =C32/C32 -> 1

Sheet Financial_Model
B2: FINANCIAL PROJECTION MODEL
B4: ($mm) | C4: LTM | D4: Year 1 | E4: Year 2 | F4: Year 3 | G4: Year 4 | H4: Year 5
B6: Revenue | C6: {=Inputs!C14} -> 200 | D6: =C6*(1+Inputs!C16) -> 210 | E6: =D6*(1+Inputs!D16) -> 210 | F6: =E6*(1+Inputs!E16) -> 210 | G6: =F6*(1+Inputs!F16) -> 210 | H6: =G6*(1+Inputs!G16) -> 210
B7: EBITDA | C7: {=Inputs!C15} -> 50 | D7: =D6*Inputs!C17 -> 52.5 | E7: =E6*Inputs!C17 -> 52.5 | F7: =F6*Inputs!C17 -> 52.5 | G7: =G6*Inputs!C17 -> 52.5 | H7: =H6*Inputs!C17 -> 52.5
B8: Less: D&A | C8: =-C6*Inputs!C18 -> -6 | D8: =-D6*Inputs!D18 -> 0 | E8: =-E6*Inputs!E18 -> 0 | F8: =-F6*Inputs!F18 -> 0 | G8: =-G6*Inputs!G18 -> 0 | H8: =-H6*Inputs!H18 -> 0
B9: EBIT | C9: =C7+C8 -> 44 | D9: =D7+D8 -> 52.5 | E9: =E7+E8 -> 52.5 | F9: =F7+F8 -> 52.5 | G9: =G7+G8 -> 52.5 | H9: =H7+H8 -> 52.5
B10: Less: Interest Expense | C10: 0 | D10: =-Debt_Schedule!C26 -> -16.25 | E10: =-Debt_Schedule!D26 -> 0 | F10: =-Debt_Schedule!E26 -> 0 | G10: =-Debt_Schedule!F26 -> 0 | H10: =-Debt_Schedule!G26 -> 0
B11: EBT | C11: =C9+C10 -> 44 | D11: =D9+D10 -> 36.25 | E11: =E9+E10 -> 52.5 | F11: =F9+F10 -> 52.5 | G11: =G9+G10 -> 52.5 | H11: =H9+H10 -> 52.5
B12: Less: Taxes | C12: =-C11*Inputs!C21 -> -11 | D12: =-D11*Inputs!D21 -> 0 | E12: =-E11*Inputs!E21 -> 0 | F12: =-F11*Inputs!F21 -> 0 | G12: =-G11*Inputs!G21 -> 0 | H12: =-H11*Inputs!H21 -> 0
B13: Net Income | C13: =C11+C12 -> 33 | D13: =D11+D12 -> 36.25 | E13: =E11+E12 -> 52.5 | F13: =F11+F12 -> 52.5 | G13: =G11+G12 -> 52.5 | H13: =H11+H12 -> 52.5
B15: 0
B16: CASH FLOW
B17: EBITDA | C17: {=C7} -> 50 | D17: {=D7} -> 52.5 | E17: {=E7} -> 52.5 | F17: {=F7} -> 52.5 | G17: {=G7} -> 52.5 | H17: {=H7} -> 52.5
B18: Less: Cash Taxes | C18: {=C12} -> -11 | D18: {=D12} -> 0 | E18: {=E12} -> 0 | F18: {=F12} -> 0 | G18: {=G12} -> 0 | H18: {=H12} -> 0
B19: Less: CapEx | C19: =-C6*Inputs!C19 -> -4 | D19: =-D6*Inputs!D19 -> 0 | E19: =-E6*Inputs!E19 -> 0 | F19: =-F6*Inputs!F19 -> 0 | G19: =-G6*Inputs!G19 -> 0 | H19: =-H6*Inputs!H19 -> 0
B20: Less: Increase in NWC | C20: 0 | D20: =-(D6*Inputs!C20-C6*Inputs!C20) -> -1 | E20: =-(E6*Inputs!D20-D6*Inputs!D20) -> 0 | F20: =-(F6*Inputs!E20-E6*Inputs!E20) -> 0 | G20: =-(G6*Inputs!F20-F6*Inputs!F20) -> 0 | H20: =-(H6*Inputs!G20-G6*Inputs!G20) -> 0
B21: Unlevered FCF | C21: =C17+C18+C19+C20 -> 35 | D21: =D17+D18+D19+D20 -> 51.5 | E21: =E17+E18+E19+E20 -> 52.5 | F21: =F17+F18+F19+F20 -> 52.5 | G21: =G17+G18+G19+G20 -> 52.5 | H21: =H17+H18+H19+H20 -> 52.5
B22: 0
B23: Less: Interest Expense | C23: {=C10} -> 0 | D23: {=D10} -> -16.25 | E23: {=E10} -> 0 | F23: {=F10} -> 0 | G23: {=G10} -> 0 | H23: {=H10} -> 0
B24: Less: Mandatory Amortization | C24: 0 | D24: =-Debt_Schedule!D20 -> 0 | E24: =-Debt_Schedule!E20 -> 0 | F24: =-Debt_Schedule!F20 -> 0 | G24: =-Debt_Schedule!G20 -> 0 | H24: =-Debt_Schedule!H20 -> 0
B25: Levered FCF | C25: =C21+C23+C24 -> 35 | D25: =D21+D23+D24 -> 35.25 | E25: =E21+E23+E24 -> 52.5 | F25: =F21+F23+F24 -> 52.5 | G25: =G21+G23+G24 -> 52.5 | H25: =H21+H23+H24 -> 52.5
B27: 0
B28: KEY METRICS
B29: Revenue Growth | C29: 0 | D29: =D6/C6-1 -> 0.05 | E29: =E6/D6-1 -> 0 | F29: =F6/E6-1 -> 0 | G29: =G6/F6-1 -> 0 | H29: =H6/G6-1 -> 0
B30: EBITDA Margin | C30: =C7/C6 -> 0.25 | D30: =D7/D6 -> 0.25 | E30: =E7/E6 -> 0.25 | F30: =F7/F6 -> 0.25 | G30: =G7/G6 -> 0.25 | H30: =H7/H6 -> 0.25
B31: Total Debt / EBITDA | C31: 0 | D31: =Debt_Schedule!D37/D7 -> 4.7619048 | E31: =Debt_Schedule!E37/E7 -> 4.7142857 | F31: =Debt_Schedule!F37/F7 -> 4.7142857 | G31: =Debt_Schedule!G37/G7 -> 4.7142857 | H31: =Debt_Schedule!H37/H7 -> 0
B33: 0
B34: WORKING CAPITAL ANALYSIS
B35: Beginning NWC | C35: =C6*Inputs!C20 -> 20 | D35: =D6*Inputs!D20 -> 0 | E35: =E6*Inputs!E20 -> 0 | F35: =F6*Inputs!F20 -> 0 | G35: =G6*Inputs!G20 -> 0 | H35: =H6*Inputs!H20 -> 0
B36: Ending NWC | C36: =C6*Inputs!C20 -> 20 | D36: =D6*Inputs!C20 -> 21 | E36: =E6*Inputs!D20 -> 0 | F36: =F6*Inputs!E20 -> 0 | G36: =G6*Inputs!F20 -> 0 | H36: =H6*Inputs!G20 -> 0
B37: Change in NWC (Use of Cash) | C37: =C36-C35 -> 0 | D37: =D36-D35 -> 21 | E37: =E36-E35 -> 0 | F37: =F36-F35 -> 0 | G37: =G36-G35 -> 0 | H37: =H36-H35 -> 0
B39: 0
B40: CREDIT & VALUATION METRICS
B41: Total Debt Outstanding | C41: 0 | D41: {=Debt_Schedule!D37} -> 250 | E41: {=Debt_Schedule!E37} -> 247.5 | F41: {=Debt_Schedule!F37} -> 247.5 | G41: {=Debt_Schedule!G37} -> 247.5 | H41: {=Debt_Schedule!H37} -> 0
B42: Net Debt (Debt - Cash) | C42: 0 | D42: =D41-Inputs!C42 -> 235 | E42: =E41-Inputs!D42 -> 247.5 | F42: =F41-Inputs!E42 -> 247.5 | G42: =G41-Inputs!F42 -> 247.5 | H42: =H41-Inputs!G42 -> 0
B43: Net Debt / EBITDA | C43: 0 | D43: =D42/D7 -> 4.4761905 | E43: =E42/E7 -> 4.7142857 | F43: =F42/F7 -> 4.7142857 | G43: =G42/G7 -> 4.7142857 | H43: =H42/H7 -> 0
B44: Interest Coverage (EBIT / Int) | C44: 0 | D44: =IF(-D10>0,D9/(-D10),"N/A") -> 3.2307692 | E44: =IF(-E10>0,E9/(-E10),"N/A") -> N/A | F44: =IF(-F10>0,F9/(-F10),"N/A") -> N/A | G44: =IF(-G10>0,G9/(-G10),"N/A") -> N/A | H44: =IF(-H10>0,H9/(-H10),"N/A") -> N/A
B45: EBITDA - CapEx | C45: =C7+C19 -> 46 | D45: =D7+D19 -> 52.5 | E45: =E7+E19 -> 52.5 | F45: =F7+F19 -> 52.5 | G45: =G7+G19 -> 52.5 | H45: =H7+H19 -> 52.5
B46: FCF Yield (FCF / EV Entry) | C46: =C21/Inputs!C6 -> 0.07 | D46: =D21/Inputs!C6 -> 0.103 | E46: =E21/Inputs!C6 -> 0.105 | F46: =F21/Inputs!C6 -> 0.105 | G46: =G21/Inputs!C6 -> 0.105 | H46: =H21/Inputs!C6 -> 0.105

Sheet Debt_Schedule
B2: DEBT SCHEDULE & CASH SWEEP ANALYSIS
B4: ($mm) | C4: Year 1 | D4: Year 2 | E4: Year 3 | F4: Year 4 | G4: Year 5
B6: REVOLVER
B7: Beginning Balance | C7: 0 | D7: {=C8} -> 0 | E7: {=D8} -> 0 | F7: {=E8} -> 0 | G7: {=F8} -> 0
B8: Ending Balance | C8: 0 | D8: 0 | E8: 0 | F8: 0 | G8: 0
B10: TERM LOAN B
B11: Beginning Balance | C11: {=Inputs!C27} -> 250 | D11: {=C12} -> 247.5 | E11: {=D12} -> 247.5 | F11: {=E12} -> 247.5 | G11: {=F12} -> 247.5
B12: Ending Bal (Before Sweep) | C12: =C11-C20 -> 247.5 | D12: =D11-D20 -> 247.5 | E12: =E11-E20 -> 247.5 | F12: =F11-F20 -> 247.5 | G12: =G11-G20 -> 247.5
B13: 0
B14: CASH SWEEP ANALYSIS
B15: Available Cash (FCF) | C15: {=Financial_Model!C25} -> 35 | D15: {=Financial_Model!D25} -> 35.25 | E15: {=Financial_Model!E25} -> 52.5 | F15: {=Financial_Model!F25} -> 52.5 | G15: {=Financial_Model!G25} -> 52.5
B16: TLB Optional Paydown | C16: =MIN(C15,C12) -> 35 | D16: =MIN(D15,D12) -> 35.25 | E16: =MIN(E15,E12) -> 52.5 | F16: =MIN(F15,F12) -> 52.5 | G16: =MIN(G15,G12) -> 52.5
B17: TLB Ending Balance (After Sweep) | C17: =C12-C16 -> 212.5 | D17: =D12-D16 -> 212.25 | E17: =E12-E16 -> 195 | F17: =F12-F16 -> 195 | G17: =G12-G16 -> 195
B19: Beginning Balance | C19: {=Inputs!C35} -> 50 | D19: {=C20} -> 2.5 | E19: {=D20} -> 0 | F19: {=E20} -> 0 | G19: {=F20} -> 0
B20: Mandatory Amortization | C20: =C11*Inputs!C29 -> 2.5 | D20: =D11*Inputs!D29 -> 0 | E20: =E11*Inputs!E29 -> 0 | F20: =F11*Inputs!F29 -> 0 | G20: =G11*Inputs!G29 -> 0
B21: Ending Balance | C21: {=C19} -> 50 | D21: {=D19} -> 2.5 | E21: {=E19} -> 0 | F21: {=F19} -> 0 | G21: {=G19} -> 0
B23: 0
B24: INTEREST EXPENSE
B25: Revolver Interest | C25: =C7*Inputs!C25 -> 0 | D25: =D7*Inputs!D25 -> 0 | E25: =E7*Inputs!E25 -> 0 | F25: =F7*Inputs!F25 -> 0 | G25: =G7*Inputs!G25 -> 0
B26: TLB Interest | C26: =C11*Inputs!C28 -> 16.25 | D26: =D11*Inputs!D28 -> 0 | E26: =E11*Inputs!E28 -> 0 | F26: =F11*Inputs!F28 -> 0 | G26: =G11*Inputs!G28 -> 0
B27: Senior Notes Interest | C27: =C15*Inputs!C32 -> 2.625 | D27: =D15*Inputs!D32 -> 0 | E27: =E15*Inputs!E32 -> 0 | F27: =F15*Inputs!F32 -> 0 | G27: =G15*Inputs!G32 -> 0
B28: Subordinated Notes Interest | C28: =C19*Inputs!C36 -> 4.75 | D28: =D19*Inputs!D36 -> 0 | E28: =E19*Inputs!E36 -> 0 | F28: =F19*Inputs!F36 -> 0 | G28: =G19*Inputs!G36 -> 0
B29: Total Interest Expense | C29: =C25+C26+C27+C28 -> 23.625 | D29: =D25+D26+D27+D28 -> 0 | E29: =E25+E26+E27+E28 -> 0 | F29: =F25+F26+F27+F28 -> 0 | G29: =G25+G26+G27+G28 -> 0
B31: 0
B32: TOTAL DEBT
B33: Revolver | C33: {=C8} -> 0 | D33: {=D8} -> 0 | E33: {=E8} -> 0 | F33: {=F8} -> 0 | G33: {=G8} -> 0
B34: Term Loan B | C34: {=C17} -> 212.5 | D34: {=D17} -> 212.25 | E34: {=E17} -> 195 | F34: {=F17} -> 195 | G34: {=G17} -> 195
B35: Senior Notes | C35: {=C16} -> 35 | D35: {=D16} -> 35.25 | E35: {=E16} -> 52.5 | F35: {=F16} -> 52.5 | G35: {=G16} -> 52.5
B36: Subordinated Notes | C36: {=C21} -> 50 | D36: {=D21} -> 2.5 | E36: {=E21} -> 0 | F36: {=F21} -> 0 | G36: {=G21} -> 0
B37: Total Debt | C37: =C33+C34+C35+C36 -> 297.5 | D37: =D33+D34+D35+D36 -> 250 | E37: =E33+E34+E35+E36 -> 247.5 | F37: =F33+F34+F35+F36 -> 247.5 | G37: =G33+G34+G35+G36 -> 247.5

Sheet Returns
B2: RETURNS ANALYSIS
B4: EXIT VALUATION
B5: Exit Year | C5: {=Inputs!C40} -> 5
B6: Exit Year EBITDA ($mm) | C6: {=Financial_Model!H7} -> 52.5
B7: Exit EV / EBITDA Multiple | C7: {=Inputs!C41} -> 10.5
B8: Exit Enterprise Value ($mm) | C8: =C6*C7 -> 551.25
B9: 0
B10: Less: Exit Year Debt ($mm) | C10: =-Debt_Schedule!G37 -> -247.5
B11: Plus: Exit Year Cash ($mm) | C11: {=Inputs!C42} -> 15
B12: Equity Value at Exit ($mm) | C12: =C8+C10+C11 -> 318.75
B14: 0
B15: RETURNS METRICS
B16: Initial Equity Investment ($mm) | C16: {=Transaction!C9} -> 87.75
B17: Equity Value at Exit ($mm) | C17: {=C12} -> 318.75
B18: 0
B19: Gross MOIC | C19: =C17/C16 -> 3.6324786
B20: Gross IRR | C20: =(C17/C16)^(1/C5)-1 -> 0.29431688
B22: 0
B23: IRR SENSITIVITY TABLE
B24: Exit EV / EBITDA | C24: 9 | D24: 9.5 | E24: 10 | F24: 10.5 | G24: 11
B25: IRR | C25: =((C6*C24-Debt_Schedule!G37+Inputs!C42)/C16)^(1/C5)-1 -> 0.22290529 | D25: =((C6*D24-Debt_Schedule!G37+Inputs!C42)/C16)^(1/C5)-1 -> 0.24855736 | E25: =((C6*E24-Debt_Schedule!G37+Inputs!C42)/C16)^(1/C5)-1 -> 0.27225964 | F25: =((C6*F24-Debt_Schedule!G37+Inputs!C42)/C16)^(1/C5)-1 -> 0.29431688 | G25: =((C6*G24-Debt_Schedule!G37+Inputs!C42)/C16)^(1/C5)-1 -> 0.31496561
B27: 0
B28: DCF VALUATION ANALYSIS
B29: 0 | C29: Year 1 | D29: Year 2 | E29: Year 3 | F29: Year 4 | G29: Year 5
B30: Unlevered FCF | C30: {=Financial_Model!D21} -> 51.5 | D30: {=Financial_Model!E21} -> 52.5 | E30: {=Financial_Model!F21} -> 52.5 | F30: {=Financial_Model!G21} -> 52.5 | G30: {=Financial_Model!H21} -> 52.5
B31: WACC | C31: 0.12 | D31: 0.12 | E31: 0.12 | F31: 0.12 | G31: 0.12
B32: Discount Factor | C32: =1/(1+C31)^1 -> 0.89285714 | D32: =1/(1+D31)^2 -> 0.79719388 | E32: =1/(1+E31)^3 -> 0.71178025 | F32: =1/(1+F31)^4 -> 0.63551808 | G32: =1/(1+G31)^5 -> 0.56742686
B33: PV of Unlevered FCF | C33: =C30*C32 -> 45.982143 | D33: =D30*D32 -> 41.852679 | E33: =E30*E32 -> 37.368463 | F33: =F30*F32 -> 33.364699 | G33: =G30*G32 -> 29.78991
B34: Terminal Value (PV) | G34: =C8*G32 -> 312.79405
B35: Enterprise Value (DCF) | C35: =SUM(C33:G33)+G34 -> 501.15195
B37: 0
B38: MOIC SENSITIVITY TABLE
B39: Exit EV / EBITDA | C39: 9 | D39: 9.5 | E39: 10 | F39: 10.5 | G39: 11
B40: MOIC | C40: =((C6*C39-Debt_Schedule!G37+Inputs!C42)/C16) -> 2.7350427 | D40: =((C6*D39-Debt_Schedule!G37+Inputs!C42)/C16) -> 3.034188 | E40: =((C6*E39-Debt_Schedule!G37+Inputs!C42)/C16) -> 3.3333333 | F40: =((C6*F39-Debt_Schedule!G37+Inputs!C42)/C16) -> 3.6324786 | G40: =((C6*G39-Debt_Schedule!G37+Inputs!C42)/C16) -> 3.9316239
B42: 0
B43: TRANSACTION SUMMARY
B44: Target IRR Achieved (≥20%)? | C44: =IF(C20>=0.20,"YES ✓","NO ✗") -> YES ✓
B45: Total Debt Paydown | C45: =Debt_Schedule!C37-Debt_Schedule!G37 -> 50 | D45: =(Debt_Schedule!C37-Debt_Schedule!G37)/Debt_Schedule!C37 -> 0.16806723
B46: Equity Value Created | C46: =C12-C16 -> 231 | D46: =(C12-C16)/C16 -> 2.6324786
B47: Levered IRR vs Entry Multiple | C47: {=C20} -> 0.29431688 | D47: {=Inputs!C7} -> 10
