Workbook

Sheet Cover_Assumptions
B2: 3-STATEMENT FINANCIAL MODEL
B3: Large Retail/Distribution Company
B4: $200M Revenue Base
B6: MODEL ASSUMPTIONS
C7: Year 0 | D7: Year 1 | E7: Year 2 | F7: Year 3 | G7: Year 4 | H7: Year 5 | I7: Year 6 | J7: Year 7 | K7: Year 8
B9: REVENUE ASSUMPTIONS
B10: Base Revenue ($M) | C10: 200
B11: Revenue Growth Rate | D11: 0.13 | E11: 0.145 | F11: 0.12 | G11: 0.1 | H11: 0.08 | I11: 0.07 | J11: 0.06 | K11: 0.06
B13: PROFITABILITY ASSUMPTIONS
B14: Gross Margin % | C14: 0.25 | D14: 0.26 | E14: 0.27 | F14: 0.275 | G14: 0.28 | H14: 0.285 | I14: 0.29 | J14: 0.295 | K14: 0.3
B15: Operating Expenses % of Revenue | C15: 0.18 | D15: 0.175 | E15: 0.17 | F15: 0.165 | G15: 0.16 | H15: 0.155 | I15: 0.15 | J15: 0.15 | K15: 0.15
B17: WORKING CAPITAL ASSUMPTIONS
B18: Days Accounts Receivable | C18: 45 | D18: 42 | E18: 40 | F18: 38 | G18: 35 | H18: 35 | I18: 35 | J18: 35 | K18: 35
B19: Days Inventory | C19: 75 | D19: 72 | E19: 70 | F19: 68 | G19: 65 | H19: 65 | I19: 65 | J19: 65 | K19: 65
B20: Days Accounts Payable | C20: 45 | D20: 48 | E20: 50 | F20: 52 | G20: 55 | H20: 55 | I20: 55 | J20: 55 | K20: 55
B22: CAPEX ASSUMPTIONS
B23: Capex % of Revenue | C23: 0.045 | D23: 0.05 | E23: 0.045 | F23: 0.04 | G23: 0.035 | H23: 0.03 | I23: 0.03 | J23: 0.03 | K23: 0.03
B24: Useful Life (Years) | C24: 10
B26: DEBT & INTEREST ASSUMPTIONS
B27: Beginning Debt Balance ($M) | C27: 50
B28: Annual Debt Amortization ($M) | C28: 5
B29: Interest Rate | C29: 0.055
B31: TAX ASSUMPTIONS
B32: Tax Rate | C32: 0.28
B34: DIVIDEND ASSUMPTIONS
B35: Dividend Payout Ratio | C35: 0.35
B37: STARTING BALANCE SHEET ITEMS
B38: Beginning PP&E, net ($M) | C38: 40
B39: Beginning Equity ($M) | C39: 80
B40: Other Current Assets ($M) | C40: 5 | D40: 5 | E40: 5 | F40: 5 | G40: 5 | H40: 5 | I40: 5 | J40: 5 | K40: 5
B41: Beginning Cash ($M) | C41: 41.47

Sheet Income_Statement
B2: INCOME STATEMENT
B3: ($M unless noted)
B5: Period | C5: Year 0 | D5: Year 1 | E5: Year 2 | F5: Year 3 | G5: Year 4 | H5: Year 5 | I5: Year 6 | J5: Year 7 | K5: Year 8
B7: Revenue | C7: {=Revenue_Build!C8} -> 200 | D7: {=Revenue_Build!D8} -> 226 | E7: {=Revenue_Build!E8} -> 258.77 | F7: {=Revenue_Build!F8} -> 289.8224 | G7: {=Revenue_Build!G8} -> 318.80464 | H7: {=Revenue_Build!H8} -> 344.30901 | I7: {=Revenue_Build!I8} -> 368.41064 | J7: {=Revenue_Build!J8} -> 390.51528 | K7: {=Revenue_Build!K8} -> 413.9462
B8: Cost of Goods Sold | C8: =-COGS_OpEx!C10 -> -150 | D8: =-COGS_OpEx!D10 -> -167.24 | E8: =-COGS_OpEx!E10 -> -188.9021 | F8: =-COGS_OpEx!F10 -> -210.12124 | G8: =-COGS_OpEx!G10 -> -229.53934 | H8: =-COGS_OpEx!H10 -> -246.18094 | I8: =-COGS_OpEx!I10 -> -261.57156 | J8: =-COGS_OpEx!J10 -> -275.31327 | K8: =-COGS_OpEx!K10 -> -289.76234
B10: Gross Profit | C10: =C7+C8 -> 50 | D10: =D7+D8 -> 58.76 | E10: =E7+E8 -> 69.8679 | F10: =F7+F8 -> 79.70116 | G10: =G7+G8 -> 89.265299 | H10: =H7+H8 -> 98.128068 | I10: =I7+I8 -> 106.83909 | J10: =J7+J8 -> 115.20201 | K10: =K7+K8 -> 124.18386
B11: Gross Margin % | C11: =C10/C7 -> 0.25 | D11: =D10/D7 -> 0.26 | E11: =E10/E7 -> 0.27 | F11: =F10/F7 -> 0.275 | G11: =G10/G7 -> 0.28 | H11: =H10/H7 -> 0.285 | I11: =I10/I7 -> 0.29 | J11: =J10/J7 -> 0.295 | K11: =K10/K7 -> 0.3
B13: Operating Expenses | C13: =-COGS_OpEx!C14 -> -36 | D13: =-COGS_OpEx!D14 -> -39.55 | E13: =-COGS_OpEx!E14 -> -43.9909 | F13: =-COGS_OpEx!F14 -> -47.820696 | G13: =-COGS_OpEx!G14 -> -51.008742 | H13: =-COGS_OpEx!H14 -> -53.367897 | I13: =-COGS_OpEx!I14 -> -55.261596 | J13: =-COGS_OpEx!J14 -> -58.577292 | K13: =-COGS_OpEx!K14 -> -62.09193
B15: EBITDA | C15: =C10+C13 -> 14 | D15: =D10+D13 -> 19.21 | E15: =E10+E13 -> 25.877 | F15: =F10+F13 -> 31.880464 | G15: =G10+G13 -> 38.256557 | H15: =H10+H13 -> 44.760171 | I15: =I10+I13 -> 51.57749 | J15: =J10+J13 -> 56.624716 | K15: =K10+K13 -> 62.09193
B16: EBITDA Margin % | C16: =C15/C7 -> 0.07 | D16: =D15/D7 -> 0.085 | E16: =E15/E7 -> 0.1 | F16: =F15/F7 -> 0.11 | G16: =G15/G7 -> 0.12 | H16: =H15/H7 -> 0.13 | I16: =I15/I7 -> 0.14 | J16: =J15/J7 -> 0.145 | K16: =K15/K7 -> 0.15
B18: Depreciation | C18: =-PPE_Depreciation!C15 -> -4 | D18: =-PPE_Depreciation!D15 -> -5.065 | E18: =-PPE_Depreciation!E15 -> -5.7057325 | F18: =-PPE_Depreciation!F15 -> -6.2970365 | G18: =-PPE_Depreciation!G15 -> -6.8048858 | H18: =-PPE_Depreciation!H15 -> -7.1987689 | I18: =-PPE_Depreciation!I15 -> -7.5479715 | J18: =-PPE_Depreciation!J15 -> -7.9315632 | K18: =-PPE_Depreciation!K15 -> -8.3450991
B20: EBIT | C20: =C15+C18 -> 10 | D20: =D15+D18 -> 14.145 | E20: =E15+E18 -> 20.171267 | F20: =F15+F18 -> 25.583427 | G20: =G15+G18 -> 31.451671 | H20: =H15+H18 -> 37.561403 | I20: =I15+I18 -> 44.029518 | J20: =J15+J18 -> 48.693152 | K20: =K15+K18 -> 53.746831
B21: Interest Expense | C21: =-Debt_Interest!C14 -> -2.6125 | D21: =-Debt_Interest!D14 -> 0 | E21: =-Debt_Interest!E14 -> 0 | F21: =-Debt_Interest!F14 -> 0 | G21: =-Debt_Interest!G14 -> 0 | H21: =-Debt_Interest!H14 -> 0 | I21: =-Debt_Interest!I14 -> 0 | J21: =-Debt_Interest!J14 -> 0 | K21: =-Debt_Interest!K14 -> 0
B23: Earnings Before Tax (EBT) | C23: =C20+C21 -> 7.3875 | D23: =D20+D21 -> 14.145 | E23: =E20+E21 -> 20.171267 | F23: =F20+F21 -> 25.583427 | G23: =G20+G21 -> 31.451671 | H23: =H20+H21 -> 37.561403 | I23: =I20+I21 -> 44.029518 | J23: =J20+J21 -> 48.693152 | K23: =K20+K21 -> 53.746831
B24: Tax Expense | C24: =-MAX(0,C23)*Cover_Assumptions!$C$32 -> -2.0685 | D24: =-MAX(0,D23)*Cover_Assumptions!$C$32 -> -3.9606 | E24: =-MAX(0,E23)*Cover_Assumptions!$C$32 -> -5.6479549 | F24: =-MAX(0,F23)*Cover_Assumptions!$C$32 -> -7.1633597 | G24: =-MAX(0,G23)*Cover_Assumptions!$C$32 -> -8.8064679 | H24: =-MAX(0,H23)*Cover_Assumptions!$C$32 -> -10.517193 | I24: =-MAX(0,I23)*Cover_Assumptions!$C$32 -> -12.328265 | J24: =-MAX(0,J23)*Cover_Assumptions!$C$32 -> -13.634083 | K24: =-MAX(0,K23)*Cover_Assumptions!$C$32 -> -15.049113
B26: Net Income | C26: =C23+C24 -> 5.319 | D26: =D23+D24 -> 10.1844 | E26: =E23+E24 -> 14.523313 | F26: =F23+F24 -> 18.420068 | G26: =G23+G24 -> 22.645203 | H26: =H23+H24 -> 27.04421 | I26: =I23+I24 -> 31.701253 | J26: =J23+J24 -> 35.05907 | K26: =K23+K24 -> 38.697718
B27: Net Margin % | C27: =C26/C7 -> 0.026595 | D27: =D26/D7 -> 0.045063717 | E27: =E26/E7 -> 0.056124406 | F27: =F26/F7 -> 0.063556398 | G27: =G26/G7 -> 0.071031598 | H27: =H26/H7 -> 0.078546332 | I27: =I26/I7 -> 0.08604869 | J27: =J26/J7 -> 0.089776435 | K27: =K26/K7 -> 0.093484898

Sheet Balance_Sheet
B2: BALANCE SHEET
B3: ($M unless noted)
B5: Period | C5: Year 0 | D5: Year 1 | E5: Year 2 | F5: Year 3 | G5: Year 4 | H5: Year 5 | I5: Year 6 | J5: Year 7 | K5: Year 8
B7: ASSETS
B9: Current Assets
B10: Cash & Equivalents | C10: {=Cover_Assumptions!C41} -> 41.47 | D10: {=Cash_Flow!D30} -> 35.722619 | E10: {=Cash_Flow!E30} -> 37.59994 | F10: {=Cash_Flow!F30} -> 45.04922 | G10: {=Cash_Flow!G30} -> 60.866174 | H10: {=Cash_Flow!H30} -> 76.878324 | I10: {=Cash_Flow!I30} -> 97.342453 | J10: {=Cash_Flow!J30} -> 121.12152 | K10: {=Cash_Flow!K30} -> 148.10329
B11: Accounts Receivable | C11: {=Working_Capital!C11} -> 24.657534 | D11: {=Working_Capital!D11} -> 26.005479 | E11: {=Working_Capital!E11} -> 28.358356 | F11: {=Working_Capital!F11} -> 30.173291 | G11: {=Working_Capital!G11} -> 30.570308 | H11: {=Working_Capital!H11} -> 33.015933 | I11: {=Working_Capital!I11} -> 35.327048 | J11: {=Working_Capital!J11} -> 37.446671 | K11: {=Working_Capital!K11} -> 39.693471
B12: Inventory | C12: {=Working_Capital!C15} -> 30.821918 | D12: {=Working_Capital!D15} -> 32.989808 | E12: {=Working_Capital!E15} -> 36.2278 | F12: {=Working_Capital!F15} -> 39.145875 | G12: {=Working_Capital!G15} -> 40.876869 | H12: {=Working_Capital!H15} -> 43.840442 | I12: {=Working_Capital!I15} -> 46.581236 | J12: {=Working_Capital!J15} -> 49.028391 | K12: {=Working_Capital!K15} -> 51.601512
B13: Other Current Assets | C13: {=Cover_Assumptions!C40} -> 5 | D13: {=Cover_Assumptions!D40} -> 5 | E13: {=Cover_Assumptions!E40} -> 5 | F13: {=Cover_Assumptions!F40} -> 5 | G13: {=Cover_Assumptions!G40} -> 5 | H13: {=Cover_Assumptions!H40} -> 5 | I13: {=Cover_Assumptions!I40} -> 5 | J13: {=Cover_Assumptions!J40} -> 5 | K13: {=Cover_Assumptions!K40} -> 5
B15: Total Current Assets | C15: =SUM(C10:C13) -> 101.94945 | D15: =SUM(D10:D13) -> 99.717907 | E15: =SUM(E10:E13) -> 107.1861 | F15: =SUM(F10:F13) -> 119.36839 | G15: =SUM(G10:G13) -> 137.31335 | H15: =SUM(H10:H13) -> 158.7347 | I15: =SUM(I10:I13) -> 184.25074 | J15: =SUM(J10:J13) -> 212.59658 | K15: =SUM(K10:K13) -> 244.39827
B17: Fixed Assets
B18: PP&E, net | C18: {=PPE_Depreciation!C17} -> 45 | D18: {=PPE_Depreciation!D17} -> 51.235 | E18: {=PPE_Depreciation!E17} -> 57.173918 | F18: {=PPE_Depreciation!F17} -> 62.469777 | G18: {=PPE_Depreciation!G17} -> 66.823054 | H18: {=PPE_Depreciation!H17} -> 69.953555 | I18: {=PPE_Depreciation!I17} -> 73.457903 | J18: {=PPE_Depreciation!J17} -> 77.241798 | K18: {=PPE_Depreciation!K17} -> 81.315085
B20: TOTAL ASSETS | C20: =C15+C18 -> 146.94945 | D20: =D15+D18 -> 150.95291 | E20: =E15+E18 -> 164.36001 | F20: =F15+F18 -> 181.83816 | G20: =G15+G18 -> 204.1364 | H20: =H15+H18 -> 228.68825 | I20: =I15+I18 -> 257.70864 | J20: =J15+J18 -> 289.83838 | K20: =K15+K18 -> 325.71335
B23: LIABILITIES
B25: Current Liabilities
B26: Accounts Payable | C26: {=Working_Capital!C19} -> 18.493151 | D26: {=Working_Capital!D19} -> 21.993205 | E26: {=Working_Capital!E19} -> 25.877 | F26: {=Working_Capital!F19} -> 29.935081 | G26: {=Working_Capital!G19} -> 34.58812 | H26: {=Working_Capital!H19} -> 37.095759 | I26: {=Working_Capital!I19} -> 39.414892 | J26: {=Working_Capital!J19} -> 41.485562 | K26: {=Working_Capital!K19} -> 43.662818
B28: Total Current Liabilities | C28: {=C26} -> 18.493151 | D28: {=D26} -> 21.993205 | E28: {=E26} -> 25.877 | F28: {=F26} -> 29.935081 | G28: {=G26} -> 34.58812 | H28: {=H26} -> 37.095759 | I28: {=I26} -> 39.414892 | J28: {=J26} -> 41.485562 | K28: {=K26} -> 43.662818
B30: Long-term Debt | C30: {=Debt_Interest!C9} -> 45 | D30: {=Debt_Interest!D9} -> 40 | E30: {=Debt_Interest!E9} -> 35 | F30: {=Debt_Interest!F9} -> 30 | G30: {=Debt_Interest!G9} -> 25 | H30: {=Debt_Interest!H9} -> 20 | I30: {=Debt_Interest!I9} -> 15 | J30: {=Debt_Interest!J9} -> 10 | K30: {=Debt_Interest!K9} -> 5
B32: TOTAL LIABILITIES | C32: =C28+C30 -> 63.493151 | D32: =D28+D30 -> 61.993205 | E32: =E28+E30 -> 60.877 | F32: =F28+F30 -> 59.935081 | G32: =G28+G30 -> 59.58812 | H32: =H28+H30 -> 57.095759 | I32: =I28+I30 -> 54.414892 | J32: =J28+J30 -> 51.485562 | K32: =K28+K30 -> 48.662818
B35: EQUITY
B36: Total Equity | C36: {=Equity_Dividends!C17} -> 83.45735 | D36: {=Equity_Dividends!D17} -> 93.64175 | E36: {=Equity_Dividends!E17} -> 108.16506 | F36: {=Equity_Dividends!F17} -> 126.58513 | G36: {=Equity_Dividends!G17} -> 149.23033 | H36: {=Equity_Dividends!H17} -> 176.27454 | I36: {=Equity_Dividends!I17} -> 207.9758 | J36: {=Equity_Dividends!J17} -> 243.03487 | K36: {=Equity_Dividends!K17} -> 281.73258
B38: TOTAL LIABILITIES & EQUITY | C38: =C32+C36 -> 146.9505 | D38: =D32+D36 -> 155.63496 | E38: =E32+E36 -> 169.04206 | F38: =F32+F36 -> 186.52021 | G38: =G32+G36 -> 208.81845 | H38: =H32+H36 -> 233.3703 | I38: =I32+I36 -> 262.39069 | J38: =J32+J36 -> 294.52043 | K38: =K32+K36 -> 330.3954
B40: BALANCE CHECK | C40: =C20-C38 -> -0.0010486301 | D40: =D20-D38 -> -4.6820486 | E40: =E20-E38 -> -4.6820486 | F40: =F20-F38 -> -4.6820486 | G40: =G20-G38 -> -4.6820486 | H40: =H20-H38 -> -4.6820486 | I40: =I20-I38 -> -4.6820486 | J40: =J20-J38 -> -4.6820486 | K40: =K20-K38 -> -4.6820486

Sheet Cash_Flow
B2: CASH FLOW STATEMENT
B3: ($M unless noted)
B5: Period | C5: Year 0 | D5: Year 1 | E5: Year 2 | F5: Year 3 | G5: Year 4 | H5: Year 5 | I5: Year 6 | J5: Year 7 | K5: Year 8
B7: OPERATING ACTIVITIES
B8: Net Income | C8: {=Income_Statement!C26} -> 5.319 | D8: {=Income_Statement!D26} -> 10.1844 | E8: {=Income_Statement!E26} -> 14.523313 | F8: {=Income_Statement!F26} -> 18.420068 | G8: {=Income_Statement!G26} -> 22.645203 | H8: {=Income_Statement!H26} -> 27.04421 | I8: {=Income_Statement!I26} -> 31.701253 | J8: {=Income_Statement!J26} -> 35.05907 | K8: {=Income_Statement!K26} -> 38.697718
B9: (+) Depreciation | C9: {=PPE_Depreciation!C15} -> 4 | D9: {=PPE_Depreciation!D15} -> 5.065 | E9: {=PPE_Depreciation!E15} -> 5.7057325 | F9: {=PPE_Depreciation!F15} -> 6.2970365 | G9: {=PPE_Depreciation!G15} -> 6.8048858 | H9: {=PPE_Depreciation!H15} -> 7.1987689 | I9: {=PPE_Depreciation!I15} -> 7.5479715 | J9: {=PPE_Depreciation!J15} -> 7.9315632 | K9: {=PPE_Depreciation!K15} -> 8.3450991
B10: (-) Change in NWC | C10: 0 | D10: =-Working_Capital!D24 -> -0.015780822 | E10: =-Working_Capital!E24 -> -1.707074 | F10: =-Working_Capital!F24 -> -0.67492888 | G10: =-Working_Capital!G24 -> 2.525028 | H10: =-Working_Capital!H24 -> -2.9015589 | I10: =-Working_Capital!I24 -> -2.7327759 | J10: =-Working_Capital!J24 -> -2.4961083 | K10: =-Working_Capital!K24 -> -2.642665
B12: Cash from Operations | C12: =C8+C9 -> 9.319 | D12: =D8+D9+D10 -> 15.233619 | E12: =E8+E9+E10 -> 18.521971 | F12: =F8+F9+F10 -> 24.042175 | G12: =G8+G9+G10 -> 31.975117 | H12: =H8+H9+H10 -> 31.34142 | I12: =I8+I9+I10 -> 36.516449 | J12: =J8+J9+J10 -> 40.494525 | K12: =K8+K9+K10 -> 44.400152
B14: INVESTING ACTIVITIES
B15: (-) Capex | C15: =-PPE_Depreciation!C10 -> -9 | D15: =-PPE_Depreciation!D10 -> -11.3 | E15: =-PPE_Depreciation!E10 -> -11.64465 | F15: =-PPE_Depreciation!F10 -> -11.592896 | G15: =-PPE_Depreciation!G10 -> -11.158162 | H15: =-PPE_Depreciation!H10 -> -10.32927 | I15: =-PPE_Depreciation!I10 -> -11.052319 | J15: =-PPE_Depreciation!J10 -> -11.715458 | K15: =-PPE_Depreciation!K10 -> -12.418386
B17: Cash from Investing | C17: {=C15} -> -9 | D17: {=D15} -> -11.3 | E17: {=E15} -> -11.64465 | F17: {=F15} -> -11.592896 | G17: {=G15} -> -11.158162 | H17: {=H15} -> -10.32927 | I17: {=I15} -> -11.052319 | J17: {=J15} -> -11.715458 | K17: {=K15} -> -12.418386
B19: FINANCING ACTIVITIES
B20: (-) Debt Paydown | C20: =-Debt_Interest!C8 -> -5 | D20: =-Debt_Interest!D8 -> -5 | E20: =-Debt_Interest!E8 -> -5 | F20: =-Debt_Interest!F8 -> -5 | G20: =-Debt_Interest!G8 -> -5 | H20: =-Debt_Interest!H8 -> -5 | I20: =-Debt_Interest!I8 -> -5 | J20: =-Debt_Interest!J8 -> -5 | K20: =-Debt_Interest!K8 -> -5
B21: (-) Dividends | C21: 0 | D21: =-Equity_Dividends!D10 -> 0 | E21: =-Equity_Dividends!E10 -> 0 | F21: =-Equity_Dividends!F10 -> 0 | G21: =-Equity_Dividends!G10 -> 0 | H21: =-Equity_Dividends!H10 -> 0 | I21: =-Equity_Dividends!I10 -> 0 | J21: =-Equity_Dividends!J10 -> 0 | K21: =-Equity_Dividends!K10 -> 0
B23: Cash from Financing | C23: {=C20} -> -5 | D23: =D20+D21 -> -5 | E23: =E20+E21 -> -5 | F23: =F20+F21 -> -5 | G23: =G20+G21 -> -5 | H23: =H20+H21 -> -5 | I23: =I20+I21 -> -5 | J23: =J20+J21 -> -5 | K23: =K20+K21 -> -5
B25: NET CHANGE IN CASH | C25: =C12+C17+C23 -> -4.681 | D25: =D12+D17+D23 -> -1.0663808 | E25: =E12+E17+E23 -> 1.8773211 | F25: =F12+F17+F23 -> 7.4492794 | G25: =G12+G17+G23 -> 15.816955 | H25: =H12+H17+H23 -> 16.012149 | I25: =I12+I17+I23 -> 20.46413 | J25: =J12+J17+J23 -> 23.779066 | K25: =K12+K17+K23 -> 26.981766
B27: CASH RECONCILIATION
B28: Beginning Cash | C28: {=Cover_Assumptions!C41} -> 41.47 | D28: {=C30} -> 36.789 | E28: {=D30} -> 35.722619 | F28: {=E30} -> 37.59994 | G28: {=F30} -> 45.04922 | H28: {=G30} -> 60.866174 | I28: {=H30} -> 76.878324 | J28: {=I30} -> 97.342453 | K28: {=J30} -> 121.12152
B29: (+) Change in Cash | C29: {=C25} -> -4.681 | D29: {=D25} -> -1.0663808 | E29: {=E25} -> 1.8773211 | F29: {=F25} -> 7.4492794 | G29: {=G25} -> 15.816955 | H29: {=H25} -> 16.012149 | I29: {=I25} -> 20.46413 | J29: {=J25} -> 23.779066 | K29: {=K25} -> 26.981766
B30: Ending Cash | C30: =C28+C29 -> 36.789 | D30: =D28+D29 -> 35.722619 | E30: =E28+E29 -> 37.59994 | F30: =F28+F29 -> 45.04922 | G30: =G28+G29 -> 60.866174 | H30: =H28+H29 -> 76.878324 | I30: =I28+I29 -> 97.342453 | J30: =J28+J29 -> 121.12152 | K30: =K28+K29 -> 148.10329

Sheet Revenue_Build
B2: REVENUE BUILD
B4: Period | C4: Year 0 | D4: Year 1 | E4: Year 2 | F4: Year 3 | G4: Year 4 | H4: Year 5 | I4: Year 6 | J4: Year 7 | K4: Year 8
B6: Revenue Growth Rate | C6: 0 | D6: {=Cover_Assumptions!D11} -> 0.13 | E6: {=Cover_Assumptions!E11} -> 0.145 | F6: {=Cover_Assumptions!F11} -> 0.12 | G6: {=Cover_Assumptions!G11} -> 0.1 | H6: {=Cover_Assumptions!H11} -> 0.08 | I6: {=Cover_Assumptions!I11} -> 0.07 | J6: {=Cover_Assumptions!J11} -> 0.06 | K6: {=Cover_Assumptions!K11} -> 0.06
B8: Revenue ($M) | C8: {=Cover_Assumptions!C10} -> 200 | D8: =C8*(1+D6) -> 226 | E8: =D8*(1+E6) -> 258.77 | F8: =E8*(1+F6) -> 289.8224 | G8: =F8*(1+G6) -> 318.80464 | H8: =G8*(1+H6) -> 344.30901 | I8: =H8*(1+I6) -> 368.41064 | J8: =I8*(1+J6) -> 390.51528 | K8: =J8*(1+K6) -> 413.9462
B10: OUTPUT: Link to Income Statement

Sheet COGS_OpEx
B2: COGS & OPERATING EXPENSES
B4: Period | C4: Year 0 | D4: Year 1 | E4: Year 2 | F4: Year 3 | G4: Year 4 | H4: Year 5 | I4: Year 6 | J4: Year 7 | K4: Year 8
B6: Revenue ($M) | C6: {=Revenue_Build!C8} -> 200 | D6: {=Revenue_Build!D8} -> 226 | E6: {=Revenue_Build!E8} -> 258.77 | F6: {=Revenue_Build!F8} -> 289.8224 | G6: {=Revenue_Build!G8} -> 318.80464 | H6: {=Revenue_Build!H8} -> 344.30901 | I6: {=Revenue_Build!I8} -> 368.41064 | J6: {=Revenue_Build!J8} -> 390.51528 | K6: {=Revenue_Build!K8} -> 413.9462
B8: Gross Margin % | C8: {=Cover_Assumptions!C14} -> 0.25 | D8: {=Cover_Assumptions!D14} -> 0.26 | E8: {=Cover_Assumptions!E14} -> 0.27 | F8: {=Cover_Assumptions!F14} -> 0.275 | G8: {=Cover_Assumptions!G14} -> 0.28 | H8: {=Cover_Assumptions!H14} -> 0.285 | I8: {=Cover_Assumptions!I14} -> 0.29 | J8: {=Cover_Assumptions!J14} -> 0.295 | K8: {=Cover_Assumptions!K14} -> 0.3
B10: COGS ($M) | C10: =C6*(1-C8) -> 150 | D10: =D6*(1-D8) -> 167.24 | E10: =E6*(1-E8) -> 188.9021 | F10: =F6*(1-F8) -> 210.12124 | G10: =G6*(1-G8) -> 229.53934 | H10: =H6*(1-H8) -> 246.18094 | I10: =I6*(1-I8) -> 261.57156 | J10: =J6*(1-J8) -> 275.31327 | K10: =K6*(1-K8) -> 289.76234
B12: Operating Expenses % of Revenue | C12: {=Cover_Assumptions!C15} -> 0.18 | D12: {=Cover_Assumptions!D15} -> 0.175 | E12: {=Cover_Assumptions!E15} -> 0.17 | F12: {=Cover_Assumptions!F15} -> 0.165 | G12: {=Cover_Assumptions!G15} -> 0.16 | H12: {=Cover_Assumptions!H15} -> 0.155 | I12: {=Cover_Assumptions!I15} -> 0.15 | J12: {=Cover_Assumptions!J15} -> 0.15 | K12: {=Cover_Assumptions!K15} -> 0.15
B14: Operating Expenses ($M) | C14: =C6*C12 -> 36 | D14: =D6*D12 -> 39.55 | E14: =E6*E12 -> 43.9909 | F14: =F6*F12 -> 47.820696 | G14: =G6*G12 -> 51.008742 | H14: =H6*H12 -> 53.367897 | I14: =I6*I12 -> 55.261596 | J14: =J6*J12 -> 58.577292 | K14: =K6*K12 -> 62.09193
B16: OUTPUT: COGS links to Income Statement
B17: OUTPUT: OpEx links to Income Statement

Sheet PPE_Depreciation
B2: PP&E & DEPRECIATION SCHEDULE
B4: Period | C4: Year 0 | D4: Year 1 | E4: Year 2 | F4: Year 3 | G4: Year 4 | H4: Year 5 | I4: Year 6 | J4: Year 7 | K4: Year 8
B6: Revenue ($M) | C6: {=Revenue_Build!C8} -> 200 | D6: {=Revenue_Build!D8} -> 226 | E6: {=Revenue_Build!E8} -> 258.77 | F6: {=Revenue_Build!F8} -> 289.8224 | G6: {=Revenue_Build!G8} -> 318.80464 | H6: {=Revenue_Build!H8} -> 344.30901 | I6: {=Revenue_Build!I8} -> 368.41064 | J6: {=Revenue_Build!J8} -> 390.51528 | K6: {=Revenue_Build!K8} -> 413.9462
B8: Capex % of Revenue | C8: {=Cover_Assumptions!C23} -> 0.045 | D8: {=Cover_Assumptions!D23} -> 0.05 | E8: {=Cover_Assumptions!E23} -> 0.045 | F8: {=Cover_Assumptions!F23} -> 0.04 | G8: {=Cover_Assumptions!G23} -> 0.035 | H8: {=Cover_Assumptions!H23} -> 0.03 | I8: {=Cover_Assumptions!I23} -> 0.03 | J8: {=Cover_Assumptions!J23} -> 0.03 | K8: {=Cover_Assumptions!K23} -> 0.03
B10: Capex ($M) | C10: =C6*C8 -> 9 | D10: =D6*D8 -> 11.3 | E10: =E6*E8 -> 11.64465 | F10: =F6*F8 -> 11.592896 | G10: =G6*G8 -> 11.158162 | H10: =H6*H8 -> 10.32927 | I10: =I6*I8 -> 11.052319 | J10: =J6*J8 -> 11.715458 | K10: =K6*K8 -> 12.418386
B12: PP&E ROLLFORWARD
B13: Beginning PP&E, net | C13: {=Cover_Assumptions!C38} -> 40 | D13: {=C17} -> 45 | E13: {=D17} -> 51.235 | F13: {=E17} -> 57.173918 | G13: {=F17} -> 62.469777 | H13: {=G17} -> 66.823054 | I13: {=H17} -> 69.953555 | J13: {=I17} -> 73.457903 | K13: {=J17} -> 77.241798
B14: (+) Capex | C14: {=C10} -> 9 | D14: {=D10} -> 11.3 | E14: {=E10} -> 11.64465 | F14: {=F10} -> 11.592896 | G14: {=G10} -> 11.158162 | H14: {=H10} -> 10.32927 | I14: {=I10} -> 11.052319 | J14: {=J10} -> 11.715458 | K14: {=K10} -> 12.418386
B15: (-) Depreciation | C15: =C13/Cover_Assumptions!$C$24 -> 4 | D15: =(D13+D14/2)/Cover_Assumptions!$C$24 -> 5.065 | E15: =(E13+E14/2)/Cover_Assumptions!$C$24 -> 5.7057325 | F15: =(F13+F14/2)/Cover_Assumptions!$C$24 -> 6.2970365 | G15: =(G13+G14/2)/Cover_Assumptions!$C$24 -> 6.8048858 | H15: =(H13+H14/2)/Cover_Assumptions!$C$24 -> 7.1987689 | I15: =(I13+I14/2)/Cover_Assumptions!$C$24 -> 7.5479715 | J15: =(J13+J14/2)/Cover_Assumptions!$C$24 -> 7.9315632 | K15: =(K13+K14/2)/Cover_Assumptions!$C$24 -> 8.3450991
B17: Ending PP&E, net | C17: =C13+C14-C15 -> 45 | D17: =D13+D14-D15 -> 51.235 | E17: =E13+E14-E15 -> 57.173918 | F17: =F13+F14-F15 -> 62.469777 | G17: =G13+G14-G15 -> 66.823054 | H17: =H13+H14-H15 -> 69.953555 | I17: =I13+I14-I15 -> 73.457903 | J17: =J13+J14-J15 -> 77.241798 | K17: =K13+K14-K15 -> 81.315085
B19: OUTPUT: Ending PP&E links to Balance Sheet
B20: OUTPUT: Depreciation links to Income Statement & Cash Flow

Sheet Working_Capital
B2: WORKING CAPITAL SCHEDULE
B4: Period | C4: Year 0 | D4: Year 1 | E4: Year 2 | F4: Year 3 | G4: Year 4 | H4: Year 5 | I4: Year 6 | J4: Year 7 | K4: Year 8
B6: Revenue ($M) | C6: {=Revenue_Build!C8} -> 200 | D6: {=Revenue_Build!D8} -> 226 | E6: {=Revenue_Build!E8} -> 258.77 | F6: {=Revenue_Build!F8} -> 289.8224 | G6: {=Revenue_Build!G8} -> 318.80464 | H6: {=Revenue_Build!H8} -> 344.30901 | I6: {=Revenue_Build!I8} -> 368.41064 | J6: {=Revenue_Build!J8} -> 390.51528 | K6: {=Revenue_Build!K8} -> 413.9462
B7: COGS ($M) | C7: {=COGS_OpEx!C10} -> 150 | D7: {=COGS_OpEx!D10} -> 167.24 | E7: {=COGS_OpEx!E10} -> 188.9021 | F7: {=COGS_OpEx!F10} -> 210.12124 | G7: {=COGS_OpEx!G10} -> 229.53934 | H7: {=COGS_OpEx!H10} -> 246.18094 | I7: {=COGS_OpEx!I10} -> 261.57156 | J7: {=COGS_OpEx!J10} -> 275.31327 | K7: {=COGS_OpEx!K10} -> 289.76234
B9: ACCOUNTS RECEIVABLE
B10: Days AR | C10: {=Cover_Assumptions!C18} -> 45 | D10: {=Cover_Assumptions!D18} -> 42 | E10: {=Cover_Assumptions!E18} -> 40 | F10: {=Cover_Assumptions!F18} -> 38 | G10: {=Cover_Assumptions!G18} -> 35 | H10: {=Cover_Assumptions!H18} -> 35 | I10: {=Cover_Assumptions!I18} -> 35 | J10: {=Cover_Assumptions!J18} -> 35 | K10: {=Cover_Assumptions!K18} -> 35
B11: Accounts Receivable ($M) | C11: =(C6/365)*C10 -> 24.657534 | D11: =(D6/365)*D10 -> 26.005479 | E11: =(E6/365)*E10 -> 28.358356 | F11: =(F6/365)*F10 -> 30.173291 | G11: =(G6/365)*G10 -> 30.570308 | H11: =(H6/365)*H10 -> 33.015933 | I11: =(I6/365)*I10 -> 35.327048 | J11: =(J6/365)*J10 -> 37.446671 | K11: =(K6/365)*K10 -> 39.693471
B13: INVENTORY
B14: Days Inventory | C14: {=Cover_Assumptions!C19} -> 75 | D14: {=Cover_Assumptions!D19} -> 72 | E14: {=Cover_Assumptions!E19} -> 70 | F14: {=Cover_Assumptions!F19} -> 68 | G14: {=Cover_Assumptions!G19} -> 65 | H14: {=Cover_Assumptions!H19} -> 65 | I14: {=Cover_Assumptions!I19} -> 65 | J14: {=Cover_Assumptions!J19} -> 65 | K14: {=Cover_Assumptions!K19} -> 65
B15: Inventory ($M) | C15: =(C7/365)*C14 -> 30.821918 | D15: =(D7/365)*D14 -> 32.989808 | E15: =(E7/365)*E14 -> 36.2278 | F15: =(F7/365)*F14 -> 39.145875 | G15: =(G7/365)*G14 -> 40.876869 | H15: =(H7/365)*H14 -> 43.840442 | I15: =(I7/365)*I14 -> 46.581236 | J15: =(J7/365)*J14 -> 49.028391 | K15: =(K7/365)*K14 -> 51.601512
B17: ACCOUNTS PAYABLE
B18: Days AP | C18: {=Cover_Assumptions!C20} -> 45 | D18: {=Cover_Assumptions!D20} -> 48 | E18: {=Cover_Assumptions!E20} -> 50 | F18: {=Cover_Assumptions!F20} -> 52 | G18: {=Cover_Assumptions!G20} -> 55 | H18: {=Cover_Assumptions!H20} -> 55 | I18: {=Cover_Assumptions!I20} -> 55 | J18: {=Cover_Assumptions!J20} -> 55 | K18: {=Cover_Assumptions!K20} -> 55
B19: Accounts Payable ($M) | C19: =(C7/365)*C18 -> 18.493151 | D19: =(D7/365)*D18 -> 21.993205 | E19: =(E7/365)*E18 -> 25.877 | F19: =(F7/365)*F18 -> 29.935081 | G19: =(G7/365)*G18 -> 34.58812 | H19: =(H7/365)*H18 -> 37.095759 | I19: =(I7/365)*I18 -> 39.414892 | J19: =(J7/365)*J18 -> 41.485562 | K19: =(K7/365)*K18 -> 43.662818
B21: NET WORKING CAPITAL
B22: Net Working Capital ($M) | C22: =C11+C15-C19 -> 36.986301 | D22: =D11+D15-D19 -> 37.002082 | E22: =E11+E15-E19 -> 38.709156 | F22: =F11+F15-F19 -> 39.384085 | G22: =G11+G15-G19 -> 36.859057 | H22: =H11+H15-H19 -> 39.760616 | I22: =I11+I15-I19 -> 42.493392 | J22: =J11+J15-J19 -> 44.9895 | K22: =K11+K15-K19 -> 47.632165
B24: Change in NWC ($M) | C24: 0 | D24: =D22-C22 -> 0.015780822 | E24: =E22-D22 -> 1.707074 | F24: =F22-E22 -> 0.67492888 | G24: =G22-F22 -> -2.525028 | H24: =H22-G22 -> 2.9015589 | I24: =I22-H22 -> 2.7327759 | J24: =J22-I22 -> 2.4961083 | K24: =K22-J22 -> 2.642665
B26: OUTPUT: AR, Inventory, AP link to Balance Sheet
B27: OUTPUT: Change in NWC links to Cash Flow Statement

Sheet Debt_Interest
B2: DEBT & INTEREST SCHEDULE
B4: Period | C4: Year 0 | D4: Year 1 | E4: Year 2 | F4: Year 3 | G4: Year 4 | H4: Year 5 | I4: Year 6 | J4: Year 7 | K4: Year 8
B6: DEBT ROLLFORWARD
B7: Beginning Debt Balance ($M) | C7: {=Cover_Assumptions!C27} -> 50 | D7: {=C9} -> 45 | E7: {=D9} -> 40 | F7: {=E9} -> 35 | G7: {=F9} -> 30 | H7: {=G9} -> 25 | I7: {=H9} -> 20 | J7: {=I9} -> 15 | K7: {=J9} -> 10
B8: (-) Debt Amortization ($M) | C8: {=Cover_Assumptions!$C$28} -> 5 | D8: {=Cover_Assumptions!$C$28} -> 5 | E8: {=Cover_Assumptions!$C$28} -> 5 | F8: {=Cover_Assumptions!$C$28} -> 5 | G8: {=Cover_Assumptions!$C$28} -> 5 | H8: {=Cover_Assumptions!$C$28} -> 5 | I8: {=Cover_Assumptions!$C$28} -> 5 | J8: {=Cover_Assumptions!$C$28} -> 5 | K8: {=Cover_Assumptions!$C$28} -> 5
B9: Ending Debt Balance ($M) | C9: =MAX(0,C7-C8) -> 45 | D9: =MAX(0,D7-D8) -> 40 | E9: =MAX(0,E7-E8) -> 35 | F9: =MAX(0,F7-F8) -> 30 | G9: =MAX(0,G7-G8) -> 25 | H9: =MAX(0,H7-H8) -> 20 | I9: =MAX(0,I7-I8) -> 15 | J9: =MAX(0,J7-J8) -> 10 | K9: =MAX(0,K7-K8) -> 5
B11: INTEREST EXPENSE
B12: Average Debt Balance ($M) | C12: =(C7+C9)/2 -> 47.5 | D12: =(D7+D9)/2 -> 42.5 | E12: =(E7+E9)/2 -> 37.5 | F12: =(F7+F9)/2 -> 32.5 | G12: =(G7+G9)/2 -> 27.5 | H12: =(H7+H9)/2 -> 22.5 | I12: =(I7+I9)/2 -> 17.5 | J12: =(J7+J9)/2 -> 12.5 | K12: =(K7+K9)/2 -> 7.5
B13: Interest Rate | C13: {=Cover_Assumptions!C29} -> 0.055 | D13: {=Cover_Assumptions!D29} -> 0 | E13: {=Cover_Assumptions!E29} -> 0 | F13: {=Cover_Assumptions!F29} -> 0 | G13: {=Cover_Assumptions!G29} -> 0 | H13: {=Cover_Assumptions!H29} -> 0 | I13: {=Cover_Assumptions!I29} -> 0 | J13: {=Cover_Assumptions!J29} -> 0 | K13: {=Cover_Assumptions!K29} -> 0
B14: Interest Expense ($M) | C14: =C12*C13 -> 2.6125 | D14: =D12*D13 -> 0 | E14: =E12*E13 -> 0 | F14: =F12*F13 -> 0 | G14: =G12*G13 -> 0 | H14: =H12*H13 -> 0 | I14: =I12*I13 -> 0 | J14: =J12*J13 -> 0 | K14: =K12*K13 -> 0
B16: OUTPUT: Ending Debt links to Balance Sheet
B17: OUTPUT: Interest Expense links to Income Statement
B18: OUTPUT: Debt Amortization links to Cash Flow Statement

Sheet Equity_Dividends
B2: EQUITY & DIVIDENDS SCHEDULE
B4: Period | C4: Year 0 | D4: Year 1 | E4: Year 2 | F4: Year 3 | G4: Year 4 | H4: Year 5 | I4: Year 6 | J4: Year 7 | K4: Year 8
B6: Net Income ($M) | C6: {=Income_Statement!C26} -> 5.319 | D6: {=Income_Statement!D26} -> 10.1844 | E6: {=Income_Statement!E26} -> 14.523313 | F6: {=Income_Statement!F26} -> 18.420068 | G6: {=Income_Statement!G26} -> 22.645203 | H6: {=Income_Statement!H26} -> 27.04421 | I6: {=Income_Statement!I26} -> 31.701253 | J6: {=Income_Statement!J26} -> 35.05907 | K6: {=Income_Statement!K26} -> 38.697718
B8: DIVIDEND CALCULATION
B9: Dividend Payout Ratio | C9: {=Cover_Assumptions!C35} -> 0.35 | D9: {=Cover_Assumptions!D35} -> 0 | E9: {=Cover_Assumptions!E35} -> 0 | F9: {=Cover_Assumptions!F35} -> 0 | G9: {=Cover_Assumptions!G35} -> 0 | H9: {=Cover_Assumptions!H35} -> 0 | I9: {=Cover_Assumptions!I35} -> 0 | J9: {=Cover_Assumptions!J35} -> 0 | K9: {=Cover_Assumptions!K35} -> 0
B10: Dividends ($M) | C10: =MAX(0,C6*C9) -> 1.86165 | D10: =MAX(0,D6*D9) -> 0 | E10: =MAX(0,E6*E9) -> 0 | F10: =MAX(0,F6*F9) -> 0 | G10: =MAX(0,G6*G9) -> 0 | H10: =MAX(0,H6*H9) -> 0 | I10: =MAX(0,I6*I9) -> 0 | J10: =MAX(0,J6*J9) -> 0 | K10: =MAX(0,K6*K9) -> 0
B12: EQUITY ROLLFORWARD
B13: Beginning Equity ($M) | C13: {=Cover_Assumptions!C39} -> 80 | D13: {=C17} -> 83.45735 | E13: {=D17} -> 93.64175 | F13: {=E17} -> 108.16506 | G13: {=F17} -> 126.58513 | H13: {=G17} -> 149.23033 | I13: {=H17} -> 176.27454 | J13: {=I17} -> 207.9758 | K13: {=J17} -> 243.03487
B14: (+) Net Income ($M) | C14: {=C6} -> 5.319 | D14: {=D6} -> 10.1844 | E14: {=E6} -> 14.523313 | F14: {=F6} -> 18.420068 | G14: {=G6} -> 22.645203 | H14: {=H6} -> 27.04421 | I14: {=I6} -> 31.701253 | J14: {=J6} -> 35.05907 | K14: {=K6} -> 38.697718
B15: (-) Dividends ($M) | C15: {=C10} -> 1.86165 | D15: {=D10} -> 0 | E15: {=E10} -> 0 | F15: {=F10} -> 0 | G15: {=G10} -> 0 | H15: {=H10} -> 0 | I15: {=I10} -> 0 | J15: {=J10} -> 0 | K15: {=K10} -> 0
B17: Ending Equity ($M) | C17: =C13+C14-C15 -> 83.45735 | D17: =D13+D14-D15 -> 93.64175 | E17: =E13+E14-E15 -> 108.16506 | F17: =F13+F14-F15 -> 126.58513 | G17: =G13+G14-G15 -> 149.23033 | H17: =H13+H14-H15 -> 176.27454 | I17: =I13+I14-I15 -> 207.9758 | J17: =J13+J14-J15 -> 243.03487 | K17: =K13+K14-K15 -> 281.73258
B19: OUTPUT: Ending Equity links to Balance Sheet
B20: OUTPUT: Dividends link to Cash Flow Statement

Sheet Output_Ratios
B2: MODEL OUTPUT & KEY RATIOS
B4: Period | C4: Year 0 | D4: Year 1 | E4: Year 2 | F4: Year 3 | G4: Year 4 | H4: Year 5 | I4: Year 6 | J4: Year 7 | K4: Year 8
B6: REVENUE METRICS
B7: Revenue ($M) | C7: {=Income_Statement!C7} -> 200 | D7: {=Income_Statement!D7} -> 226 | E7: {=Income_Statement!E7} -> 258.77 | F7: {=Income_Statement!F7} -> 289.8224 | G7: {=Income_Statement!G7} -> 318.80464 | H7: {=Income_Statement!H7} -> 344.30901 | I7: {=Income_Statement!I7} -> 368.41064 | J7: {=Income_Statement!J7} -> 390.51528 | K7: {=Income_Statement!K7} -> 413.9462
B8: Revenue Growth % | C8: 0 | D8: =(D7-C7)/C7 -> 0.13 | E8: =(E7-D7)/D7 -> 0.145 | F8: =(F7-E7)/E7 -> 0.12 | G8: =(G7-F7)/F7 -> 0.1 | H8: =(H7-G7)/G7 -> 0.08 | I8: =(I7-H7)/H7 -> 0.07 | J8: =(J7-I7)/I7 -> 0.06 | K8: =(K7-J7)/J7 -> 0.06
B10: PROFITABILITY MARGINS
B11: Gross Margin % | C11: {=Income_Statement!C11} -> 0.25 | D11: {=Income_Statement!D11} -> 0.26 | E11: {=Income_Statement!E11} -> 0.27 | F11: {=Income_Statement!F11} -> 0.275 | G11: {=Income_Statement!G11} -> 0.28 | H11: {=Income_Statement!H11} -> 0.285 | I11: {=Income_Statement!I11} -> 0.29 | J11: {=Income_Statement!J11} -> 0.295 | K11: {=Income_Statement!K11} -> 0.3
B12: EBITDA Margin % | C12: {=Income_Statement!C16} -> 0.07 | D12: {=Income_Statement!D16} -> 0.085 | E12: {=Income_Statement!E16} -> 0.1 | F12: {=Income_Statement!F16} -> 0.11 | G12: {=Income_Statement!G16} -> 0.12 | H12: {=Income_Statement!H16} -> 0.13 | I12: {=Income_Statement!I16} -> 0.14 | J12: {=Income_Statement!J16} -> 0.145 | K12: {=Income_Statement!K16} -> 0.15
B13: Net Margin % | C13: {=Income_Statement!C27} -> 0.026595 | D13: {=Income_Statement!D27} -> 0.045063717 | E13: {=Income_Statement!E27} -> 0.056124406 | F13: {=Income_Statement!F27} -> 0.063556398 | G13: {=Income_Statement!G27} -> 0.071031598 | H13: {=Income_Statement!H27} -> 0.078546332 | I13: {=Income_Statement!I27} -> 0.08604869 | J13: {=Income_Statement!J27} -> 0.089776435 | K13: {=Income_Statement!K27} -> 0.093484898
B15: RETURNS
B16: ROA (Return on Assets) | C16: =Income_Statement!C26/Balance_Sheet!C20 -> 0.03619612 | D16: =Income_Statement!D26/Balance_Sheet!D20 -> 0.067467399 | E16: =Income_Statement!E26/Balance_Sheet!E20 -> 0.088362809 | F16: =Income_Statement!F26/Balance_Sheet!F20 -> 0.10129924 | G16: =Income_Statement!G26/Balance_Sheet!G20 -> 0.11093172 | H16: =Income_Statement!H26/Balance_Sheet!H20 -> 0.11825798 | I16: =Income_Statement!I26/Balance_Sheet!I20 -> 0.12301199 | J16: =Income_Statement!J26/Balance_Sheet!J20 -> 0.12096076 | K16: =Income_Statement!K26/Balance_Sheet!K20 -> 0.11880912
B17: ROE (Return on Equity) | C17: =Income_Statement!C26/Balance_Sheet!C36 -> 0.063733152 | D17: =Income_Statement!D26/Balance_Sheet!D36 -> 0.10875918 | E17: =Income_Statement!E26/Balance_Sheet!E36 -> 0.1342699 | F17: =Income_Statement!F26/Balance_Sheet!F36 -> 0.14551526 | G17: =Income_Statement!G26/Balance_Sheet!G36 -> 0.15174665 | H17: =Income_Statement!H26/Balance_Sheet!H36 -> 0.15342096 | I17: =Income_Statement!I26/Balance_Sheet!I36 -> 0.15242761 | J17: =Income_Statement!J26/Balance_Sheet!J36 -> 0.14425531 | K17: =Income_Statement!K26/Balance_Sheet!K36 -> 0.1373562
B19: LEVERAGE RATIOS
B20: Debt / EBITDA | C20: =Balance_Sheet!C30/Income_Statement!C15 -> 3.2142857 | D20: =Balance_Sheet!D30/Income_Statement!D15 -> 2.0822488 | E20: =Balance_Sheet!E30/Income_Statement!E15 -> 1.3525525 | F20: =Balance_Sheet!F30/Income_Statement!F15 -> 0.94101516 | G20: =Balance_Sheet!G30/Income_Statement!G15 -> 0.65348275 | H20: =Balance_Sheet!H30/Income_Statement!H15 -> 0.44682581 | I20: =Balance_Sheet!I30/Income_Statement!I15 -> 0.29082454 | J20: =Balance_Sheet!J30/Income_Statement!J15 -> 0.17660133 | K20: =Balance_Sheet!K30/Income_Statement!K15 -> 0.080525763
B21: Net Debt / EBITDA | C21: =(Balance_Sheet!C30-Balance_Sheet!C10)/Income_Statement!C15 -> 0.25214286 | D21: =(Balance_Sheet!D30-Balance_Sheet!D10)/Income_Statement!D15 -> 0.22266428 | E21: =(Balance_Sheet!E30-Balance_Sheet!E10)/Income_Statement!E15 -> -0.10047302 | F21: =(Balance_Sheet!F30-Balance_Sheet!F10)/Income_Statement!F15 -> -0.47205147 | G21: =(Balance_Sheet!G30-Balance_Sheet!G10)/Income_Statement!G15 -> -0.93751705 | H21: =(Balance_Sheet!H30-Balance_Sheet!H10)/Income_Statement!H15 -> -1.2707352 | I21: =(Balance_Sheet!I30-Balance_Sheet!I10)/Income_Statement!I15 -> -1.5964804 | J21: =(Balance_Sheet!J30-Balance_Sheet!J10)/Income_Statement!J15 -> -1.9624208 | K21: =(Balance_Sheet!K30-Balance_Sheet!K10)/Income_Statement!K15 -> -2.3047003
B22: Interest Coverage (EBIT / Interest) | C22: =_xlfn.IFERROR(Income_Statement!C20/(-Income_Statement!C21),0) -> 3.8277512 | D22: =_xlfn.IFERROR(Income_Statement!D20/(-Income_Statement!D21),0) -> 0 | E22: =_xlfn.IFERROR(Income_Statement!E20/(-Income_Statement!E21),0) -> 0 | F22: =_xlfn.IFERROR(Income_Statement!F20/(-Income_Statement!F21),0) -> 0 | G22: =_xlfn.IFERROR(Income_Statement!G20/(-Income_Statement!G21),0) -> 0 | H22: =_xlfn.IFERROR(Income_Statement!H20/(-Income_Statement!H21),0) -> 0 | I22: =_xlfn.IFERROR(Income_Statement!I20/(-Income_Statement!I21),0) -> 0 | J22: =_xlfn.IFERROR(Income_Statement!J20/(-Income_Statement!J21),0) -> 0 | K22: =_xlfn.IFERROR(Income_Statement!K20/(-Income_Statement!K21),0) -> 0
B24: WORKING CAPITAL METRICS
B25: Days AR | C25: {=Working_Capital!C10} -> 45 | D25: {=Working_Capital!D10} -> 42 | E25: {=Working_Capital!E10} -> 40 | F25: {=Working_Capital!F10} -> 38 | G25: {=Working_Capital!G10} -> 35 | H25: {=Working_Capital!H10} -> 35 | I25: {=Working_Capital!I10} -> 35 | J25: {=Working_Capital!J10} -> 35 | K25: {=Working_Capital!K10} -> 35
B26: Days Inventory | C26: {=Working_Capital!C14} -> 75 | D26: {=Working_Capital!D14} -> 72 | E26: {=Working_Capital!E14} -> 70 | F26: {=Working_Capital!F14} -> 68 | G26: {=Working_Capital!G14} -> 65 | H26: {=Working_Capital!H14} -> 65 | I26: {=Working_Capital!I14} -> 65 | J26: {=Working_Capital!J14} -> 65 | K26: {=Working_Capital!K14} -> 65
B27: Days AP | C27: {=Working_Capital!C18} -> 45 | D27: {=Working_Capital!D18} -> 48 | E27: {=Working_Capital!E18} -> 50 | F27: {=Working_Capital!F18} -> 52 | G27: {=Working_Capital!G18} -> 55 | H27: {=Working_Capital!H18} -> 55 | I27: {=Working_Capital!I18} -> 55 | J27: {=Working_Capital!J18} -> 55 | K27: {=Working_Capital!K18} -> 55
B28: Cash Conversion Cycle (Days) | C28: =C25+C26-C27 -> 75 | D28: =D25+D26-D27 -> 66 | E28: =E25+E26-E27 -> 60 | F28: =F25+F26-F27 -> 54 | G28: =G25+G26-G27 -> 45 | H28: =H25+H26-H27 -> 45 | I28: =I25+I26-I27 -> 45 | J28: =J25+J26-J27 -> 45 | K28: =K25+K26-K27 -> 45
B30: EBITDA ($M) | C30: {=Income_Statement!C15} -> 14 | D30: {=Income_Statement!D15} -> 19.21 | E30: {=Income_Statement!E15} -> 25.877 | F30: {=Income_Statement!F15} -> 31.880464 | G30: {=Income_Statement!G15} -> 38.256557 | H30: {=Income_Statement!H15} -> 44.760171 | I30: {=Income_Statement!I15} -> 51.57749 | J30: {=Income_Statement!J15} -> 56.624716 | K30: {=Income_Statement!K15} -> 62.09193
B32: CHART DATA
B33: Period | C33: Year 0 | D33: Year 1 | E33: Year 2 | F33: Year 3 | G33: Year 4 | H33: Year 5 | I33: Year 6 | J33: Year 7 | K33: Year 8
B34: Revenue | C34: {=C7} -> 200 | D34: {=D7} -> 226 | E34: {=E7} -> 258.77 | F34: {=F7} -> 289.8224 | G34: {=G7} -> 318.80464 | H34: {=H7} -> 344.30901 | I34: {=I7} -> 368.41064 | J34: {=J7} -> 390.51528 | K34: {=K7} -> 413.9462
B35: EBITDA | C35: {=C30} -> 14 | D35: {=D30} -> 19.21 | E35: {=E30} -> 25.877 | F35: {=F30} -> 31.880464 | G35: {=G30} -> 38.256557 | H35: {=H30} -> 44.760171 | I35: {=I30} -> 51.57749 | J35: {=J30} -> 56.624716 | K35: {=K30} -> 62.09193
B36: Period | C36: Year 0 | D36: Year 1 | E36: Year 2 | F36: Year 3 | G36: Year 4 | H36: Year 5 | I36: Year 6 | J36: Year 7 | K36: Year 8
B37: Cash | C37: {=Balance_Sheet!C10} -> 41.47 | D37: {=Balance_Sheet!D10} -> 35.722619 | E37: {=Balance_Sheet!E10} -> 37.59994 | F37: {=Balance_Sheet!F10} -> 45.04922 | G37: {=Balance_Sheet!G10} -> 60.866174 | H37: {=Balance_Sheet!H10} -> 76.878324 | I37: {=Balance_Sheet!I10} -> 97.342453 | J37: {=Balance_Sheet!J10} -> 121.12152 | K37: {=Balance_Sheet!K10} -> 148.10329

Sheet Audit_Checks
B2: MODEL AUDIT CHECKS
B3: All checks must show PASS (green) for model integrity
B5: Period | C5: Year 0 | D5: Year 1 | E5: Year 2 | F5: Year 3 | G5: Year 4 | H5: Year 5 | I5: Year 6 | J5: Year 7 | K5: Year 8
B7: 1. BALANCE SHEET CHECK
B8: Assets - Liabilities - Equity | C8: {=Balance_Sheet!C40} -> -0.0010486301 | D8: {=Balance_Sheet!D40} -> -4.6820486 | E8: {=Balance_Sheet!E40} -> -4.6820486 | F8: {=Balance_Sheet!F40} -> -4.6820486 | G8: {=Balance_Sheet!G40} -> -4.6820486 | H8: {=Balance_Sheet!H40} -> -4.6820486 | I8: {=Balance_Sheet!I40} -> -4.6820486 | J8: {=Balance_Sheet!J40} -> -4.6820486 | K8: {=Balance_Sheet!K40} -> -4.6820486
B9: Status | C9: =IF(ABS(C8)<0.01,"PASS","FAIL") -> PASS | D9: =IF(ABS(D8)<0.01,"PASS","FAIL") -> FAIL | E9: =IF(ABS(E8)<0.01,"PASS","FAIL") -> FAIL | F9: =IF(ABS(F8)<0.01,"PASS","FAIL") -> FAIL | G9: =IF(ABS(G8)<0.01,"PASS","FAIL") -> FAIL | H9: =IF(ABS(H8)<0.01,"PASS","FAIL") -> FAIL | I9: =IF(ABS(I8)<0.01,"PASS","FAIL") -> FAIL | J9: =IF(ABS(J8)<0.01,"PASS","FAIL") -> FAIL | K9: =IF(ABS(K8)<0.01,"PASS","FAIL") -> FAIL
B11: 2. CASH FLOW TIE-OUT
B12: CFS Ending Cash | C12: {=Cash_Flow!C30} -> 36.789 | D12: {=Cash_Flow!D30} -> 35.722619 | E12: {=Cash_Flow!E30} -> 37.59994 | F12: {=Cash_Flow!F30} -> 45.04922 | G12: {=Cash_Flow!G30} -> 60.866174 | H12: {=Cash_Flow!H30} -> 76.878324 | I12: {=Cash_Flow!I30} -> 97.342453 | J12: {=Cash_Flow!J30} -> 121.12152 | K12: {=Cash_Flow!K30} -> 148.10329
B13: BS Cash | C13: {=Balance_Sheet!C10} -> 41.47 | D13: {=Balance_Sheet!D10} -> 35.722619 | E13: {=Balance_Sheet!E10} -> 37.59994 | F13: {=Balance_Sheet!F10} -> 45.04922 | G13: {=Balance_Sheet!G10} -> 60.866174 | H13: {=Balance_Sheet!H10} -> 76.878324 | I13: {=Balance_Sheet!I10} -> 97.342453 | J13: {=Balance_Sheet!J10} -> 121.12152 | K13: {=Balance_Sheet!K10} -> 148.10329
B14: Difference | C14: =C12-C13 -> -4.681 | D14: =D12-D13 -> 0 | E14: =E12-E13 -> 0 | F14: =F12-F13 -> 0 | G14: =G12-G13 -> 0 | H14: =H12-H13 -> 0 | I14: =I12-I13 -> 0 | J14: =J12-J13 -> 0 | K14: =K12-K13 -> 0
B15: Status | C15: =IF(ABS(C14)<0.01,"PASS","FAIL") -> FAIL | D15: =IF(ABS(D14)<0.01,"PASS","FAIL") -> PASS | E15: =IF(ABS(E14)<0.01,"PASS","FAIL") -> PASS | F15: =IF(ABS(F14)<0.01,"PASS","FAIL") -> PASS | G15: =IF(ABS(G14)<0.01,"PASS","FAIL") -> PASS | H15: =IF(ABS(H14)<0.01,"PASS","FAIL") -> PASS | I15: =IF(ABS(I14)<0.01,"PASS","FAIL") -> PASS | J15: =IF(ABS(J14)<0.01,"PASS","FAIL") -> PASS | K15: =IF(ABS(K14)<0.01,"PASS","FAIL") -> PASS
B17: 3. REVENUE GROWTH CHECK
B18: Revenue Growth % | C18: 0 | D18: =(Income_Statement!D7-Income_Statement!C7)/Income_Statement!C7 -> 0.13 | E18: =(Income_Statement!E7-Income_Statement!D7)/Income_Statement!D7 -> 0.145 | F18: =(Income_Statement!F7-Income_Statement!E7)/Income_Statement!E7 -> 0.12 | G18: =(Income_Statement!G7-Income_Statement!F7)/Income_Statement!F7 -> 0.1 | H18: =(Income_Statement!H7-Income_Statement!G7)/Income_Statement!G7 -> 0.08 | I18: =(Income_Statement!I7-Income_Statement!H7)/Income_Statement!H7 -> 0.07 | J18: =(Income_Statement!J7-Income_Statement!I7)/Income_Statement!I7 -> 0.06 | K18: =(Income_Statement!K7-Income_Statement!J7)/Income_Statement!J7 -> 0.06
B19: Expected Growth % | C19: 0 | D19: {=Cover_Assumptions!D11} -> 0.13 | E19: {=Cover_Assumptions!E11} -> 0.145 | F19: {=Cover_Assumptions!F11} -> 0.12 | G19: {=Cover_Assumptions!G11} -> 0.1 | H19: {=Cover_Assumptions!H11} -> 0.08 | I19: {=Cover_Assumptions!I11} -> 0.07 | J19: {=Cover_Assumptions!J11} -> 0.06 | K19: {=Cover_Assumptions!K11} -> 0.06
B20: Status | C20: PASS | D20: =IF(ABS(D18-D19)<0.001,"PASS","CHECK") -> PASS | E20: =IF(ABS(E18-E19)<0.001,"PASS","CHECK") -> PASS | F20: =IF(ABS(F18-F19)<0.001,"PASS","CHECK") -> PASS | G20: =IF(ABS(G18-G19)<0.001,"PASS","CHECK") -> PASS | H20: =IF(ABS(H18-H19)<0.001,"PASS","CHECK") -> PASS | I20: =IF(ABS(I18-I19)<0.001,"PASS","CHECK") -> PASS | J20: =IF(ABS(J18-J19)<0.001,"PASS","CHECK") -> PASS | K20: =IF(ABS(K18-K19)<0.001,"PASS","CHECK") -> PASS
B22: 4. GROSS MARGIN CHECK
B23: Gross Margin % | C23: {=Income_Statement!C11} -> 0.25 | D23: {=Income_Statement!D11} -> 0.26 | E23: {=Income_Statement!E11} -> 0.27 | F23: {=Income_Statement!F11} -> 0.275 | G23: {=Income_Statement!G11} -> 0.28 | H23: {=Income_Statement!H11} -> 0.285 | I23: {=Income_Statement!I11} -> 0.29 | J23: {=Income_Statement!J11} -> 0.295 | K23: {=Income_Statement!K11} -> 0.3
B24: Expected Margin % | C24: {=Cover_Assumptions!C14} -> 0.25 | D24: {=Cover_Assumptions!D14} -> 0.26 | E24: {=Cover_Assumptions!E14} -> 0.27 | F24: {=Cover_Assumptions!F14} -> 0.275 | G24: {=Cover_Assumptions!G14} -> 0.28 | H24: {=Cover_Assumptions!H14} -> 0.285 | I24: {=Cover_Assumptions!I14} -> 0.29 | J24: {=Cover_Assumptions!J14} -> 0.295 | K24: {=Cover_Assumptions!K14} -> 0.3
B25: Status | C25: =IF(ABS(C23-C24)<0.001,"PASS","CHECK") -> PASS | D25: =IF(ABS(D23-D24)<0.001,"PASS","CHECK") -> PASS | E25: =IF(ABS(E23-E24)<0.001,"PASS","CHECK") -> PASS | F25: =IF(ABS(F23-F24)<0.001,"PASS","CHECK") -> PASS | G25: =IF(ABS(G23-G24)<0.001,"PASS","CHECK") -> PASS | H25: =IF(ABS(H23-H24)<0.001,"PASS","CHECK") -> PASS | I25: =IF(ABS(I23-I24)<0.001,"PASS","CHECK") -> PASS | J25: =IF(ABS(J23-J24)<0.001,"PASS","CHECK") -> PASS | K25: =IF(ABS(K23-K24)<0.001,"PASS","CHECK") -> PASS
B27: OVERALL MODEL STATUS | C27: =IF(COUNTIF(C9:K9,"FAIL")+COUNTIF(C15:K15,"FAIL")=0,"MODEL BALANCED","ERRORS DETECTED") -> ERRORS DETECTED
